Workbook

Sheet Fluxos Monetários
A1: (1) a matriz de fluxos em valores monetários Z, com os setores de valor adicionado e a demanda final;
A3: Valores correntes em 1 000 000 R$ | D3: S01 | E3: S02 | F3: S03 | G3: S04 | H3: S05 | I3: S06 | J3: S07 | K3: S08 | L3: S09 | M3: S10 | N3: S11 | O3: S12 | P3: S13 | Q3: S14 | R3: S15 | S3: S16 | T3: S17 | U3: S18 | V3: S19 | W3: S20 | X3: S21 | Y3: S22 | Z3: S23 | AA3: S24 | AB3: S25 | AC3: S26 | AD3: S27 | AE3: S28 | AF3: S29 | AG3: S30 | AH3: S31 | AI3: S32 | AJ3: S33 | AK3: S34 | AL3: S35 | AM3: S36 | AN3: S37 | AO3: S38 | AP3: S39 | AQ3: S40 | AR3: S41 | AS3: S42 | AT3: S43 | AU3: S44 | AV3: S45 | AW3: S46 | AX3: S47 | AY3: S48 | AZ3: S49 | BA3: S50 | BB3: S51 | BC3: S52 | BD3: S53 | BE3: S54 | BF3: S55 | BG3: S56 | BH3: S57 | BI3: S58 | BJ3: S59 | BK3: S60 | BL3: S61 | BM3: S62 | BN3: S63 | BO3: S64 | BP3: S65 | BQ3: S66 | BR3: S67 | BS3: S68 | BT3: S69 | BU3: S70 | BV3: S71 | BW3: S72 | BX3: S73
A4: Matriz de usos setor x setor | D4: Agricultura, inclusive o apoio à agricultura e a pós-colheita | E4: Pecuária, inclusive o apoio à pecuária | F4: Produção florestal; pesca e aquicultura | G4: Extração de carvão mineral e de minerais não-metálicos | H4: Extração de petróleo e gás, inclusive as atividades de apoio | I4: Extração de minério de ferro, inclusive beneficiamentos e a aglomeração | J4: Extração de minerais metálicos não-ferrosos, inclusive beneficiamentos | K4: Abate e produtos de carne, inclusive os produtos do laticínio e da pesca | L4: Fabricação e refino de açúcar | M4: Outros produtos alimentares | N4: Fabricação de bebidas | O4: Fabricação de produtos do fumo | P4: Fabricação de produtos têxteis | Q4: Confecção de artefatos do vestuário e acessórios | R4: Fabricação de calçados e de artefatos de couro | S4: Fabricação de produtos da madeira | T4: Fabricação de celulose, papel e produtos de papel | U4: Impressão e reprodução de gravações | V4: Derivados de petróleo | W4: Biodiesel | X4: Coquerias | Y4: Fabricação de biocombustíveis | Z4: Fabricação de químicos orgânicos e inorgânicos, resinas e elastômeros | AA4: Fabricação de defensivos, desinfestantes, tintas e químicos diversos | AB4: Fabricação de produtos de limpeza, cosméticos/perfumaria e higiene pessoal | AC4: Fabricação de produtos farmoquímicos e farmacêuticos | AD4: Fabricação de produtos de borracha e de material plástico | AE4: Fabricação de produtos de minerais não-metálicos | AF4: Produção de ferro-gusa/ferroligas, siderurgia e tubos de aço sem costura | AG4: Metalurgia de metais não-ferosos e a fundição de metais | AH4: Fabricação de produtos de metal, exceto máquinas e equipamentos | AI4: Fabricação de equipamentos de informática, produtos eletrônicos e ópticos | AJ4: Fabricação de máquinas e equipamentos elétricos | AK4: Fabricação de máquinas e equipamentos mecânicos | AL4: Fabricação de automóveis, caminhões e ônibus, exceto peças | AM4: Fabricação de peças e acessórios para veículos automotores | AN4: Fabricação de outros equipamentos de transporte, exceto veículos automotores | AO4: Fabricação de móveis e de produtos de indústrias diversas | AP4: Manutenção, reparação e instalação de máquinas e equipamentos | AQ4: Geração centralizada de energia elétrica | AR4: Geração distribuída de energia elétrica | AS4: Transmissão | AT4: Gás Natural | AU4: Água, esgoto e gestão de resíduos | AV4: Construção | AW4: Comércio e reparação de veículos automotores e motocicletas | AX4: Comércio por atacado e a varejo, exceto veículos automotores | AY4: Transporte terrestre | AZ4: Transporte aquaviário | BA4: Transporte aéreo | BB4: Armazenamento, atividades auxiliares dos transportes e correio | BC4: Alojamento | BD4: Alimentação | BE4: Edição e edição integrada à impressão | BF4: Atividades de televisão, rádio, cinema e gravação/edição de som e imagem | BG4: Telecomunicações | BH4: Desenvolvimento de sistemas e outros serviços de informação | BI4: Intermediação financeira, seguros e previdência complementar | BJ4: Atividades imobiliárias | BK4: Atividades jurídicas, contábeis, consultoria e sedes de empresas | BL4: Serviços de arquitetura, engenharia, testes/análises técnicas e P & D | BM4: Outras atividades profissionais, científicas e técnicas | BN4: Aluguéis não-imobiliários e gestão de ativos de propriedade intelectual | BO4: Outras atividades administrativas e serviços complementares | BP4: Atividades de vigilância, segurança e investigação | BQ4: Administração pública, defesa e seguridade social | BR4: Educação pública | BS4: Educação privada | BT4: Saúde pública | BU4: Saúde privada | BV4: Atividades artísticas, criativas e de espetáculos | BW4: Organizações associativas e outros serviços pessoais | BX4: Serviços domésticos | BY4: Consumo Intermediário total | BZ4: Exportação de bens e serviços | CA4: Consumo do governo | CB4: Consumo das ISFLSF | CC4: Consumo das famílias | CD4: Formação bruta de capital fixo | CE4: Variação de estoque | CF4: Demanda final | CG4: Demanda total | CI4: Proporção Demanda Final / Demanda total
B5: Número identificador | C5: 0 | D5: 1 | E5: 2 | F5: 3 | G5: 4 | H5: 5 | I5: 6 | J5: 7 | K5: 8 | L5: 9 | M5: 10 | N5: 11 | O5: 12 | P5: 13 | Q5: 14 | R5: 15 | S5: 16 | T5: 17 | U5: 18 | V5: 19 | W5: 20 | X5: 21 | Y5: 22 | Z5: 23 | AA5: 24 | AB5: 25 | AC5: 26 | AD5: 27 | AE5: 28 | AF5: 29 | AG5: 30 | AH5: 31 | AI5: 32 | AJ5: 33 | AK5: 34 | AL5: 35 | AM5: 36 | AN5: 37 | AO5: 38 | AP5: 39 | AQ5: 40 | AR5: 41 | AS5: 42 | AT5: 43 | AU5: 44 | AV5: 45 | AW5: 46 | AX5: 47 | AY5: 48 | AZ5: 49 | BA5: 50 | BB5: 51 | BC5: 52 | BD5: 53 | BE5: 54 | BF5: 55 | BG5: 56 | BH5: 57 | BI5: 58 | BJ5: 59 | BK5: 60 | BL5: 61 | BM5: 62 | BN5: 63 | BO5: 64 | BP5: 65 | BQ5: 66 | BR5: 67 | BS5: 68 | BT5: 69 | BU5: 70 | BV5: 71 | BW5: 72 | BX5: 73 | BY5: 74 | BZ5: 75 | CA5: 76 | CB5: 77 | CC5: 78 | CD5: 79 | CE5: 80 | CF5: 81 | CG5: 82
A6: S01 | B6: Agricultura, inclusive o apoio à agricultura e a pós-colheita | C6: 1 | D6: 8170.3586 | E6: 5290.2246 | F6: 156.75542 | G6: 1.8265937 | H6: 9.8692679 | I6: 1.1434984 | J6: 1.7841451 | K6: 7264.3074 | L6: 28021.78 | M6: 76458.432 | N6: 2089.3011 | O6: 4889.0335 | P6: 5526.2619 | Q6: 518.70182 | R6: 6.6028531 | S6: 90.994169 | T6: 172.72948 | U6: 0.25638423 | V6: 8.6760449 | W6: 0.051985351 | X6: 0.041880586 | Y6: 22484.79 | Z6: 15.129223 | AA6: 18.049511 | AB6: 2.2091675 | AC6: 13.484794 | AD6: 38.146982 | AE6: 14.418004 | AF6: 42.241869 | AG6: 26.216602 | AH6: 2.7665426 | AI6: 0.27528051 | AJ6: 0.30007581 | AK6: 0.76078595 | AL6: 0.62121565 | AM6: 0.40229091 | AN6: 0.52416479 | AO6: 10.45024 | AP6: 0.065167124 | AQ6: 0.47598929 | AR6: 0.077753282 | AS6: 0.055707325 | AT6: 0.062671933 | AU6: 28.709259 | AV6: 402.52785 | AW6: 2.6558165 | AX6: 12090.688 | AY6: 0.96387781 | AZ6: 0.028456625 | BA6: 0.29297865 | BB6: 12.456639 | BC6: 277.13534 | BD6: 4385.9634 | BE6: 0.088943908 | BF6: 0.61952657 | BG6: 44.855835 | BH6: 2.1532612 | BI6: 14.762971 | BJ6: 20.40651 | BK6: 7.4743084 | BL6: 12.024632 | BM6: 0.80278958 | BN6: 0.68757086 | BO6: 133.6114 | BP6: 0.22205855 | BQ6: 947.57032 | BR6: 357.35736 | BS6: 43.808221 | BT6: 354.48805 | BU6: 180.63426 | BV6: 2.8571215 | BW6: 249.91177 | BX6: 0 | BY6: 180926.42 | BZ6: 150718.72 | CA6: 48.304678 | CB6: 0 | CC6: 71191.699 | CD6: 3188.2578 | CE6: -8036.3973 | CF6: 217110.58 | CG6: 398037 | CI6: =CF6/CG6 -> 0.54545327
A7: S02 | B7: Pecuária, inclusive o apoio à pecuária | C7: 2 | D7: 1004.9599 | E7: 6106.8111 | F7: 183.36264 | G7: 3.7251917 | H7: 22.939 | I7: 1.9494384 | J7: 3.2441343 | K7: 84046.279 | L7: 152.99908 | M7: 4376.6755 | N7: 64.457872 | O7: 192.81143 | P7: 250.2414 | Q7: 190.38282 | R7: 6.6377087 | S7: 143.03866 | T7: 239.09947 | U7: 0.46679488 | V7: 0.72657442 | W7: 0.018633166 | X7: 0.0001190597 | Y7: 178.77565 | Z7: 46.126672 | AA7: 7.8961205 | AB7: 5.0532195 | AC7: 5.4165196 | AD7: 52.888428 | AE7: 56.619524 | AF7: 70.6231 | AG7: 49.444454 | AH7: 2.5281526 | AI7: 0.71683903 | AJ7: 0.95724033 | AK7: 1.7317397 | AL7: 1.242744 | AM7: 0.99247143 | AN7: 0.87514563 | AO7: 7.2734053 | AP7: 0.23085892 | AQ7: 0.79136222 | AR7: 0.12926974 | AS7: 0.092616943 | AT7: 0.16790002 | AU7: 5.6993907 | AV7: 751.8631 | AW7: 3.5113748 | AX7: 386.78199 | AY7: 1.0736839 | AZ7: 0.037829304 | BA7: 0.34145151 | BB7: 22.136468 | BC7: 331.24359 | BD7: 1919.459 | BE7: 0.21618546 | BF7: 1.1913409 | BG7: 80.686603 | BH7: 4.2899018 | BI7: 25.488379 | BJ7: 38.429739 | BK7: 6.829628 | BL7: 14.52577 | BM7: 6.4682792 | BN7: 1.1312263 | BO7: 36.689298 | BP7: 0.34850966 | BQ7: 301.70844 | BR7: 120.20425 | BS7: 17.204426 | BT7: 110.89112 | BU7: 110.42372 | BV7: 3.3228892 | BW7: 37.971527 | BX7: 0 | BY7: 101821.57 | BZ7: 7635.5157 | CA7: 3.1875319 | CB7: 0 | CC7: 27053.775 | CD7: 16625.08 | CE7: -1180.1272 | CF7: 50137.431 | CG7: 151959 | CI7: =CF7/CG7 -> 0.32994052
A8: S03 | B8: Produção florestal; pesca e aquicultura | C8: 3 | D8: 1414.9162 | E8: 1437.2819 | F8: 2063.4117 | G8: 1.7907537 | H8: 1.8236877 | I8: 0.17010573 | J8: 0.24112751 | K8: 1830.067 | L8: 0.62916373 | M8: 261.16769 | N8: 13.874288 | O8: 13.085165 | P8: 25.024372 | Q8: 8.2471144 | R8: 6.78895 | S8: 1995.4595 | T8: 3242.7461 | U8: 0.035396002 | V8: 0.056630047 | W8: 0.0014522904 | X8: 9.2796503e-06 | Y8: 3.6633906 | Z8: 162.13204 | AA8: 2.8177035 | AB8: 0.084317617 | AC8: 0.12671282 | AD8: 713.86171 | AE8: 59.563969 | AF8: 910.44283 | AG8: 3.7053405 | AH8: 5.5140517 | AI8: 0.069501986 | AJ8: 0.088522362 | AK8: 0.17941951 | AL8: 0.11471484 | AM8: 0.093657764 | AN8: 0.076952408 | AO8: 2.773387 | AP8: 0.02522399 | AQ8: 0.094589682 | AR8: 0.015451311 | AS8: 0.011070287 | AT8: 0.019459657 | AU8: 0.4257136 | AV8: 759.42361 | AW8: 0.27333371 | AX8: 161.92523 | AY8: 0.099740228 | AZ8: 0.0030144069 | BA8: 0.027363157 | BB8: 1.6585272 | BC8: 42.674553 | BD8: 549.53668 | BE8: 0.021951251 | BF8: 0.10959413 | BG8: 5.9766224 | BH8: 0.36575555 | BI8: 1.9402982 | BJ8: 2.9162219 | BK8: 0.52073673 | BL8: 3.7816158 | BM8: 0.083967239 | BN8: 0.095237422 | BO8: 2.6303824 | BP8: 0.029566698 | BQ8: 91.342914 | BR8: 66.866054 | BS8: 8.8889308 | BT8: 63.403735 | BU8: 19.813852 | BV8: 0.24397311 | BW8: 2.9434756 | BX8: 0 | BY8: 15970.315 | BZ8: 3068.1586 | CA8: 2.4427056 | CB8: 0 | CC8: 17611.77 | CD8: 1054.003 | CE8: 163.3106 | CF8: 21899.685 | CG8: 37870 | CI8: =CF8/CG8 -> 0.57828585
A9: S04 | B9: Extração de carvão mineral e de minerais não-metálicos | C9: 4 | D9: 154.57131 | E9: 418.65628 | F9: 13.284636 | G9: 255.38746 | H9: 731.23872 | I9: 0.30874708 | J9: 1.3587158 | K9: 53.244166 | L9: 8.1587147 | M9: 279.65589 | N9: 16.421368 | O9: 0.065622521 | P9: 0.97438319 | Q9: 0.29823967 | R9: 0.94713613 | S9: 0.22325809 | T9: 18.581952 | U9: 0.14003746 | V9: 6.1948655 | W9: 0.1589928 | X9: 0.0058538919 | Y9: 219.10581 | Z9: 2854.8663 | AA9: 68.702101 | AB9: 8.0050703 | AC9: 1.8960083 | AD9: 6.7281211 | AE9: 4463.2487 | AF9: 1496.018 | AG9: 337.50822 | AH9: 3.5700793 | AI9: 0.34796092 | AJ9: 35.919486 | AK9: 2.5200509 | AL9: 18.623404 | AM9: 34.401273 | AN9: 1.7813222 | AO9: 31.983519 | AP9: 2.7992514 | AQ9: 235.19416 | AR9: 5.7714331 | AS9: 1.184596 | AT9: 1.2563515 | AU9: 356.51608 | AV9: 5769.238 | AW9: 2.9175716 | AX9: 79.436083 | AY9: 0.65802409 | AZ9: 0.02811291 | BA9: 0.057457623 | BB9: 4.3639196 | BC9: 2.4382302 | BD9: 15.584106 | BE9: 0.087448574 | BF9: 0.1645093 | BG9: 0.76492018 | BH9: 0.61648428 | BI9: 1.6296091 | BJ9: 369.75982 | BK9: 1.5956916 | BL9: 1.1474393 | BM9: 0.42774142 | BN9: 0.35090323 | BO9: 2.106388 | BP9: 0.086702237 | BQ9: 71.223802 | BR9: 16.960069 | BS9: 1.5619518 | BT9: 6.8222989 | BU9: 5.5002185 | BV9: 1.1191405 | BW9: 4.310632 | BX9: 0 | BY9: 18508.781 | BZ9: 1808.1263 | CA9: 0.074826886 | CB9: 0 | CC9: 199.54565 | CD9: 9.7663346 | CE9: -515.2941 | CF9: 1502.2191 | CG9: 20011 | CI9: =CF9/CG9 -> 0.075069665
A10: S05 | B10: Extração de petróleo e gás, inclusive as atividades de apoio | C10: 5 | D10: 21.840529 | E10: 15.400401 | F10: 0.88883243 | G10: 2.8557716 | H10: 6630.1612 | I10: 276.15336 | J10: 28.805251 | K10: 63.705839 | L10: 0.44529788 | M10: 591.27168 | N10: 106.02011 | O10: 0.12079151 | P10: 91.397968 | Q10: 0.98598288 | R10: 1.5852201 | S10: 39.944558 | T10: 541.2167 | U10: 0.14283782 | V10: 106597.07 | W10: 2746.8599 | X10: 590.10146 | Y10: 1.2543756 | Z10: 1369.8245 | AA10: 67.887327 | AB10: 24.388558 | AC10: 28.616612 | AD10: 80.815094 | AE10: 444.90473 | AF10: 358.13112 | AG10: 243.1048 | AH10: 282.1276 | AI10: 1.128992 | AJ10: 26.624933 | AK10: 19.396171 | AL10: 62.055893 | AM10: 126.58879 | AN10: 1.6722904 | AO10: 2.9946627 | AP10: 6.2288933 | AQ10: 3962.6267 | AR10: 1.0026425 | AS10: 0.71835594 | AT10: 5204.7213 | AU10: 522.87686 | AV10: 571.58375 | AW10: 9.6259108 | AX10: 157.08909 | AY10: 72.420509 | AZ10: 0.79119726 | BA10: 0.27180433 | BB10: 47.629023 | BC10: 3.4384093 | BD10: 49.277023 | BE10: 0.46020694 | BF10: 1.2321138 | BG10: 87.263751 | BH10: 4.8051068 | BI10: 13.428733 | BJ10: 6.8459631 | BK10: 13.309644 | BL10: 55.849417 | BM10: 3.1144653 | BN10: 5.7667873 | BO10: 9.2018492 | BP10: 0.72124886 | BQ10: 1045.7362 | BR10: 8.0402548 | BS10: 12.284845 | BT10: 1.4955079 | BU10: 7.5123371 | BV10: 9.5743714 | BW10: 21.701482 | BX10: 0 | BY10: 133407.14 | BZ10: 92727.09 | CA10: 0 | CB10: 0 | CC10: 602.27835 | CD10: 11369.449 | CE10: -12167.956 | CF10: 92530.862 | CG10: 225938 | CI10: =CF10/CG10 -> 0.40954095
A11: S06 | B11: Extração de minério de ferro, inclusive beneficiamentos e a aglomeração | C11: 6 | D11: 0.13674266 | E11: 0.077076579 | F11: 0.0079907095 | G11: 0.02196498 | H11: 2.3512303 | I11: 1793.5447 | J11: 45.052166 | K11: 0.48557035 | L11: 0.032457224 | M11: 0.34478482 | N11: 0.27770406 | O11: 0.063359672 | P11: 0.043394837 | Q11: 0.095809719 | R11: 0.10896933 | S11: 0.074421837 | T11: 0.14841067 | U11: 0.014610975 | V11: 0.14103175 | W11: 0.0036167913 | X11: 2.3110087e-05 | Y11: 0.017588449 | Z11: 0.34414227 | AA11: 0.11931618 | AB11: 0.21383963 | AC11: 0.70292247 | AD11: 0.20161083 | AE11: 106.29352 | AF11: 16914.009 | AG11: 123.08645 | AH11: 0.096515193 | AI11: 0.2311134 | AJ11: 0.55081086 | AK11: 4.5165857 | AL11: 1.1407709 | AM11: 0.66480908 | AN11: 0.23246828 | AO11: 0.11436779 | AP11: 2.6358292 | AQ11: 0.28979805 | AR11: 0.047338775 | AS11: 0.033916466 | AT11: 0.019881708 | AU11: 0.072340698 | AV11: 1.2898289 | AW11: 0.20090651 | AX11: 1.8876588 | AY11: 0.11844738 | AZ11: 0.04249387 | BA11: 0.0099650457 | BB11: 0.14510725 | BC11: 0.043813445 | BD11: 0.31459912 | BE11: 0.020385269 | BF11: 0.020853743 | BG11: 0.29065394 | BH11: 0.36060677 | BI11: 0.19109174 | BJ11: 0.07465067 | BK11: 0.16290206 | BL11: 6.5571966 | BM11: 0.053040758 | BN11: 0.12392835 | BO11: 0.64194197 | BP11: 0.010178673 | BQ11: 0.14299228 | BR11: 0.052338503 | BS11: 0.14785893 | BT11: 0.091322143 | BU11: 0.22754425 | BV11: 0.11034237 | BW11: 0.13327856 | BX11: 0 | BY11: 19012.127 | BZ11: 65510.697 | CA11: 0.014070934 | CB11: 0 | CC11: 7.116125 | CD11: 145.98411 | CE11: 7650.0619 | CF11: 73313.873 | CG11: 92326 | CI11: =CF11/CG11 -> 0.79407613
A12: S07 | B12: Extração de minerais metálicos não-ferrosos, inclusive beneficiamentos | C12: 7 | D12: 4.6695015 | E12: 2.628304 | F12: 0.12435658 | G12: 1.2402923 | H12: 68.177003 | I12: 10.656378 | J12: 810.56588 | K12: 6.0089169 | L12: 0.15093813 | M12: 12.972218 | N12: 1.4659626 | O12: 0.0030025647 | P12: 0.16470019 | Q12: 0.037493815 | R12: 0.28587826 | S12: 0.12078567 | T12: 5.8959539 | U12: 3.4978879 | V12: 0.045892973 | W12: 0.0011822536 | X12: 0.00021491581 | Y12: 0.99308581 | Z12: 30.317773 | AA12: 5.272019 | AB12: 1.7076522 | AC12: 0.54015883 | AD12: 7.8003983 | AE12: 52.370365 | AF12: 1602.2277 | AG12: 5411.8108 | AH12: 31.658929 | AI12: 2.4799909 | AJ12: 79.4302 | AK12: 12.403471 | AL12: 8.4362246 | AM12: 49.252453 | AN12: 12.92217 | AO12: 30.016131 | AP12: 5.5688269 | AQ12: 0.38191835 | AR12: 0.06238671 | AS12: 0.044697749 | AT12: 0.002747953 | AU12: 3.6386314 | AV12: 59.821666 | AW12: 0.56351331 | AX12: 3.5850876 | AY12: 0.16152433 | AZ12: 0 | BA12: 0.0036377033 | BB12: 0.073311621 | BC12: 0.0046298042 | BD12: 0.25629273 | BE12: 0.00037532059 | BF12: 0 | BG12: 0.012010259 | BH12: 0.01938281 | BI12: 0.015203035 | BJ12: 2.0032489 | BK12: 0.23876561 | BL12: 0.70972307 | BM12: 0.0016222907 | BN12: 0.0054421485 | BO12: 0.26001967 | BP12: 0 | BQ12: 0.51230206 | BR12: 0.19266821 | BS12: 0.00018766029 | BT12: 0.41110175 | BU12: 0.71872299 | BV12: 0 | BW12: 0.38814583 | BX12: 0 | BY12: 8348.0101 | BZ12: 11140.001 | CA12: 0 | CB12: 0 | CC12: 7.4490404 | CD12: 8.4306387 | CE12: -1230.8903 | CF12: 9924.9899 | CG12: 18273 | CI12: =CF12/CG12 -> 0.54315054
A13: S08 | B13: Abate e produtos de carne, inclusive os produtos do laticínio e da pesca | C13: 8 | D13: 73.15487 | E13: 2090.4666 | F13: 38.303224 | G13: 9.9476144 | H13: 19.441015 | I13: 17.034337 | J13: 3.2840564 | K13: 22154.159 | L13: 1.0823479 | M13: 2486.5336 | N13: 47.126808 | O13: 2.4639672 | P13: 7.0604126 | Q13: 8.6616937 | R13: 1473.7109 | S13: 5.5399254 | T13: 15.727026 | U13: 3.1952587 | V13: 23.045817 | W13: 0.59120438 | X13: 0.011154334 | Y13: 737.52755 | Z13: 29.649497 | AA13: 44.063117 | AB13: 1728.7212 | AC13: 13.395568 | AD13: 28.418666 | AE13: 9.9546155 | AF13: 10.274331 | AG13: 5.788068 | AH13: 65.983484 | AI13: 13.052513 | AJ13: 11.427341 | AK13: 65.885116 | AL13: 13.947594 | AM13: 8.0334682 | AN13: 3.9970415 | AO13: 12.233521 | AP13: 40.666301 | AQ13: 4.9078319 | AR13: 0.80169879 | AS13: 0.57438727 | AT13: 0.39508868 | AU13: 3.2880463 | AV13: 58.979781 | AW13: 7.2079814 | AX13: 448.87841 | AY13: 13.177598 | AZ13: 0.87761198 | BA13: 1.2127732 | BB13: 4.6743079 | BC13: 445.42571 | BD13: 17469.215 | BE13: 1.6282579 | BF13: 1.6628426 | BG13: 6.3279886 | BH13: 4.661158 | BI13: 8.4847063 | BJ13: 4.2251629 | BK13: 7.7048874 | BL13: 6.6234746 | BM13: 5.7445294 | BN13: 2.4002707 | BO13: 15.891834 | BP13: 0.73876873 | BQ13: 2176.6448 | BR13: 1294.0752 | BS13: 207.92015 | BT13: 1280.2889 | BU13: 750.19255 | BV13: 7.872699 | BW13: 194.08998 | BX13: 0 | BY13: 55760.354 | BZ13: 46170.634 | CA13: 72.403107 | CB13: 0 | CC13: 189902.01 | CD13: 408.57985 | CE13: 92.022182 | CF13: 236645.65 | CG13: 292406 | CI13: =CF13/CG13 -> 0.80930503
A14: S09 | B14: Fabricação e refino de açúcar | C14: 9 | D14: 53.525246 | E14: 87.091629 | F14: 2.3933686 | G14: 1.6267936 | H14: 330.37378 | I14: 22.21335 | J14: 3.8758144 | K14: 291.48502 | L14: 755.07055 | M14: 3193.1451 | N14: 671.87757 | O14: 0.80970769 | P14: 2.0182717 | Q14: 2.6748804 | R14: 2.0719631 | S14: 14.517455 | T14: 5.707496 | U14: 0.69458071 | V14: 7507.7582 | W14: 38.065829 | X14: 37.884553 | Y14: 641.94531 | Z14: 141.83333 | AA14: 414.07002 | AB14: 612.65487 | AC14: 355.93829 | AD14: 4.1415098 | AE14: 3.0130159 | AF14: 3.8189358 | AG14: 2.182539 | AH14: 17.070744 | AI14: 4.3963944 | AJ14: 6.2673357 | AK14: 94.892959 | AL14: 16.375697 | AM14: 2.8484954 | AN14: 3.8857596 | AO14: 3.4125174 | AP14: 59.620441 | AQ14: 4.5778112 | AR14: 0.74778963 | AS14: 0.53576336 | AT14: 0.18604367 | AU14: 10.534485 | AV14: 172.49428 | AW14: 139.72003 | AX14: 273.44868 | AY14: 351.88253 | AZ14: 3.0478343 | BA14: 9.5131123 | BB14: 24.925262 | BC14: 7.1586323 | BD14: 795.99698 | BE14: 2.2736976 | BF14: 4.3632644 | BG14: 12.172919 | BH14: 17.104176 | BI14: 62.695757 | BJ14: 8.9417937 | BK14: 62.340633 | BL14: 49.822366 | BM14: 19.535258 | BN14: 47.389975 | BO14: 66.916953 | BP14: 31.905779 | BQ14: 347.6269 | BR14: 93.441802 | BS14: 10.050684 | BT14: 71.418105 | BU14: 65.577576 | BV14: 9.0821778 | BW14: 75.349417 | BX14: 0 | BY14: 18266.028 | BZ14: 16586.094 | CA14: 0.75832747 | CB14: 0 | CC14: 16804.06 | CD14: 332.2654 | CE14: -434.20561 | CF14: 33288.972 | CG14: 51555 | CI14: =CF14/CG14 -> 0.64569823
A15: S10 | B15: Outros produtos alimentares | C15: 10 | D15: 1901.0055 | E15: 13289.225 | F15: 896.41033 | G15: 153.2433 | H15: 190.88615 | I15: 51.948534 | J15: 15.388239 | K15: 23451.189 | L15: 23.73499 | M15: 28439.3 | N15: 2077.0625 | O15: 14.848455 | P15: 56.298103 | Q15: 48.649656 | R15: 64.823663 | S15: 57.154409 | T15: 656.92772 | U15: 23.74503 | V15: 2090.5259 | W15: 13.734147 | X15: 9.9100746 | Y15: 3052.5007 | Z15: 488.08572 | AA15: 802.79043 | AB15: 1071.7383 | AC15: 229.29723 | AD15: 175.308 | AE15: 93.455962 | AF15: 91.502096 | AG15: 40.730426 | AH15: 88.811443 | AI15: 75.800275 | AJ15: 60.469387 | AK15: 109.61639 | AL15: 56.823494 | AM15: 43.043403 | AN15: 18.514591 | AO15: 81.249431 | AP15: 72.461506 | AQ15: 32.640495 | AR15: 5.3318544 | AS15: 3.8200747 | AT15: 1.9974554 | AU15: 32.438763 | AV15: 362.30878 | AW15: 131.80172 | AX15: 3488.1786 | AY15: 177.61548 | AZ15: 2.5711517 | BA15: 31.863844 | BB15: 38.202178 | BC15: 243.18735 | BD15: 12354.485 | BE15: 10.176693 | BF15: 10.564222 | BG15: 46.146675 | BH15: 27.97588 | BI15: 179.04353 | BJ15: 39.398785 | BK15: 74.566393 | BL15: 36.341617 | BM15: 66.42593 | BN15: 23.287125 | BO15: 77.880838 | BP15: 12.251409 | BQ15: 1527.907 | BR15: 1168.2631 | BS15: 166.10331 | BT15: 1598.3147 | BU15: 711.43383 | BV15: 52.378456 | BW15: 738.0151 | BX15: 0 | BY15: 103651.13 | BZ15: 40248.49 | CA15: 79.511138 | CB15: 0 | CC15: 177717.31 | CD15: 617.39769 | CE15: 2629.1666 | CF15: 221291.87 | CG15: 324943 | CI15: =CF15/CG15 -> 0.68101751
A16: S11 | B16: Fabricação de bebidas | C16: 11 | D16: 14.73899 | E16: 9.3559629 | F16: 0.76997094 | G16: 5.2965241 | H16: 13.258631 | I16: 7.7752004 | J16: 1.7552234 | K16: 397.9374 | L16: 1.2398412 | M16: 99.164789 | N16: 6639.8139 | O16: 1.607351 | P16: 4.5283349 | Q16: 5.5452055 | R16: 4.3324331 | S16: 4.1709141 | T16: 8.1110653 | U16: 1.6440958 | V16: 62.724309 | W16: 0.63813413 | X16: 0.24728806 | Y16: 3.2332953 | Z16: 10.807878 | AA16: 13.785349 | AB16: 11.285939 | AC16: 8.407027 | AD16: 10.372939 | AE16: 5.7335931 | AF16: 10.690565 | AG16: 3.6727054 | AH16: 20.532547 | AI16: 9.8421771 | AJ16: 9.681718 | AK16: 31.591531 | AL16: 12.546867 | AM16: 8.0829596 | AN16: 5.4079929 | AO16: 8.3460781 | AP16: 19.980903 | AQ16: 8.2460964 | AR16: 1.3470073 | AS16: 0.96508049 | AT16: 0.45259475 | AU16: 3.0293874 | AV16: 69.490475 | AW16: 10.121867 | AX16: 107.19138 | AY16: 17.00447 | AZ16: 0.45098489 | BA16: 8.1017402 | BB16: 6.2954672 | BC16: 450.04095 | BD16: 26011.353 | BE16: 1.2831512 | BF16: 1.6703356 | BG16: 6.6399483 | BH16: 5.1156866 | BI16: 98.337038 | BJ16: 6.2222205 | BK16: 12.41899 | BL16: 3.020191 | BM16: 4.3590942 | BN16: 2.9262015 | BO16: 13.385941 | BP16: 1.1279803 | BQ16: 100.9831 | BR16: 69.203497 | BS16: 17.627628 | BT16: 72.575288 | BU16: 174.85303 | BV16: 28.677202 | BW16: 19.690719 | BX16: 0 | BY16: 34822.866 | BZ16: 2978.2515 | CA16: 1.7119308 | CB16: 0 | CC16: 40937.66 | CD16: 99.164106 | CE16: -295.65319 | CF16: 43721.134 | CG16: 78544 | CI16: =CF16/CG16 -> 0.55664512
A17: S12 | B17: Fabricação de produtos do fumo | C17: 12 | D17: 1.8863692 | E17: 0.9809415 | F17: 0.089514122 | G17: 0.088027857 | H17: 2.1983798 | I17: 2.4823702 | J17: 0.38449654 | K17: 3.1242665 | L17: 0.08724313 | M17: 3.0183844 | N17: 0.69678189 | O17: 304.40931 | P17: 0.50326689 | Q17: 0.6927617 | R17: 0.57329707 | S17: 0.29665773 | T17: 0.77841528 | U17: 0.1475926 | V17: 1.9269422 | W17: 0.04941687 | X17: 0.00031575728 | Y17: 0.17235201 | Z17: 1.1070472 | AA17: 0.63432236 | AB17: 0.4849366 | AC17: 0.79277348 | AD17: 0.99845903 | AE17: 0.6455419 | AF17: 0.71252419 | AG17: 0.61963993 | AH17: 0.72265568 | AI17: 1.1712195 | AJ17: 1.1271924 | AK17: 9.9519577 | AL17: 1.7055668 | AM17: 0.71215732 | AN17: 0.50240734 | AO17: 0.67606475 | AP17: 6.042271 | AQ17: 0.46340185 | AR17: 0.075697113 | AS17: 0.054234156 | AT17: 0.031969707 | AU17: 0.18846967 | AV17: 5.1648107 | AW17: 0.45008789 | AX17: 3.6160293 | AY17: 1.1145936 | AZ17: 0.10844203 | BA17: 0.10146145 | BB17: 0.28571454 | BC17: 0.1431338 | BD17: 2.3330807 | BE17: 0.14060472 | BF17: 0.12207898 | BG17: 0.53625142 | BH17: 0.43983917 | BI17: 0.45998094 | BJ17: 0.24562702 | BK17: 0.37100818 | BL17: 1.3352302 | BM17: 0.34056163 | BN17: 0.16603915 | BO17: 1.6680395 | BP17: 0.047183572 | BQ17: 0.73080867 | BR17: 0.48670412 | BS17: 0.26664794 | BT17: 0.6912563 | BU17: 1.7783447 | BV17: 0.16768687 | BW17: 0.52694909 | BX17: 0 | BY17: 377.84581 | BZ17: 6460.6451 | CA17: 0.19900321 | CB17: 0 | CC17: 7980.5129 | CD17: 100.82736 | CE17: 773.96982 | CF17: 15316.154 | CG17: 15694 | CI17: =CF17/CG17 -> 0.97592419
... A78: S73 | B78: Serviços domésticos | C78: 73 | D78: 0 | E78: 0 | F78: 0 | G78: 0 | H78: 0 | I78: 0 | J78: 0 | K78: 0 | L78: 0 | M78: 0 | N78: 0 | O78: 0 | P78: 0 | Q78: 0 | R78: 0 | S78: 0 | T78: 0 | U78: 0 | V78: 0 | W78: 0 | X78: 0 | Y78: 0 | Z78: 0 | AA78: 0 | AB78: 0 | AC78: 0 | AD78: 0 | AE78: 0 | AF78: 0 | AG78: 0 | AH78: 0 | AI78: 0 | AJ78: 0 | AK78: 0 | AL78: 0 | AM78: 0 | AN78: 0 | AO78: 0 | AP78: 0 | AQ78: 0 | AR78: 0 | AS78: 0 | AT78: 0 | AU78: 0 | AV78: 0 | AW78: 0 | AX78: 0 | AY78: 0 | AZ78: 0 | BA78: 0 | BB78: 0 | BC78: 0 | BD78: 0 | BE78: 0 | BF78: 0 | BG78: 0 | BH78: 0 | BI78: 0 | BJ78: 0 | BK78: 0 | BL78: 0 | BM78: 0 | BN78: 0 | BO78: 0 | BP78: 0 | BQ78: 0 | BR78: 0 | BS78: 0 | BT78: 0 | BU78: 0 | BV78: 0 | BW78: 0 | BX78: 0 | BY78: 0 | BZ78: 0 | CA78: 0 | CB78: 0 | CC78: 74451 | CD78: 0 | CE78: 0 | CF78: 74451 | CG78: 74451 | CI78: =CF78/CG78 -> 1
B79: Prod Nac | C79: 74 | D79: 149151.39 | E79: 68079.254 | F79: 8177.4548 | G79: 9360.8652 | H79: 86780.302 | I79: 38249.787 | J79: 8861.9731 | K79: 226295.97 | L79: 40680.402 | M79: 229159.4 | N79: 47291.889 | O79: 10510.046 | P79: 30369.291 | Q79: 29704.034 | R79: 22278.689 | S79: 17495.769 | T79: 62825.276 | U79: 8728.225 | V79: 287013.67 | W79: 6884.7092 | X79: 3133.1479 | Y79: 39806.995 | Z79: 93685.49 | AA79: 50165.759 | AB79: 29616.109 | AC79: 32534.935 | AD79: 67095.931 | AE79: 47995.653 | AF79: 90011.633 | AG79: 42241.063 | AH79: 55292.639 | AI79: 48924.359 | AJ79: 43882.672 | AK79: 69100.829 | AL79: 125399.05 | AM79: 57957.342 | AN79: 14198.782 | AO79: 34015.197 | AP79: 34232.729 | AQ79: 127681.24 | AR79: 18161.429 | AS79: 4642.9823 | AT79: 13663.351 | AU79: 25919.117 | AV79: 258586.87 | AW79: 61466.17 | AX79: 379634.9 | AY79: =SUM(AY6:AY78) -> 203094.51 | AZ79: 10000.749 | BA79: 22005.894 | BB79: 50075.886 | BC79: 11174.565 | BD79: 120776.23 | BE79: 7719.1866 | BF79: 22366.727 | BG79: 80996.904 | BH79: 45349.946 | BI79: 196028.97 | BJ79: 44529.805 | BK79: 62859.567 | BL79: 18857.747 | BM79: 59576.858 | BN79: 14344.205 | BO79: 71519.591 | BP79: 6663.1352 | BQ79: 207583.76 | BR79: 47100.065 | BS79: 34108.375 | BT79: 55184.158 | BU79: 109176.75 | BV79: 14856.013 | BW79: 67590.784 | BX79: 0 | BY79: 4840485.2 | BZ79: 1025056 | CA79: 1393480 | CB79: 102253 | CC79: 3769922 | CD79: 878944.83 | CE79: -131 | CF79: 7169524.8 | CG79: 12010010
B80: Importado | C80: 75 | D80: 24183.129 | E80: 5755.6609 | F80: 537.51612 | G80: 1556.2578 | H80: 27867.644 | I80: 5714.0844 | J80: 1597.9782 | K80: 6328.4894 | L80: 797.17685 | M80: 16720.175 | N80: 3497.4522 | O80: 722.70448 | P80: 5295.776 | Q80: 4427.6391 | R80: 2917.4641 | S80: 1608.7089 | T80: 9260.3347 | U80: 1398.3211 | V80: 55572.301 | W80: 1426.2976 | X80: 53.305845 | Y80: 1431.7307 | Z80: 48562.221 | AA80: 17822.444 | AB80: 6237.9026 | AC80: 5422.9335 | AD80: 17408.563 | AE80: 6069.3113 | AF80: 19877.812 | AG80: 11436.201 | AH80: 8465.1792 | AI80: 30697.93 | AJ80: 11191.577 | AK80: 15905.433 | AL80: 26596.214 | AM80: 12200.315 | AN80: 14472.288 | AO80: 4902.2705 | AP80: 13043.475 | AQ80: 9178.8369 | AR80: 1499.3714 | AS80: 1074.2436 | AT80: 1248.4881 | AU80: 3312.4579 | AV80: 25282.9 | AW80: 9933.6931 | AX80: 25771.75 | AY80: 14216.85 | AZ80: 1813.1869 | BA80: 6864.6108 | BB80: 5592.0703 | BC80: 580.0006 | BD80: 7774.4096 | BE80: 867.59187 | BF80: 2456.9546 | BG80: 6453.1873 | BH80: 7361.4426 | BI80: 10937.472 | BJ80: 2406.1138 | BK80: 3950.1054 | BL80: 3129.4021 | BM80: 2737.6559 | BN80: 2492.8391 | BO80: 5948.6571 | BP80: 637.79733 | BQ80: 14920.461 | BR80: 4536.5689 | BS80: 3659.9193 | BT80: 7433.0689 | BU80: 11490.934 | BV80: 1279.3587 | BW80: 10473.725 | BX80: 0 | BY80: 666298.34 | BZ80: 0 | CA80: 0 | CB80: 0 | CC80: 223389.89 | CD80: 107785.77 | CE80: 0 | CF80: 331175.66 | CG80: 997474
B81: Imp Import | C81: 76 | D81: 712.48471 | E81: 199.5759 | F81: 13.047764 | G81: 76.297227 | H81: 466.80115 | I81: 239.77884 | J81: 45.092211 | K81: 238.16234 | L81: 10.760873 | M81: 528.53165 | N81: 179.89358 | O81: 15.484262 | P81: 582.11499 | Q81: 903.7247 | R81: 373.57057 | S81: 89.304294 | T81: 245.81929 | U81: 54.472307 | V81: 155.63269 | W81: 3.9944096 | X81: 0.14928538 | Y81: 46.298515 | Z81: 853.5344 | AA81: 659.64531 | AB81: 267.98503 | AC81: 175.63799 | AD81: 1221.5685 | AE81: 203.34953 | AF81: 250.88856 | AG81: 153.88986 | AH81: 467.94078 | AI81: 1037.8875 | AJ81: 727.82478 | AK81: 1148.6944 | AL81: 2358.4851 | AM81: 941.11738 | AN81: 205.25746 | AO81: 337.80723 | AP81: 775.38843 | AQ81: 314.97887 | AR81: 51.452084 | AS81: 36.863498 | AT81: 42.842833 | AU81: 59.210497 | AV81: 1773.444 | AW81: 813.62324 | AX81: 365.11869 | AY81: 764.6132 | AZ81: 11.32522 | BA81: 28.371281 | BB81: 40.502798 | BC81: 23.078653 | BD81: 276.9793 | BE81: 6.1069491 | BF81: 23.590256 | BG81: 46.680084 | BH81: 85.295711 | BI81: 46.890031 | BJ81: 70.859998 | BK81: 71.367215 | BL81: 85.10213 | BM81: 31.274499 | BN81: 44.544242 | BO81: 239.64417 | BP81: 14.531849 | BQ81: 164.15405 | BR81: 116.15244 | BS81: 12.221295 | BT81: 240.39342 | BU81: 698.18873 | BV81: 16.167585 | BW81: 154.32497 | BX81: 0 | BY81: 23737.788 | BZ81: 0 | CA81: 0 | CB81: 0 | CC81: 11407.196 | CD81: 5430.0163 | CE81: 0 | CF81: 16837.212 | CG81: 40575
B82: ICMS Total | C82: 77 | D82: 8343.3248 | E82: 4147.5786 | F82: 444.5748 | G82: 280.50113 | H82: 2135.2467 | I82: 953.89695 | J82: 215.15108 | K82: 7586.0308 | L82: 306.04427 | M82: 6674.5662 | N82: 2477.124 | O82: 442.39621 | P82: 1237.9742 | Q82: 1774.1848 | R82: 1798.833 | S82: 1016.1477 | T82: 2030.5233 | U82: 435.32753 | V82: 8752.2784 | W82: 178.62543 | X82: 0.36781858 | Y82: 628.38128 | Z82: 2149.1884 | AA82: 1286.9069 | AB82: 1455.429 | AC82: 1781.9362 | AD82: 1993.9188 | AE82: 2222.71 | AF82: 1552.7652 | AG82: 965.71295 | AH82: 1751.693 | AI82: 2602.761 | AJ82: 1490.1682 | AK82: 1879.5987 | AL82: 2966.0638 | AM82: 1722.8801 | AN82: 883.29842 | AO82: 1714.3592 | AP82: 1225.2546 | AQ82: 12175.833 | AR82: 1988.9335 | AS82: 1424.9966 | AT82: 1656.134 | AU82: 1108.2852 | AV82: 10706.709 | AW82: 1612.3979 | AX82: 10468.138 | AY82: 8076.6371 | AZ82: 111.34152 | BA82: 2402.9494 | BB82: 783.90607 | BC82: 694.50274 | BD82: 10107.12 | BE82: 290.44062 | BF82: 399.46081 | BG82: 4518.3805 | BH82: 1004.7901 | BI82: 3115.6887 | BJ82: 907.5556 | BK82: 1600.7393 | BL82: 638.51923 | BM82: 1102.1474 | BN82: 490.89624 | BO82: 3608.0465 | BP82: 253.90625 | BQ82: 5343.4811 | BR82: 2010.6387 | BS82: 1049.8188 | BT82: 3299.4808 | BU82: 7722.846 | BV82: 443.82303 | BW82: 3537.0443 | BX82: 0 | BY82: 186159.31 | BZ82: 0 | CA82: 0 | CB82: 0 | CC82: 274756.24 | CD82: 18394.451 | CE82: 0 | CF82: 293150.69 | CG82: 479310
B83: Zeros | C83: 78 | D83: 0 | E83: 0 | F83: 0 | G83: 0 | H83: 0 | I83: 0 | J83: 0 | K83: 0 | L83: 0 | M83: 0 | N83: 0 | O83: 0 | P83: 0 | Q83: 0 | R83: 0 | S83: 0 | T83: 0 | U83: 0 | V83: 0 | W83: 0 | X83: 0 | Y83: 0 | Z83: 0 | AA83: 0 | AB83: 0 | AC83: 0 | AD83: 0 | AE83: 0 | AF83: 0 | AG83: 0 | AH83: 0 | AI83: 0 | AJ83: 0 | AK83: 0 | AL83: 0 | AM83: 0 | AN83: 0 | AO83: 0 | AP83: 0 | AQ83: 0 | AR83: 0 | AS83: 0 | AT83: 0 | AU83: 0 | AV83: 0 | AW83: 0 | AX83: 0 | AY83: 0 | AZ83: 0 | BA83: 0 | BB83: 0 | BC83: 0 | BD83: 0 | BE83: 0 | BF83: 0 | BG83: 0 | BH83: 0 | BI83: 0 | BJ83: 0 | BK83: 0 | BL83: 0 | BM83: 0 | BN83: 0 | BO83: 0 | BP83: 0 | BQ83: 0 | BR83: 0 | BS83: 0 | BT83: 0 | BU83: 0 | BV83: 0 | BW83: 0 | BX83: 0 | BY83: 0 | BZ83: 0 | CA83: 0 | CB83: 0 | CC83: 0 | CD83: 0 | CE83: 0 | CF83: 0 | CG83: 0
B84: IPI Total | C84: 79 | D84: 92.83045 | E84: 108.75609 | F84: 8.8181189 | G84: 43.901705 | H84: 149.82467 | I84: 114.79842 | J84: 21.270716 | K84: 343.65182 | L84: 12.27611 | M84: 474.52055 | N84: 656.88983 | O84: 224.92679 | P84: 64.127689 | Q84: 91.499562 | R84: 95.836041 | S84: 103.98039 | T84: 264.25549 | U84: 70.396165 | V84: 98.002876 | W84: 2.0001427 | X84: 0.0041186166 | Y84: 10.183701 | Z84: 85.352802 | AA84: 111.77922 | AB84: 205.31806 | AC84: 57.339309 | AD84: 488.98762 | AE84: 148.60719 | AF84: 123.62493 | AG84: 62.22164 | AH84: 343.11461 | AI84: 1261.8141 | AJ84: 422.20155 | AK84: 506.16003 | AL84: 1432.0627 | AM84: 488.59848 | AN84: 502.12281 | AO84: 267.14322 | AP84: 455.42621 | AQ84: 200.78386 | AR84: 32.798227 | AS84: 23.498705 | AT84: 27.310243 | AU84: 42.842027 | AV84: 1560.7762 | AW84: 461.77681 | AX84: 574.3649 | AY84: 548.46866 | AZ84: 6.291749 | BA84: 28.427618 | BB84: 34.720319 | BC84: 52.355074 | BD84: 1985.9758 | BE84: 26.799991 | BF84: 40.444089 | BG84: 47.213289 | BH84: 192.23565 | BI84: 87.152662 | BJ84: 78.291817 | BK84: 125.437 | BL84: 82.52707 | BM84: 60.613208 | BN84: 52.163486 | BO84: 368.76159 | BP84: 18.233672 | BQ84: 160.10975 | BR84: 131.36614 | BS84: 33.137338 | BT84: 133.81203 | BU84: 479.39071 | BV84: 25.764398 | BW84: 246.34988 | BX84: 0 | BY84: 17984.82 | BZ84: 0 | CA84: 0 | CB84: 0 | CC84: 27535.434 | CD84: 8464.7465 | CE84: 0 | CF84: 36000.18 | CG84: 53985
B85: Zeros | C85: 80 | D85: 0 | E85: 0 | F85: 0 | G85: 0 | H85: 0 | I85: 0 | J85: 0 | K85: 0 | L85: 0 | M85: 0 | N85: 0 | O85: 0 | P85: 0 | Q85: 0 | R85: 0 | S85: 0 | T85: 0 | U85: 0 | V85: 0 | W85: 0 | X85: 0 | Y85: 0 | Z85: 0 | AA85: 0 | AB85: 0 | AC85: 0 | AD85: 0 | AE85: 0 | AF85: 0 | AG85: 0 | AH85: 0 | AI85: 0 | AJ85: 0 | AK85: 0 | AL85: 0 | AM85: 0 | AN85: 0 | AO85: 0 | AP85: 0 | AQ85: 0 | AR85: 0 | AS85: 0 | AT85: 0 | AU85: 0 | AV85: 0 | AW85: 0 | AX85: 0 | AY85: 0 | AZ85: 0 | BA85: 0 | BB85: 0 | BC85: 0 | BD85: 0 | BE85: 0 | BF85: 0 | BG85: 0 | BH85: 0 | BI85: 0 | BJ85: 0 | BK85: 0 | BL85: 0 | BM85: 0 | BN85: 0 | BO85: 0 | BP85: 0 | BQ85: 0 | BR85: 0 | BS85: 0 | BT85: 0 | BU85: 0 | BV85: 0 | BW85: 0 | BX85: 0 | BY85: 0 | BZ85: 0 | CA85: 0 | CB85: 0 | CC85: 0 | CD85: 0 | CE85: 0 | CF85: 0 | CG85: 0
B86: Outros IIL Total | C86: 81 | D86: 6042.8387 | E86: 1976.1746 | F86: 280.58837 | G86: 542.17693 | H86: 7778.1809 | I86: 1919.654 | J86: 507.53471 | K86: 5782.6909 | L86: 1324.3403 | M86: 5357.8042 | N86: 2360.7513 | O86: 196.44201 | P86: 1196.7163 | Q86: 1126.9178 | R86: 813.60704 | S86: 614.08995 | T86: 3188.7908 | U86: 386.25785 | V86: 41050.979 | W86: 837.81029 | X86: 1.7251865 | Y86: 1189.411 | Z86: 7474.2134 | AA86: 3009.4653 | AB86: 1473.2559 | AC86: 1482.2181 | AD86: 3363.0311 | AE86: 2491.3685 | AF86: 4071.2767 | AG86: 2442.911 | AH86: 2290.4334 | AI86: 3419.2493 | AJ86: 2196.5567 | AK86: 3229.2856 | AL86: 5950.1222 | AM86: 2615.7468 | AN86: 872.25178 | AO86: 1270.2224 | AP86: 1720.7274 | AQ86: 4884.6491 | AR86: 797.91186 | AS86: 571.67407 | AT86: 664.40077 | AU86: 1439.0873 | AV86: 10882.295 | AW86: 2927.3386 | AX86: 18595.729 | AY86: 6896.9237 | AZ86: 1024.1055 | BA86: 3522.7472 | BB86: 2896.9147 | BC86: 440.49756 | BD86: 5506.2819 | BE86: 380.87397 | BF86: 1598.8234 | BG86: 4872.6352 | BH86: 2867.2902 | BI86: 16130.832 | BJ86: 3723.3741 | BK86: 3130.7843 | BL86: 1098.7025 | BM86: 2497.4509 | BN86: 903.35185 | BO86: 3371.2999 | BP86: 393.3957 | BQ86: 14569.03 | BR86: 2067.2089 | BS86: 1689.5278 | BT86: 2196.0872 | BU86: 3526.8894 | BV86: 760.87382 | BW86: 3517.7723 | BX86: 0 | BY86: 264194.58 | BZ86: 0 | CA86: 0 | CB86: 0 | CC86: 116537.24 | CD86: 38389.184 | CE86: 0 | CF86: 154926.42 | CG86: 419121
B87: Zeros | C87: 82 | D87: 0 | E87: 0 | F87: 0 | G87: 0 | H87: 0 | I87: 0 | J87: 0 | K87: 0 | L87: 0 | M87: 0 | N87: 0 | O87: 0 | P87: 0 | Q87: 0 | R87: 0 | S87: 0 | T87: 0 | U87: 0 | V87: 0 | W87: 0 | X87: 0 | Y87: 0 | Z87: 0 | AA87: 0 | AB87: 0 | AC87: 0 | AD87: 0 | AE87: 0 | AF87: 0 | AG87: 0 | AH87: 0 | AI87: 0 | AJ87: 0 | AK87: 0 | AL87: 0 | AM87: 0 | AN87: 0 | AO87: 0 | AP87: 0 | AQ87: 0 | AR87: 0 | AS87: 0 | AT87: 0 | AU87: 0 | AV87: 0 | AW87: 0 | AX87: 0 | AY87: 0 | AZ87: 0 | BA87: 0 | BB87: 0 | BC87: 0 | BD87: 0 | BE87: 0 | BF87: 0 | BG87: 0 | BH87: 0 | BI87: 0 | BJ87: 0 | BK87: 0 | BL87: 0 | BM87: 0 | BN87: 0 | BO87: 0 | BP87: 0 | BQ87: 0 | BR87: 0 | BS87: 0 | BT87: 0 | BU87: 0 | BV87: 0 | BW87: 0 | BX87: 0 | BY87: 0 | BZ87: 0 | CA87: 0 | CB87: 0 | CC87: 0 | CD87: 0 | CE87: 0 | CF87: 0 | CG87: 0
B88: CONSUMO INTERMEDIÁRIO | C88: 83 | D88: 188526 | E88: 80267 | F88: 9462 | G88: 11860 | H88: 125178 | I88: 47192 | J88: 11249 | K88: 246575 | L88: 43131 | M88: 258915 | N88: 56464 | O88: 12112 | P88: 38746 | Q88: 38028 | R88: 28278 | S88: 20928 | T88: 77815 | U88: 11073 | V88: 392642.86 | W88: 9333.4371 | X88: 3188.7001 | Y88: 43113 | Z88: 152810 | AA88: 73056 | AB88: 39256 | AC88: 41455 | AD88: 91572 | AE88: 59131 | AF88: 115888 | AG88: 57302 | AH88: 68611 | AI88: 87944 | AJ88: 59911 | AK88: 91770 | AL88: 164702 | AM88: 75926 | AN88: 31134 | AO88: 42507 | AP88: 51453 | AQ88: 154436.32 | AR88: 22531.896 | AS88: 7774.2588 | AT88: 17302.527 | AU88: 31881 | AV88: 308793 | AW88: 77215 | AX88: 435410 | AY88: =SUM(AY79:AY87) -> 233598 | AZ88: 12967 | BA88: 34853 | BB88: 59424 | BC88: 12965 | BD88: 146427 | BE88: 9291 | BF88: 26886 | BG88: 96935 | BH88: 56861 | BI88: 226347 | BJ88: 51716 | BK88: 71738 | BL88: 23892 | BM88: 66006 | BN88: 18328 | BO88: 85056 | BP88: 7981 | BQ88: 242741 | BR88: 55962 | BS88: 40553 | BT88: 68487 | BU88: 133095 | BV88: 17382 | BW88: 85520 | BX88: 0 | BY88: 5998860 | BZ88: 1025056 | CA88: 1393480 | CB88: 102253 | CC88: 4423548 | CD88: 1057409 | CE88: -131 | CF88: 8001615 | CG88: 14000475
A89: R10 | B89: Remunerações | C89: 84 | D89: 34356 | E89: 22217 | F89: 2255 | G89: 4126 | H89: 16917 | I89: 4502 | J89: 2607 | K89: 30117 | L89: 8690 | M89: 35422 | N89: 9953 | O89: 1711 | P89: 11262 | Q89: 18543 | R89: 11048 | S89: 6644 | T89: 14028 | U89: 5664 | V89: 8644.8181 | W89: 222.3 | X89: 24.88187 | Y89: 7013 | Z89: 12903 | AA89: 9380 | AB89: 6854 | AC89: 12695 | AD89: 22917 | AE89: 19150 | AF89: 13401 | AG89: 6247 | AH89: 22042 | AI89: 9775 | AJ89: 14631 | AK89: 27620 | AL89: 20483 | AM89: 20855 | AN89: 8257 | AO89: 16648 | AP89: 13057 | AQ89: 14489.444 | AR89: 1691.8722 | AS89: 1627.8645 | AT89: 3685.8193 | AU89: 22993 | AV89: 104570 | AW89: 49181 | AX89: 352528 | AY89: =AY90+AY91+AY94 -> 87877 | AZ89: 5137 | BA89: 7492 | BB89: 44037 | BC89: 11307 | BD89: 60116 | BE89: 6798 | BF89: 11678 | BG89: 19212 | BH89: 57187 | BI89: 165217 | BJ89: 7923 | BK89: 61939 | BL89: 18585 | BM89: 15429 | BN89: 11344 | BO89: 118404 | BP89: 31074 | BQ89: 528703 | BR89: 282090 | BS89: 89933 | BT89: 127700 | BU89: 89831 | BV89: 13265 | BW89: 45395 | BX89: 74451 | BY89: 3055773 | BZ89: 0 | CA89: 0 | CB89: 0 | CC89: 0 | CD89: 0 | CE89: 0 | CF89: 0 | CG89: 3055773
A90: R11 | B90: Salários | C90: 85 | D90: 29230 | E90: 19506 | F90: 1981 | G90: 3307 | H90: 12359 | I90: 3581 | J90: 2011 | K90: 23432 | L90: 6252 | M90: 27911 | N90: 7718 | O90: 1309 | P90: 9222 | Q90: 14743 | R90: 9151 | S90: 5395 | T90: 11059 | U90: 4600 | V90: 6069.4556 | W90: 156.075 | X90: 17.469356 | Y90: 5622 | Z90: 9758 | AA90: 7225 | AB90: 5400 | AC90: 9702 | AD90: 17824 | AE90: 15527 | AF90: 10413 | AG90: 5015 | AH90: 17453 | AI90: 7775 | AJ90: 11477 | AK90: 21904 | AL90: 15859 | AM90: 17465 | AN90: 6659 | AO90: 13658 | AP90: 10523 | AQ90: 10400.448 | AR90: 1214.4171 | AS90: 1168.4727 | AT90: 2645.6621 | AU90: 17320 | AV90: 85935 | AW90: 40106 | AX90: 279452 | AY90: 71610 | AZ90: 4217 | BA90: 6119 | BB90: 34067 | BC90: 9520 | BD90: 50603 | BE90: 5563 | BF90: 9857 | BG90: 14372 | BH90: 45370 | BI90: 127124 | BJ90: 6253 | BK90: 50719 | BL90: 14886 | BM90: 12362 | BN90: 8992 | BO90: 95075 | BP90: 24376 | BQ90: 381003 | BR90: 227721 | BS90: 74374 | BT90: 102765 | BU90: 77743 | BV90: 11518 | BW90: 38820 | BX90: 70758 | BY90: 2422298 | BZ90: 0 | CA90: 0 | CB90: 0 | CC90: 0 | CD90: 0 | CE90: 0 | CF90: 0 | CG90: 2422298
A91: R12 | B91: Contribuições sociais efetivas | C91: 86 | D91: 5126 | E91: 2711 | F91: 274 | G91: 819 | H91: 4558 | I91: 921 | J91: 596 | K91: 6685 | L91: 2438 | M91: 7511 | N91: 2235 | O91: 402 | P91: 2040 | Q91: 3800 | R91: 1897 | S91: 1249 | T91: 2969 | U91: 1064 | V91: 2575.3625 | W91: 66.225 | X91: 7.412514 | Y91: 1391 | Z91: 3145 | AA91: 2155 | AB91: 1454 | AC91: 2993 | AD91: 5093 | AE91: 3623 | AF91: 2988 | AG91: 1232 | AH91: 4589 | AI91: 2000 | AJ91: 3154 | AK91: 5716 | AL91: 4624 | AM91: 3390 | AN91: 1598 | AO91: 2990 | AP91: 2534 | AQ91: 4088.9959 | AR91: 477.45506 | AS91: 459.39176 | AT91: 1040.1573 | AU91: 5673 | AV91: 18635 | AW91: 9075 | AX91: 73076 | AY91: =AY92+AY93 -> 16267 | AZ91: 920 | BA91: 1373 | BB91: 9970 | BC91: 1787 | BD91: 9513 | BE91: 1235 | BF91: 1821 | BG91: 4840 | BH91: 11817 | BI91: 38093 | BJ91: 1670 | BK91: 11220 | BL91: 3699 | BM91: 3067 | BN91: 2352 | BO91: 23329 | BP91: 6698 | BQ91: 64857 | BR91: 47663 | BS91: 15559 | BT91: 17672 | BU91: 12088 | BV91: 1747 | BW91: 6575 | BX91: 3693 | BY91: 536663 | BZ91: 0 | CA91: 0 | CB91: 0 | CC91: 0 | CD91: 0 | CE91: 0 | CF91: 0 | CG91: 536663
B92: Previdência oficial /FGTS | C92: 87 | D92: 5123 | E92: 2698 | F92: 272 | G92: 806 | H92: 3536 | I92: 884 | J92: 566 | K92: 6513 | L92: 2394 | M92: 7273 | N92: 2148 | O92: 367 | P92: 1996 | Q92: 3739 | R92: 1856 | S92: 1182 | T92: 2686 | U92: 1025 | V92: 1824.8227 | W92: 46.925 | X92: 5.2522797 | Y92: 1350 | Z92: 2868 | AA92: 1980 | AB92: 1412 | AC92: 2814 | AD92: 4943 | AE92: 3466 | AF92: 2727 | AG92: 1168 | AH92: 4470 | AI92: 1937 | AJ92: 3036 | AK92: 5460 | AL92: 4407 | AM92: 3257 | AN92: 1477 | AO92: 2905 | AP92: 2436 | AQ92: 3142.5814 | AR92: 366.94617 | AS92: 353.06369 | AT92: 799.40869 | AU92: 5109 | AV92: 18183 | AW92: 8959 | AX92: 71753 | AY92: 15650 | AZ92: 881 | BA92: 1333 | BB92: 8842 | BC92: 1736 | BD92: 9380 | BE92: 1198 | BF92: 1745 | BG92: 3960 | BH92: 11081 | BI92: 32184 | BJ92: 1614 | BK92: 10153 | BL92: 3565 | BM92: 3015 | BN92: 2297 | BO92: 22948 | BP92: 6601 | BQ92: 64134 | BR92: 47469 | BS92: 15429 | BT92: 17649 | BU92: 11939 | BV92: 1701 | BW92: 6456 | BX92: 3693 | BY92: 514373 | BZ92: 0 | CA92: 0 | CB92: 0 | CC92: 0 | CD92: 0 | CE92: 0 | CF92: 0 | CG92: 514373
B93: Previdência privada | C93: 88 | D93: 3 | E93: 13 | F93: 2 | G93: 13 | H93: 1022 | I93: 37 | J93: 30 | K93: 172 | L93: 44 | M93: 238 | N93: 87 | O93: 35 | P93: 44 | Q93: 61 | R93: 41 | S93: 67 | T93: 283 | U93: 39 | V93: 750.53977 | W93: 19.3 | X93: 2.1602344 | Y93: 41 | Z93: 277 | AA93: 175 | AB93: 42 | AC93: 179 | AD93: 150 | AE93: 157 | AF93: 261 | AG93: 64 | AH93: 119 | AI93: 63 | AJ93: 118 | AK93: 256 | AL93: 217 | AM93: 133 | AN93: 121 | AO93: 85 | AP93: 98 | AQ93: 946.41449 | AR93: 110.50889 | AS93: 106.32806 | AT93: 240.74856 | AU93: 564 | AV93: 452 | AW93: 116 | AX93: 1323 | AY93: 617 | AZ93: 39 | BA93: 40 | BB93: 1128 | BC93: 51 | BD93: 133 | BE93: 37 | BF93: 76 | BG93: 880 | BH93: 736 | BI93: 5909 | BJ93: 56 | BK93: 1067 | BL93: 134 | BM93: 52 | BN93: 55 | BO93: 381 | BP93: 97 | BQ93: 723 | BR93: 194 | BS93: 130 | BT93: 23 | BU93: 149 | BV93: 46 | BW93: 119 | BX93: 0 | BY93: 22290 | BZ93: 0 | CA93: 0 | CB93: 0 | CC93: 0 | CD93: 0 | CE93: 0 | CF93: 0 | CG93: 22290
A94: R13 | B94: Contribuições sociais imputadas | C94: 89 | D94: 0 | E94: 0 | F94: 0 | G94: 0 | H94: 0 | I94: 0 | J94: 0 | K94: 0 | L94: 0 | M94: 0 | N94: 0 | O94: 0 | P94: 0 | Q94: 0 | R94: 0 | S94: 0 | T94: 0 | U94: 0 | V94: 0 | W94: 0 | X94: 0 | Y94: 0 | Z94: 0 | AA94: 0 | AB94: 0 | AC94: 0 | AD94: 0 | AE94: 0 | AF94: 0 | AG94: 0 | AH94: 0 | AI94: 0 | AJ94: 0 | AK94: 0 | AL94: 0 | AM94: 0 | AN94: 0 | AO94: 0 | AP94: 0 | AQ94: 0 | AR94: 0 | AS94: 0 | AT94: 0 | AU94: 0 | AV94: 0 | AW94: 0 | AX94: 0 | AY94: 0 | AZ94: 0 | BA94: 0 | BB94: 0 | BC94: 0 | BD94: 0 | BE94: 0 | BF94: 0 | BG94: 0 | BH94: 0 | BI94: 0 | BJ94: 0 | BK94: 0 | BL94: 0 | BM94: 0 | BN94: 0 | BO94: 0 | BP94: 0 | BQ94: 82843 | BR94: 6706 | BS94: 0 | BT94: 7263 | BU94: 0 | BV94: 0 | BW94: 0 | BX94: 0 | BY94: 96812 | BZ94: 0 | CA94: 0 | CB94: 0 | CC94: 0 | CD94: 0 | CE94: 0 | CF94: 0 | CG94: 96812
A95: N2 | B95: Excedente operacional bruto e rendimento misto bruto | C95: 90 | D95: 182575 | E95: 48953 | F95: 26039 | G95: 3887 | H95: 82275 | I95: 40026 | J95: 4247 | K95: 13233 | L95: -927 | M95: 27501 | N95: 11221 | O95: 1741 | P95: 4276 | Q95: 9211 | R95: 4032 | S95: 4783 | T95: 16893 | U95: 4315 | V95: 31352.535 | W95: 806.225 | X95: 90.240153 | Y95: 4134 | Z95: 12505 | AA95: 5167 | AB95: 3587 | AC95: 21406 | AD95: 5651 | AE95: 4831 | AF95: 19673 | AG95: 9072 | AH95: 10310 | AI95: 4751 | AJ95: 4693 | AK95: 8755 | AL95: 1419 | AM95: 8283 | AN95: 2054 | AO95: 15383 | AP95: 14972 | AQ95: 60670.726 | AR95: 9910.6183 | AS95: 7100.5882 | AT95: 18879.067 | AU95: 26426 | AV95: 135690 | AW95: 47260 | AX95: 320736 | AY95: =AY96+AY97 -> 75354 | AZ95: 4521 | BA95: 1775 | BB95: 33698 | BC95: 3121 | BD95: 68654 | BE95: 1586 | BF95: 3948 | BG95: 43825 | BH95: 51289 | BI95: 249222 | BJ95: 579640 | BK95: 92276 | BL95: 20171 | BM95: 22865 | BN95: 18437 | BO95: 54852 | BP95: 2998 | BQ95: 87157 | BR95: 13026 | BS95: 10137 | BT95: 6529 | BU95: 77062 | BV95: 9413 | BW95: 39805 | BX95: 0 | BY95: 2871210 | BZ95: 0 | CA95: 0 | CB95: 0 | CC95: 0 | CD95: 0 | CE95: 0 | CF95: 0 | CG95: 2871210
B96: Rendimento misto bruto | C96: 91 | D96: 97228 | E96: 38269 | F96: 12179 | G96: 254 | H96: 0 | I96: 0 | J96: 0 | K96: 365 | L96: 0 | M96: 4151 | N96: 23 | O96: 0 | P96: 1228 | Q96: 6429 | R96: 625 | S96: 1625 | T96: 296 | U96: 460 | V96: 0 | W96: 0 | X96: 0 | Y96: 0 | Z96: 0 | AA96: 0 | AB96: 585 | AC96: 0 | AD96: 373 | AE96: 799 | AF96: 0 | AG96: -18 | AH96: 2385 | AI96: 0 | AJ96: 0 | AK96: 0 | AL96: 0 | AM96: 28 | AN96: 0 | AO96: 1333 | AP96: 5023 | AQ96: 0 | AR96: 0 | AS96: 0 | AT96: 0 | AU96: 1734 | AV96: 68569 | AW96: 22740 | AX96: 58881 | AY96: 25394 | AZ96: 430 | BA96: 0 | BB96: 1273 | BC96: 1302 | BD96: 48476 | BE96: 56 | BF96: 853 | BG96: 253 | BH96: 9240 | BI96: 2638 | BJ96: 4300 | BK96: 39398 | BL96: 11034 | BM96: 6368 | BN96: 793 | BO96: 7868 | BP96: 1175 | BQ96: 0 | BR96: 0 | BS96: 7947 | BT96: 0 | BU96: 50020 | BV96: 6325 | BW96: 32861 | BX96: 0 | BY96: 583568 | BZ96: 0 | CA96: 0 | CB96: 0 | CC96: 0 | CD96: 0 | CE96: 0 | CF96: 0 | CG96: 583568
B97: Excedente operacional bruto (EOB) | C97: 92 | D97: 85347 | E97: 10684 | F97: 13860 | G97: 3633 | H97: 82275 | I97: 40026 | J97: 4247 | K97: 12868 | L97: -927 | M97: 23350 | N97: 11198 | O97: 1741 | P97: 3048 | Q97: 2782 | R97: 3407 | S97: 3158 | T97: 16597 | U97: 3855 | V97: 31352.535 | W97: 806.225 | X97: 90.240153 | Y97: 4134 | Z97: 12505 | AA97: 5167 | AB97: 3002 | AC97: 21406 | AD97: 5278 | AE97: 4032 | AF97: 19673 | AG97: 9090 | AH97: 7925 | AI97: 4751 | AJ97: 4693 | AK97: 8755 | AL97: 1419 | AM97: 8255 | AN97: 2054 | AO97: 14050 | AP97: 9949 | AQ97: 60670.726 | AR97: 9910.6183 | AS97: 7100.5882 | AT97: 18879.067 | AU97: 24692 | AV97: 67121 | AW97: 24520 | AX97: 261855 | AY97: 49960 | AZ97: 4091 | BA97: 1775 | BB97: 32425 | BC97: 1819 | BD97: 20178 | BE97: 1530 | BF97: 3095 | BG97: 43572 | BH97: 42049 | BI97: 246584 | BJ97: 575340 | BK97: 52878 | BL97: 9137 | BM97: 16497 | BN97: 17644 | BO97: 46984 | BP97: 1823 | BQ97: 87157 | BR97: 13026 | BS97: 2190 | BT97: 6529 | BU97: 27042 | BV97: 3088 | BW97: 6944 | BX97: 0 | BY97: 2287642 | BZ97: 0 | CA97: 0 | CB97: 0 | CC97: 0 | CD97: 0 | CE97: 0 | CF97: 0 | CG97: 2287642
A98: N0 | B98: VALOR ADICIONADO CUSTO FATORES | C98: 93 | D98: 216931 | E98: 71170 | F98: 28294 | G98: 8013 | H98: 99192 | I98: 44528 | J98: 6854 | K98: 43350 | L98: 7763 | M98: 62923 | N98: 21174 | O98: 3452 | P98: 15538 | Q98: 27754 | R98: 15080 | S98: 11427 | T98: 30921 | U98: 9979 | V98: 39997.353 | W98: 1028.525 | X98: 115.12202 | Y98: 11147 | Z98: 25408 | AA98: 14547 | AB98: 10441 | AC98: 34101 | AD98: 28568 | AE98: 23981 | AF98: 33074 | AG98: 15319 | AH98: 32352 | AI98: 14526 | AJ98: 19324 | AK98: 36375 | AL98: 21902 | AM98: 29138 | AN98: 10311 | AO98: 32031 | AP98: 28029 | AQ98: 75160.17 | AR98: 11602.49 | AS98: 8728.4526 | AT98: 22564.887 | AU98: 49419 | AV98: 240260 | AW98: 96441 | AX98: 673264 | AY98: =AY95+AY89 -> 163231 | AZ98: 9658 | BA98: 9267 | BB98: 77735 | BC98: 14428 | BD98: 128770 | BE98: 8384 | BF98: 15626 | BG98: 63037 | BH98: 108476 | BI98: 414439 | BJ98: 587563 | BK98: 154215 | BL98: 38756 | BM98: 38294 | BN98: 29781 | BO98: 173256 | BP98: 34072 | BQ98: 615860 | BR98: 295116 | BS98: 100070 | BT98: 134229 | BU98: 166893 | BV98: 22678 | BW98: 85200 | BX98: 74451 | BY98: 5926983 | BZ98: 0 | CA98: 0 | CB98: 0 | CC98: 0 | CD98: 0 | CE98: 0 | CF98: 0 | CG98: 5926983
A99: R22 | B99: Outros impostos sobre a produção | C99: 94 | D99: 1841 | E99: 641 | F99: 151 | G99: 199 | H99: 1568 | I99: 630 | J99: 170 | K99: 2563 | L99: 775 | M99: 3210 | N99: 938 | O99: 130 | P99: 530 | Q99: 650 | R99: 490 | S99: 363 | T99: 939 | U99: 281 | V99: 1318.0446 | W99: 26.9 | X99: 0.055391439 | Y99: 501 | Z99: 1318 | AA99: 705 | AB99: 479 | AC99: 709 | AD99: 1197 | AE99: 875 | AF99: 1156 | AG99: 555 | AH99: 1058 | AI99: 1074 | AJ99: 784 | AK99: 1363 | AL99: 1530 | AM99: 1108 | AN99: 419 | AO99: 725 | AP99: 486 | AQ99: 2228.8841 | AR99: 364.09024 | AS99: 260.85707 | AT99: 303.16862 | AU99: 951 | AV99: 3384 | AW99: 1466 | AX99: 12523 | AY99: 3613 | AZ99: 417 | BA99: 712 | BB99: 1734 | BC99: 394 | BD99: 1741 | BE99: 228 | BF99: 1362 | BG99: 6971 | BH99: 2073 | BI99: 8223 | BJ99: 473 | BK99: 2660 | BL99: 617 | BM99: 520 | BN99: 525 | BO99: 3452 | BP99: 1043 | BQ99: 163 | BR99: 17 | BS99: 2814 | BT99: 0 | BU99: 3006 | BV99: 306 | BW99: 1199 | BX99: 0 | BY99: 99200 | BZ99: 0 | CA99: 0 | CB99: 0 | CC99: 0 | CD99: 0 | CE99: 0 | CF99: 0 | CG99: 99200
A100: R32 | B100: Outros subsídios à produção | C100: 95 | D100: -9261 | E100: -119 | F100: -37 | G100: -61 | H100: 0 | I100: -24 | J100: 0 | K100: -82 | L100: -114 | M100: -105 | N100: -32 | O100: 0 | P100: -21 | Q100: 0 | R100: 0 | S100: -31 | T100: -80 | U100: 0 | V100: -146.99382 | W100: -3 | X100: -0.006177484 | Y100: -124 | Z100: -30 | AA100: 0 | AB100: 0 | AC100: -21 | AD100: -120 | AE100: -99 | AF100: -53 | AG100: -28 | AH100: -67 | AI100: 0 | AJ100: -74 | AK100: -195 | AL100: -219 | AM100: -180 | AN100: -51 | AO100: -28 | AP100: 0 | AQ100: -84.015586 | AR100: -13.724022 | AS100: -9.8327498 | AT100: -11.427642 | AU100: -31 | AV100: -364 | AW100: -29 | AX100: -618 | AY100: -1629 | AZ100: 0 | BA100: -25 | BB100: -49 | BC100: 0 | BD100: 0 | BE100: 0 | BF100: 0 | BG100: -64 | BH100: 0 | BI100: 0 | BJ100: 0 | BK100: 0 | BL100: -374 | BM100: 0 | BN100: -155 | BO100: -49 | BP100: 0 | BQ100: 0 | BR100: 0 | BS100: 0 | BT100: 0 | BU100: -121 | BV100: 0 | BW100: 0 | BX100: 0 | BY100: -15033 | BZ100: 0 | CA100: 0 | CB100: 0 | CC100: 0 | CD100: 0 | CE100: 0 | CF100: 0 | CG100: -15033
A101: N1 | B101: Valor adicionado bruto ( PIB ) | C101: 96 | D101: 209511 | E101: 71692 | F101: 28408 | G101: 8151 | H101: 100760 | I101: 45134 | J101: 7024 | K101: 45831 | L101: 8424 | M101: 66028 | N101: 22080 | O101: 3582 | P101: 16047 | Q101: 28404 | R101: 15570 | S101: 11759 | T101: 31780 | U101: 10260 | V101: 41168.404 | W101: 1052.425 | X101: 115.17124 | Y101: 11524 | Z101: 26696 | AA101: 15252 | AB101: 10920 | AC101: 34789 | AD101: 29645 | AE101: 24757 | AF101: 34177 | AG101: 15846 | AH101: 33343 | AI101: 15600 | AJ101: 20034 | AK101: 37543 | AL101: 23213 | AM101: 30066 | AN101: 10679 | AO101: 32728 | AP101: 28515 | AQ101: 77305.039 | AR101: 11952.857 | AS101: 8979.4769 | AT101: 22856.628 | AU101: 50339 | AV101: 243280 | AW101: 97878 | AX101: 685169 | AY101: =AY98+AY99+AY100 -> 165215 | AZ101: 10075 | BA101: 9954 | BB101: 79420 | BC101: 14822 | BD101: 130511 | BE101: 8612 | BF101: 16988 | BG101: 69944 | BH101: 110549 | BI101: 422662 | BJ101: 588036 | BK101: 156875 | BL101: 38999 | BM101: 38814 | BN101: 30151 | BO101: 176659 | BP101: 35115 | BQ101: 616023 | BR101: 295133 | BS101: 102884 | BT101: 134229 | BU101: 169778 | BV101: 22984 | BW101: 86399 | BX101: 74451 | BY101: 6011150 | BZ101: 0 | CA101: 0 | CB101: 0 | CC101: 0 | CD101: 0 | CE101: 0 | CF101: 0 | CG101: 6011150
A102: P10 | B102: VALOR DA PRODUÇÃO | C102: 97 | D102: 398037 | E102: 151959 | F102: 37870 | G102: 20011 | H102: 225938 | I102: 92326 | J102: 18273 | K102: 292406 | L102: 51555 | M102: 324943 | N102: 78544 | O102: 15694 | P102: 54793 | Q102: 66432 | R102: 43848 | S102: 32687 | T102: 109595 | U102: 21333 | V102: 433811.27 | W102: 10385.862 | X102: 3303.8714 | Y102: 54637 | Z102: 179506 | AA102: 88308 | AB102: 50176 | AC102: 76244 | AD102: 121217 | AE102: 83888 | AF102: 150065 | AG102: 73148 | AH102: 101954 | AI102: 103544 | AJ102: 79945 | AK102: 129313 | AL102: 187915 | AM102: 105992 | AN102: 41813 | AO102: 75235 | AP102: 79968 | AQ102: 231741.36 | AR102: 34484.753 | AS102: 16753.736 | AT102: 40159.155 | AU102: 82220 | AV102: 552073 | AW102: 175093 | AX102: 1120579 | AY102: =AY101+AY88 -> 398813 | AZ102: 23042 | BA102: 44807 | BB102: 138844 | BC102: 27787 | BD102: 276938 | BE102: 17903 | BF102: 43874 | BG102: 166879 | BH102: 167410 | BI102: 649009 | BJ102: 639752 | BK102: 228613 | BL102: 62891 | BM102: 104820 | BN102: 48479 | BO102: 261715 | BP102: 43096 | BQ102: 858764 | BR102: 351095 | BS102: 143437 | BT102: 202716 | BU102: 302873 | BV102: 40366 | BW102: 171919 | BX102: 74451 | BY102: 12010010 | BZ102: 0 | CA102: 0 | CB102: 0 | CC102: 0 | CD102: 0 | CE102: 0 | CF102: 0 | CG102: 12010010
B103: Fator trabalho (ocupações) | C103: 98 | D103: 6687599 | E103: 5891326 | F103: 801096 | G103: 118276 | H103: 50144 | I103: 35440 | J103: 28949 | K103: 765202 | L103: 156442 | M103: 1285134 | N103: 190956 | O103: 17784 | P103: 632157 | Q103: 1676586 | R103: 468535 | S103: 376397 | T103: 201777 | U103: 180593 | V103: 18842.968 | W103: 2617.3805 | X103: 260.652 | Y103: 98255 | Z103: 92285 | AA103: 85311 | AB103: 137454 | AC103: 104114 | AD103: 444627 | AE103: 563545 | AF103: 122810 | AG103: 100208 | AH103: 669483 | AI103: 127233 | AJ103: 198332 | AK103: 378379 | AL103: 160623 | AM103: 305020 | AN103: 81338 | AO103: 744311 | AP103: 532601 | AQ103: 102497.99 | AR103: 16271.463 | AS103: 12467.512 | AT103: 27161.033 | AU103: 563905 | AV103: 7617875 | AW103: 2968849 | AX103: 16293655 | AY103: 4076625 | AZ103: 52733 | BA103: 60529 | BB103: 808476 | BC103: 438611 | BD103: 5622208 | BE103: 136112 | BF103: 166605 | BG103: 252106 | BH103: 752017 | BI103: 1241143 | BJ103: 466409 | BK103: 1887743 | BL103: 630552 | BM103: 613009 | BN103: 298455 | BO103: 4178701 | BP103: 781913 | BQ103: 4825230 | BR103: 4202039 | BS103: 2878667 | BT103: 2218572 | BU103: 3428002 | BV103: 1122849 | BW103: 4502808 | BX103: 6563436 | BY103: 104340275 | BZ103: 0 | CA103: 0 | CB103: 0 | CC103: 0 | CD103: 0 | CE103: 0 | CF103: 0 | CG103: 104340275
AY105: =AY101-AY102 -> -233598

Sheet FM - C1
A1: (1) a matriz de fluxos em valores monetários Z, com os setores de valor adicionado e a demanda final;
A3: Valores correntes em 1 000 000 R$ | D3: S01 | E3: S02 | F3: S03 | G3: S04 | H3: S05 | I3: S06 | J3: S07 | K3: S08 | L3: S09 | M3: S10 | N3: S11 | O3: S12 | P3: S13 | Q3: S14 | R3: S15 | S3: S16 | T3: S17 | U3: S18 | V3: S19 | W3: S20 | X3: S21 | Y3: S22 | Z3: S23 | AA3: S24 | AB3: S25 | AC3: S26 | AD3: S27 | AE3: S28 | AF3: S29 | AG3: S30 | AH3: S31 | AI3: S32 | AJ3: S33 | AK3: S34 | AL3: S35 | AM3: S36 | AN3: S37 | AO3: S38 | AP3: S39 | AQ3: S40 | AR3: S41 | AS3: S42 | AT3: S43 | AU3: S44 | AV3: S45 | AW3: S46 | AX3: S47 | AY3: S48 | AZ3: S49 | BA3: S50 | BB3: S51 | BC3: S52 | BD3: S53 | BE3: S54 | BF3: S55 | BG3: S56 | BH3: S57 | BI3: S58 | BJ3: S59 | BK3: S60 | BL3: S61 | BM3: S62 | BN3: S63 | BO3: S64 | BP3: S65 | BQ3: S66 | BR3: S67 | BS3: S68 | BT3: S69 | BU3: S70 | BV3: S71 | BW3: S72 | BX3: S73
A4: Matriz de usos setor x setor | D4: Agricultura, inclusive o apoio à agricultura e a pós-colheita | E4: Pecuária, inclusive o apoio à pecuária | F4: Produção florestal; pesca e aquicultura | G4: Extração de carvão mineral e de minerais não-metálicos | H4: Extração de petróleo e gás, inclusive as atividades de apoio | I4: Extração de minério de ferro, inclusive beneficiamentos e a aglomeração | J4: Extração de minerais metálicos não-ferrosos, inclusive beneficiamentos | K4: Abate e produtos de carne, inclusive os produtos do laticínio e da pesca | L4: Fabricação e refino de açúcar | M4: Outros produtos alimentares | N4: Fabricação de bebidas | O4: Fabricação de produtos do fumo | P4: Fabricação de produtos têxteis | Q4: Confecção de artefatos do vestuário e acessórios | R4: Fabricação de calçados e de artefatos de couro | S4: Fabricação de produtos da madeira | T4: Fabricação de celulose, papel e produtos de papel | U4: Impressão e reprodução de gravações | V4: Derivados de petróleo | W4: Biodiesel | X4: Coquerias | Y4: Fabricação de biocombustíveis | Z4: Fabricação de químicos orgânicos e inorgânicos, resinas e elastômeros | AA4: Fabricação de defensivos, desinfestantes, tintas e químicos diversos | AB4: Fabricação de produtos de limpeza, cosméticos/perfumaria e higiene pessoal | AC4: Fabricação de produtos farmoquímicos e farmacêuticos | AD4: Fabricação de produtos de borracha e de material plástico | AE4: Fabricação de produtos de minerais não-metálicos | AF4: Produção de ferro-gusa/ferroligas, siderurgia e tubos de aço sem costura | AG4: Metalurgia de metais não-ferosos e a fundição de metais | AH4: Fabricação de produtos de metal, exceto máquinas e equipamentos | AI4: Fabricação de equipamentos de informática, produtos eletrônicos e ópticos | AJ4: Fabricação de máquinas e equipamentos elétricos | AK4: Fabricação de máquinas e equipamentos mecânicos | AL4: Fabricação de automóveis, caminhões e ônibus, exceto peças | AM4: Fabricação de peças e acessórios para veículos automotores | AN4: Fabricação de outros equipamentos de transporte, exceto veículos automotores | AO4: Fabricação de móveis e de produtos de indústrias diversas | AP4: Manutenção, reparação e instalação de máquinas e equipamentos | AQ4: Geração centralizada de energia elétrica | AR4: Geração distribuída de energia elétrica | AS4: Transmissão | AT4: Gás Natural | AU4: Água, esgoto e gestão de resíduos | AV4: Construção | AW4: Comércio e reparação de veículos automotores e motocicletas | AX4: Comércio por atacado e a varejo, exceto veículos automotores | AY4: Transporte terrestre | AZ4: Transporte aquaviário | BA4: Transporte aéreo | BB4: Armazenamento, atividades auxiliares dos transportes e correio | BC4: Alojamento | BD4: Alimentação | BE4: Edição e edição integrada à impressão | BF4: Atividades de televisão, rádio, cinema e gravação/edição de som e imagem | BG4: Telecomunicações | BH4: Desenvolvimento de sistemas e outros serviços de informação | BI4: Intermediação financeira, seguros e previdência complementar | BJ4: Atividades imobiliárias | BK4: Atividades jurídicas, contábeis, consultoria e sedes de empresas | BL4: Serviços de arquitetura, engenharia, testes/análises técnicas e P & D | BM4: Outras atividades profissionais, científicas e técnicas | BN4: Aluguéis não-imobiliários e gestão de ativos de propriedade intelectual | BO4: Outras atividades administrativas e serviços complementares | BP4: Atividades de vigilância, segurança e investigação | BQ4: Administração pública, defesa e seguridade social | BR4: Educação pública | BS4: Educação privada | BT4: Saúde pública | BU4: Saúde privada | BV4: Atividades artísticas, criativas e de espetáculos | BW4: Organizações associativas e outros serviços pessoais | BX4: Serviços domésticos | BY4: Consumo Intermediário total | BZ4: Exportação de bens e serviços | CA4: Consumo do governo | CB4: Consumo das ISFLSF | CC4: Consumo das famílias | CD4: Formação bruta de capital fixo | CE4: Variação de estoque | CF4: Demanda final | CG4: Demanda total | CI4: Proporção Demanda Final / Demanda total
B5: Número identificador | C5: 0 | D5: 1 | E5: 2 | F5: 3 | G5: 4 | H5: 5 | I5: 6 | J5: 7 | K5: 8 | L5: 9 | M5: 10 | N5: 11 | O5: 12 | P5: 13 | Q5: 14 | R5: 15 | S5: 16 | T5: 17 | U5: 18 | V5: 19 | W5: 20 | X5: 21 | Y5: 22 | Z5: 23 | AA5: 24 | AB5: 25 | AC5: 26 | AD5: 27 | AE5: 28 | AF5: 29 | AG5: 30 | AH5: 31 | AI5: 32 | AJ5: 33 | AK5: 34 | AL5: 35 | AM5: 36 | AN5: 37 | AO5: 38 | AP5: 39 | AQ5: 40 | AR5: 41 | AS5: 42 | AT5: 43 | AU5: 44 | AV5: 45 | AW5: 46 | AX5: 47 | AY5: 48 | AZ5: 49 | BA5: 50 | BB5: 51 | BC5: 52 | BD5: 53 | BE5: 54 | BF5: 55 | BG5: 56 | BH5: 57 | BI5: 58 | BJ5: 59 | BK5: 60 | BL5: 61 | BM5: 62 | BN5: 63 | BO5: 64 | BP5: 65 | BQ5: 66 | BR5: 67 | BS5: 68 | BT5: 69 | BU5: 70 | BV5: 71 | BW5: 72 | BX5: 73 | BY5: 74 | BZ5: 75 | CA5: 76 | CB5: 77 | CC5: 78 | CD5: 79 | CE5: 80 | CF5: 81 | CG5: 82
A6: S01 | B6: Agricultura, inclusive o apoio à agricultura e a pós-colheita | C6: 1 | D6: 8170.3586 | E6: 5290.2246 | F6: 156.75542 | G6: 1.8265937 | H6: 9.8692679 | I6: 1.1434984 | J6: 1.7841451 | K6: 7264.3074 | L6: 28021.78 | M6: 76458.432 | N6: 2089.3011 | O6: 4889.0335 | P6: 5526.2619 | Q6: 518.70182 | R6: 6.6028531 | S6: 90.994169 | T6: 172.72948 | U6: 0.25638423 | V6: 8.6760449 | W6: 0.051985351 | X6: 0.041880586 | Y6: 22484.79 | Z6: 15.129223 | AA6: 18.049511 | AB6: 2.2091675 | AC6: 13.484794 | AD6: 38.146982 | AE6: 14.418004 | AF6: 42.241869 | AG6: 26.216602 | AH6: 2.7665426 | AI6: 0.27528051 | AJ6: 0.30007581 | AK6: 0.76078595 | AL6: 0.62121565 | AM6: 0.40229091 | AN6: 0.52416479 | AO6: 10.45024 | AP6: 0.065167124 | AQ6: 0.47598929 | AR6: 0.077753282 | AS6: 0.055707325 | AT6: 0.062671933 | AU6: 28.709259 | AV6: 402.52785 | AW6: 2.6558165 | AX6: 12090.688 | AY6: 0.96387781 | AZ6: 0.028456625 | BA6: 0.29297865 | BB6: 12.456639 | BC6: 277.13534 | BD6: 4385.9634 | BE6: 0.088943908 | BF6: 0.61952657 | BG6: 44.855835 | BH6: 2.1532612 | BI6: 14.762971 | BJ6: 20.40651 | BK6: 7.4743084 | BL6: 12.024632 | BM6: 0.80278958 | BN6: 0.68757086 | BO6: 133.6114 | BP6: 0.22205855 | BQ6: 947.57032 | BR6: 357.35736 | BS6: 43.808221 | BT6: 354.48805 | BU6: 180.63426 | BV6: 2.8571215 | BW6: 249.91177 | BX6: 0 | BY6: 180926.42 | BZ6: 150718.72 | CA6: 48.304678 | CB6: 0 | CC6: 71191.699 | CD6: 3188.2578 | CE6: -8036.3973 | CF6: 217110.58 | CG6: 398037 | CI6: =CF6/CG6 -> 0.54545327
A7: S02 | B7: Pecuária, inclusive o apoio à pecuária | C7: 2 | D7: 1004.9599 | E7: 6106.8111 | F7: 183.36264 | G7: 3.7251917 | H7: 22.939 | I7: 1.9494384 | J7: 3.2441343 | K7: 84046.279 | L7: 152.99908 | M7: 4376.6755 | N7: 64.457872 | O7: 192.81143 | P7: 250.2414 | Q7: 190.38282 | R7: 6.6377087 | S7: 143.03866 | T7: 239.09947 | U7: 0.46679488 | V7: 0.72657442 | W7: 0.018633166 | X7: 0.0001190597 | Y7: 178.77565 | Z7: 46.126672 | AA7: 7.8961205 | AB7: 5.0532195 | AC7: 5.4165196 | AD7: 52.888428 | AE7: 56.619524 | AF7: 70.6231 | AG7: 49.444454 | AH7: 2.5281526 | AI7: 0.71683903 | AJ7: 0.95724033 | AK7: 1.7317397 | AL7: 1.242744 | AM7: 0.99247143 | AN7: 0.87514563 | AO7: 7.2734053 | AP7: 0.23085892 | AQ7: 0.79136222 | AR7: 0.12926974 | AS7: 0.092616943 | AT7: 0.16790002 | AU7: 5.6993907 | AV7: 751.8631 | AW7: 3.5113748 | AX7: 386.78199 | AY7: 1.0736839 | AZ7: 0.037829304 | BA7: 0.34145151 | BB7: 22.136468 | BC7: 331.24359 | BD7: 1919.459 | BE7: 0.21618546 | BF7: 1.1913409 | BG7: 80.686603 | BH7: 4.2899018 | BI7: 25.488379 | BJ7: 38.429739 | BK7: 6.829628 | BL7: 14.52577 | BM7: 6.4682792 | BN7: 1.1312263 | BO7: 36.689298 | BP7: 0.34850966 | BQ7: 301.70844 | BR7: 120.20425 | BS7: 17.204426 | BT7: 110.89112 | BU7: 110.42372 | BV7: 3.3228892 | BW7: 37.971527 | BX7: 0 | BY7: 101821.57 | BZ7: 7635.5157 | CA7: 3.1875319 | CB7: 0 | CC7: 27053.775 | CD7: 16625.08 | CE7: -1180.1272 | CF7: 50137.431 | CG7: 151959 | CI7: =CF7/CG7 -> 0.32994052
A8: S03 | B8: Produção florestal; pesca e aquicultura | C8: 3 | D8: 1414.9162 | E8: 1437.2819 | F8: 2063.4117 | G8: 1.7907537 | H8: 1.8236877 | I8: 0.17010573 | J8: 0.24112751 | K8: 1830.067 | L8: 0.62916373 | M8: 261.16769 | N8: 13.874288 | O8: 13.085165 | P8: 25.024372 | Q8: 8.2471144 | R8: 6.78895 | S8: 1995.4595 | T8: 3242.7461 | U8: 0.035396002 | V8: 0.056630047 | W8: 0.0014522904 | X8: 9.2796503e-06 | Y8: 3.6633906 | Z8: 162.13204 | AA8: 2.8177035 | AB8: 0.084317617 | AC8: 0.12671282 | AD8: 713.86171 | AE8: 59.563969 | AF8: 910.44283 | AG8: 3.7053405 | AH8: 5.5140517 | AI8: 0.069501986 | AJ8: 0.088522362 | AK8: 0.17941951 | AL8: 0.11471484 | AM8: 0.093657764 | AN8: 0.076952408 | AO8: 2.773387 | AP8: 0.02522399 | AQ8: 0.094589682 | AR8: 0.015451311 | AS8: 0.011070287 | AT8: 0.019459657 | AU8: 0.4257136 | AV8: 759.42361 | AW8: 0.27333371 | AX8: 161.92523 | AY8: 0.099740228 | AZ8: 0.0030144069 | BA8: 0.027363157 | BB8: 1.6585272 | BC8: 42.674553 | BD8: 549.53668 | BE8: 0.021951251 | BF8: 0.10959413 | BG8: 5.9766224 | BH8: 0.36575555 | BI8: 1.9402982 | BJ8: 2.9162219 | BK8: 0.52073673 | BL8: 3.7816158 | BM8: 0.083967239 | BN8: 0.095237422 | BO8: 2.6303824 | BP8: 0.029566698 | BQ8: 91.342914 | BR8: 66.866054 | BS8: 8.8889308 | BT8: 63.403735 | BU8: 19.813852 | BV8: 0.24397311 | BW8: 2.9434756 | BX8: 0 | BY8: 15970.315 | BZ8: 3068.1586 | CA8: 2.4427056 | CB8: 0 | CC8: 17611.77 | CD8: 1054.003 | CE8: 163.3106 | CF8: 21899.685 | CG8: 37870 | CI8: =CF8/CG8 -> 0.57828585
A9: S04 | B9: Extração de carvão mineral e de minerais não-metálicos | C9: 4 | D9: 154.57131 | E9: 418.65628 | F9: 13.284636 | G9: 255.38746 | H9: 731.23872 | I9: 0.30874708 | J9: 1.3587158 | K9: 53.244166 | L9: 8.1587147 | M9: 279.65589 | N9: 16.421368 | O9: 0.065622521 | P9: 0.97438319 | Q9: 0.29823967 | R9: 0.94713613 | S9: 0.22325809 | T9: 18.581952 | U9: 0.14003746 | V9: 6.1948655 | W9: 0.1589928 | X9: 0.0058538919 | Y9: 219.10581 | Z9: 2854.8663 | AA9: 68.702101 | AB9: 8.0050703 | AC9: 1.8960083 | AD9: 6.7281211 | AE9: 4463.2487 | AF9: 1496.018 | AG9: 337.50822 | AH9: 3.5700793 | AI9: 0.34796092 | AJ9: 35.919486 | AK9: 2.5200509 | AL9: 18.623404 | AM9: 34.401273 | AN9: 1.7813222 | AO9: 31.983519 | AP9: 2.7992514 | AQ9: 235.19416 | AR9: 5.7714331 | AS9: 1.184596 | AT9: 1.2563515 | AU9: 356.51608 | AV9: 5769.238 | AW9: 2.9175716 | AX9: 79.436083 | AY9: 0.65802409 | AZ9: 0.02811291 | BA9: 0.057457623 | BB9: 4.3639196 | BC9: 2.4382302 | BD9: 15.584106 | BE9: 0.087448574 | BF9: 0.1645093 | BG9: 0.76492018 | BH9: 0.61648428 | BI9: 1.6296091 | BJ9: 369.75982 | BK9: 1.5956916 | BL9: 1.1474393 | BM9: 0.42774142 | BN9: 0.35090323 | BO9: 2.106388 | BP9: 0.086702237 | BQ9: 71.223802 | BR9: 16.960069 | BS9: 1.5619518 | BT9: 6.8222989 | BU9: 5.5002185 | BV9: 1.1191405 | BW9: 4.310632 | BX9: 0 | BY9: 18508.781 | BZ9: 1808.1263 | CA9: 0.074826886 | CB9: 0 | CC9: 199.54565 | CD9: 9.7663346 | CE9: -515.2941 | CF9: 1502.2191 | CG9: 20011 | CI9: =CF9/CG9 -> 0.075069665
A10: S05 | B10: Extração de petróleo e gás, inclusive as atividades de apoio | C10: 5 | D10: 21.840529 | E10: 15.400401 | F10: 0.88883243 | G10: 2.8557716 | H10: 6630.1612 | I10: 276.15336 | J10: 28.805251 | K10: 63.705839 | L10: 0.44529788 | M10: 591.27168 | N10: 106.02011 | O10: 0.12079151 | P10: 91.397968 | Q10: 0.98598288 | R10: 1.5852201 | S10: 39.944558 | T10: 541.2167 | U10: 0.14283782 | V10: 106597.07 | W10: 2746.8599 | X10: 590.10146 | Y10: 1.2543756 | Z10: 1369.8245 | AA10: 67.887327 | AB10: 24.388558 | AC10: 28.616612 | AD10: 80.815094 | AE10: 444.90473 | AF10: 358.13112 | AG10: 243.1048 | AH10: 282.1276 | AI10: 1.128992 | AJ10: 26.624933 | AK10: 19.396171 | AL10: 62.055893 | AM10: 126.58879 | AN10: 1.6722904 | AO10: 2.9946627 | AP10: 6.2288933 | AQ10: 3962.6267 | AR10: 1.0026425 | AS10: 0.71835594 | AT10: 5204.7213 | AU10: 522.87686 | AV10: 571.58375 | AW10: 9.6259108 | AX10: 157.08909 | AY10: 72.420509 | AZ10: 0.79119726 | BA10: 0.27180433 | BB10: 47.629023 | BC10: 3.4384093 | BD10: 49.277023 | BE10: 0.46020694 | BF10: 1.2321138 | BG10: 87.263751 | BH10: 4.8051068 | BI10: 13.428733 | BJ10: 6.8459631 | BK10: 13.309644 | BL10: 55.849417 | BM10: 3.1144653 | BN10: 5.7667873 | BO10: 9.2018492 | BP10: 0.72124886 | BQ10: 1045.7362 | BR10: 8.0402548 | BS10: 12.284845 | BT10: 1.4955079 | BU10: 7.5123371 | BV10: 9.5743714 | BW10: 21.701482 | BX10: 0 | BY10: 133407.14 | BZ10: 92727.09 | CA10: 0 | CB10: 0 | CC10: 602.27835 | CD10: 11369.449 | CE10: -12167.956 | CF10: 92530.862 | CG10: 225938 | CI10: =CF10/CG10 -> 0.40954095
A11: S06 | B11: Extração de minério de ferro, inclusive beneficiamentos e a aglomeração | C11: 6 | D11: 0.13674266 | E11: 0.077076579 | F11: 0.0079907095 | G11: 0.02196498 | H11: 2.3512303 | I11: 1793.5447 | J11: 45.052166 | K11: 0.48557035 | L11: 0.032457224 | M11: 0.34478482 | N11: 0.27770406 | O11: 0.063359672 | P11: 0.043394837 | Q11: 0.095809719 | R11: 0.10896933 | S11: 0.074421837 | T11: 0.14841067 | U11: 0.014610975 | V11: 0.14103175 | W11: 0.0036167913 | X11: 2.3110087e-05 | Y11: 0.017588449 | Z11: 0.34414227 | AA11: 0.11931618 | AB11: 0.21383963 | AC11: 0.70292247 | AD11: 0.20161083 | AE11: 106.29352 | AF11: 16914.009 | AG11: 123.08645 | AH11: 0.096515193 | AI11: 0.2311134 | AJ11: 0.55081086 | AK11: 4.5165857 | AL11: 1.1407709 | AM11: 0.66480908 | AN11: 0.23246828 | AO11: 0.11436779 | AP11: 2.6358292 | AQ11: 0.28979805 | AR11: 0.047338775 | AS11: 0.033916466 | AT11: 0.019881708 | AU11: 0.072340698 | AV11: 1.2898289 | AW11: 0.20090651 | AX11: 1.8876588 | AY11: 0.11844738 | AZ11: 0.04249387 | BA11: 0.0099650457 | BB11: 0.14510725 | BC11: 0.043813445 | BD11: 0.31459912 | BE11: 0.020385269 | BF11: 0.020853743 | BG11: 0.29065394 | BH11: 0.36060677 | BI11: 0.19109174 | BJ11: 0.07465067 | BK11: 0.16290206 | BL11: 6.5571966 | BM11: 0.053040758 | BN11: 0.12392835 | BO11: 0.64194197 | BP11: 0.010178673 | BQ11: 0.14299228 | BR11: 0.052338503 | BS11: 0.14785893 | BT11: 0.091322143 | BU11: 0.22754425 | BV11: 0.11034237 | BW11: 0.13327856 | BX11: 0 | BY11: 19012.127 | BZ11: 65510.697 | CA11: 0.014070934 | CB11: 0 | CC11: 7.116125 | CD11: 145.98411 | CE11: 7650.0619 | CF11: 73313.873 | CG11: 92326 | CI11: =CF11/CG11 -> 0.79407613
A12: S07 | B12: Extração de minerais metálicos não-ferrosos, inclusive beneficiamentos | C12: 7 | D12: 4.6695015 | E12: 2.628304 | F12: 0.12435658 | G12: 1.2402923 | H12: 68.177003 | I12: 10.656378 | J12: 810.56588 | K12: 6.0089169 | L12: 0.15093813 | M12: 12.972218 | N12: 1.4659626 | O12: 0.0030025647 | P12: 0.16470019 | Q12: 0.037493815 | R12: 0.28587826 | S12: 0.12078567 | T12: 5.8959539 | U12: 3.4978879 | V12: 0.045892973 | W12: 0.0011822536 | X12: 0.00021491581 | Y12: 0.99308581 | Z12: 30.317773 | AA12: 5.272019 | AB12: 1.7076522 | AC12: 0.54015883 | AD12: 7.8003983 | AE12: 52.370365 | AF12: 1602.2277 | AG12: 5411.8108 | AH12: 31.658929 | AI12: 2.4799909 | AJ12: 79.4302 | AK12: 12.403471 | AL12: 8.4362246 | AM12: 49.252453 | AN12: 12.92217 | AO12: 30.016131 | AP12: 5.5688269 | AQ12: 0.38191835 | AR12: 0.06238671 | AS12: 0.044697749 | AT12: 0.002747953 | AU12: 3.6386314 | AV12: 59.821666 | AW12: 0.56351331 | AX12: 3.5850876 | AY12: 0.16152433 | AZ12: 0 | BA12: 0.0036377033 | BB12: 0.073311621 | BC12: 0.0046298042 | BD12: 0.25629273 | BE12: 0.00037532059 | BF12: 0 | BG12: 0.012010259 | BH12: 0.01938281 | BI12: 0.015203035 | BJ12: 2.0032489 | BK12: 0.23876561 | BL12: 0.70972307 | BM12: 0.0016222907 | BN12: 0.0054421485 | BO12: 0.26001967 | BP12: 0 | BQ12: 0.51230206 | BR12: 0.19266821 | BS12: 0.00018766029 | BT12: 0.41110175 | BU12: 0.71872299 | BV12: 0 | BW12: 0.38814583 | BX12: 0 | BY12: 8348.0101 | BZ12: 11140.001 | CA12: 0 | CB12: 0 | CC12: 7.4490404 | CD12: 8.4306387 | CE12: -1230.8903 | CF12: 9924.9899 | CG12: 18273 | CI12: =CF12/CG12 -> 0.54315054
A13: S08 | B13: Abate e produtos de carne, inclusive os produtos do laticínio e da pesca | C13: 8 | D13: 73.15487 | E13: 2090.4666 | F13: 38.303224 | G13: 9.9476144 | H13: 19.441015 | I13: 17.034337 | J13: 3.2840564 | K13: 22154.159 | L13: 1.0823479 | M13: 2486.5336 | N13: 47.126808 | O13: 2.4639672 | P13: 7.0604126 | Q13: 8.6616937 | R13: 1473.7109 | S13: 5.5399254 | T13: 15.727026 | U13: 3.1952587 | V13: 23.045817 | W13: 0.59120438 | X13: 0.011154334 | Y13: 737.52755 | Z13: 29.649497 | AA13: 44.063117 | AB13: 1728.7212 | AC13: 13.395568 | AD13: 28.418666 | AE13: 9.9546155 | AF13: 10.274331 | AG13: 5.788068 | AH13: 65.983484 | AI13: 13.052513 | AJ13: 11.427341 | AK13: 65.885116 | AL13: 13.947594 | AM13: 8.0334682 | AN13: 3.9970415 | AO13: 12.233521 | AP13: 40.666301 | AQ13: 4.9078319 | AR13: 0.80169879 | AS13: 0.57438727 | AT13: 0.39508868 | AU13: 3.2880463 | AV13: 58.979781 | AW13: 7.2079814 | AX13: 448.87841 | AY13: 13.177598 | AZ13: 0.87761198 | BA13: 1.2127732 | BB13: 4.6743079 | BC13: 445.42571 | BD13: 17469.215 | BE13: 1.6282579 | BF13: 1.6628426 | BG13: 6.3279886 | BH13: 4.661158 | BI13: 8.4847063 | BJ13: 4.2251629 | BK13: 7.7048874 | BL13: 6.6234746 | BM13: 5.7445294 | BN13: 2.4002707 | BO13: 15.891834 | BP13: 0.73876873 | BQ13: 2176.6448 | BR13: 1294.0752 | BS13: 207.92015 | BT13: 1280.2889 | BU13: 750.19255 | BV13: 7.872699 | BW13: 194.08998 | BX13: 0 | BY13: 55760.354 | BZ13: 46170.634 | CA13: 72.403107 | CB13: 0 | CC13: 189902.01 | CD13: 408.57985 | CE13: 92.022182 | CF13: 236645.65 | CG13: 292406 | CI13: =CF13/CG13 -> 0.80930503
A14: S09 | B14: Fabricação e refino de açúcar | C14: 9 | D14: 53.525246 | E14: 87.091629 | F14: 2.3933686 | G14: 1.6267936 | H14: 330.37378 | I14: 22.21335 | J14: 3.8758144 | K14: 291.48502 | L14: 755.07055 | M14: 3193.1451 | N14: 671.87757 | O14: 0.80970769 | P14: 2.0182717 | Q14: 2.6748804 | R14: 2.0719631 | S14: 14.517455 | T14: 5.707496 | U14: 0.69458071 | V14: 7507.7582 | W14: 38.065829 | X14: 37.884553 | Y14: 641.94531 | Z14: 141.83333 | AA14: 414.07002 | AB14: 612.65487 | AC14: 355.93829 | AD14: 4.1415098 | AE14: 3.0130159 | AF14: 3.8189358 | AG14: 2.182539 | AH14: 17.070744 | AI14: 4.3963944 | AJ14: 6.2673357 | AK14: 94.892959 | AL14: 16.375697 | AM14: 2.8484954 | AN14: 3.8857596 | AO14: 3.4125174 | AP14: 59.620441 | AQ14: 4.5778112 | AR14: 0.74778963 | AS14: 0.53576336 | AT14: 0.18604367 | AU14: 10.534485 | AV14: 172.49428 | AW14: 139.72003 | AX14: 273.44868 | AY14: 351.88253 | AZ14: 3.0478343 | BA14: 9.5131123 | BB14: 24.925262 | BC14: 7.1586323 | BD14: 795.99698 | BE14: 2.2736976 | BF14: 4.3632644 | BG14: 12.172919 | BH14: 17.104176 | BI14: 62.695757 | BJ14: 8.9417937 | BK14: 62.340633 | BL14: 49.822366 | BM14: 19.535258 | BN14: 47.389975 | BO14: 66.916953 | BP14: 31.905779 | BQ14: 347.6269 | BR14: 93.441802 | BS14: 10.050684 | BT14: 71.418105 | BU14: 65.577576 | BV14: 9.0821778 | BW14: 75.349417 | BX14: 0 | BY14: 18266.028 | BZ14: 16586.094 | CA14: 0.75832747 | CB14: 0 | CC14: 16804.06 | CD14: 332.2654 | CE14: -434.20561 | CF14: 33288.972 | CG14: 51555 | CI14: =CF14/CG14 -> 0.64569823
A15: S10 | B15: Outros produtos alimentares | C15: 10 | D15: 1901.0055 | E15: 13289.225 | F15: 896.41033 | G15: 153.2433 | H15: 190.88615 | I15: 51.948534 | J15: 15.388239 | K15: 23451.189 | L15: 23.73499 | M15: 28439.3 | N15: 2077.0625 | O15: 14.848455 | P15: 56.298103 | Q15: 48.649656 | R15: 64.823663 | S15: 57.154409 | T15: 656.92772 | U15: 23.74503 | V15: 2090.5259 | W15: 13.734147 | X15: 9.9100746 | Y15: 3052.5007 | Z15: 488.08572 | AA15: 802.79043 | AB15: 1071.7383 | AC15: 229.29723 | AD15: 175.308 | AE15: 93.455962 | AF15: 91.502096 | AG15: 40.730426 | AH15: 88.811443 | AI15: 75.800275 | AJ15: 60.469387 | AK15: 109.61639 | AL15: 56.823494 | AM15: 43.043403 | AN15: 18.514591 | AO15: 81.249431 | AP15: 72.461506 | AQ15: 32.640495 | AR15: 5.3318544 | AS15: 3.8200747 | AT15: 1.9974554 | AU15: 32.438763 | AV15: 362.30878 | AW15: 131.80172 | AX15: 3488.1786 | AY15: 177.61548 | AZ15: 2.5711517 | BA15: 31.863844 | BB15: 38.202178 | BC15: 243.18735 | BD15: 12354.485 | BE15: 10.176693 | BF15: 10.564222 | BG15: 46.146675 | BH15: 27.97588 | BI15: 179.04353 | BJ15: 39.398785 | BK15: 74.566393 | BL15: 36.341617 | BM15: 66.42593 | BN15: 23.287125 | BO15: 77.880838 | BP15: 12.251409 | BQ15: 1527.907 | BR15: 1168.2631 | BS15: 166.10331 | BT15: 1598.3147 | BU15: 711.43383 | BV15: 52.378456 | BW15: 738.0151 | BX15: 0 | BY15: 103651.13 | BZ15: 40248.49 | CA15: 79.511138 | CB15: 0 | CC15: 177717.31 | CD15: 617.39769 | CE15: 2629.1666 | CF15: 221291.87 | CG15: 324943 | CI15: =CF15/CG15 -> 0.68101751
A16: S11 | B16: Fabricação de bebidas | C16: 11 | D16: 14.73899 | E16: 9.3559629 | F16: 0.76997094 | G16: 5.2965241 | H16: 13.258631 | I16: 7.7752004 | J16: 1.7552234 | K16: 397.9374 | L16: 1.2398412 | M16: 99.164789 | N16: 6639.8139 | O16: 1.607351 | P16: 4.5283349 | Q16: 5.5452055 | R16: 4.3324331 | S16: 4.1709141 | T16: 8.1110653 | U16: 1.6440958 | V16: 62.724309 | W16: 0.63813413 | X16: 0.24728806 | Y16: 3.2332953 | Z16: 10.807878 | AA16: 13.785349 | AB16: 11.285939 | AC16: 8.407027 | AD16: 10.372939 | AE16: 5.7335931 | AF16: 10.690565 | AG16: 3.6727054 | AH16: 20.532547 | AI16: 9.8421771 | AJ16: 9.681718 | AK16: 31.591531 | AL16: 12.546867 | AM16: 8.0829596 | AN16: 5.4079929 | AO16: 8.3460781 | AP16: 19.980903 | AQ16: 8.2460964 | AR16: 1.3470073 | AS16: 0.96508049 | AT16: 0.45259475 | AU16: 3.0293874 | AV16: 69.490475 | AW16: 10.121867 | AX16: 107.19138 | AY16: 17.00447 | AZ16: 0.45098489 | BA16: 8.1017402 | BB16: 6.2954672 | BC16: 450.04095 | BD16: 26011.353 | BE16: 1.2831512 | BF16: 1.6703356 | BG16: 6.6399483 | BH16: 5.1156866 | BI16: 98.337038 | BJ16: 6.2222205 | BK16: 12.41899 | BL16: 3.020191 | BM16: 4.3590942 | BN16: 2.9262015 | BO16: 13.385941 | BP16: 1.1279803 | BQ16: 100.9831 | BR16: 69.203497 | BS16: 17.627628 | BT16: 72.575288 | BU16: 174.85303 | BV16: 28.677202 | BW16: 19.690719 | BX16: 0 | BY16: 34822.866 | BZ16: 2978.2515 | CA16: 1.7119308 | CB16: 0 | CC16: 40937.66 | CD16: 99.164106 | CE16: -295.65319 | CF16: 43721.134 | CG16: 78544 | CI16: =CF16/CG16 -> 0.55664512
A17: S12 | B17: Fabricação de produtos do fumo | C17: 12 | D17: 1.8863692 | E17: 0.9809415 | F17: 0.089514122 | G17: 0.088027857 | H17: 2.1983798 | I17: 2.4823702 | J17: 0.38449654 | K17: 3.1242665 | L17: 0.08724313 | M17: 3.0183844 | N17: 0.69678189 | O17: 304.40931 | P17: 0.50326689 | Q17: 0.6927617 | R17: 0.57329707 | S17: 0.29665773 | T17: 0.77841528 | U17: 0.1475926 | V17: 1.9269422 | W17: 0.04941687 | X17: 0.00031575728 | Y17: 0.17235201 | Z17: 1.1070472 | AA17: 0.63432236 | AB17: 0.4849366 | AC17: 0.79277348 | AD17: 0.99845903 | AE17: 0.6455419 | AF17: 0.71252419 | AG17: 0.61963993 | AH17: 0.72265568 | AI17: 1.1712195 | AJ17: 1.1271924 | AK17: 9.9519577 | AL17: 1.7055668 | AM17: 0.71215732 | AN17: 0.50240734 | AO17: 0.67606475 | AP17: 6.042271 | AQ17: 0.46340185 | AR17: 0.075697113 | AS17: 0.054234156 | AT17: 0.031969707 | AU17: 0.18846967 | AV17: 5.1648107 | AW17: 0.45008789 | AX17: 3.6160293 | AY17: 1.1145936 | AZ17: 0.10844203 | BA17: 0.10146145 | BB17: 0.28571454 | BC17: 0.1431338 | BD17: 2.3330807 | BE17: 0.14060472 | BF17: 0.12207898 | BG17: 0.53625142 | BH17: 0.43983917 | BI17: 0.45998094 | BJ17: 0.24562702 | BK17: 0.37100818 | BL17: 1.3352302 | BM17: 0.34056163 | BN17: 0.16603915 | BO17: 1.6680395 | BP17: 0.047183572 | BQ17: 0.73080867 | BR17: 0.48670412 | BS17: 0.26664794 | BT17: 0.6912563 | BU17: 1.7783447 | BV17: 0.16768687 | BW17: 0.52694909 | BX17: 0 | BY17: 377.84581 | BZ17: 6460.6451 | CA17: 0.19900321 | CB17: 0 | CC17: 7980.5129 | CD17: 100.82736 | CE17: 773.96982 | CF17: 15316.154 | CG17: 15694 | CI17: =CF17/CG17 -> 0.97592419
... A23: S18 | B23: Impressão e reprodução de gravações | C23: 18 | D23: 13.339322 | E23: 3.1329614 | F23: 2.4387296 | G23: 0.41174963 | H23: 6.618274 | I23: 14.804113 | J23: 3.8701545 | K23: 85.18641 | L23: 11.087753 | M23: 114.1104 | N23: 221.79901 | O23: 5.1576768 | P23: 17.391981 | Q23: 19.532919 | R23: 12.239218 | S23: 28.701402 | T23: 196.93696 | U23: 996.48162 | V23: 8.9755705 | W23: 0.23020988 | X23: 0.0026149487 | Y23: 9.8994417 | Z23: 5.5179687 | AA23: 23.272288 | AB23: 16.904612 | AC23: 18.810886 | AD23: 61.632087 | AE23: 25.164052 | AF23: 18.243605 | AG23: 1.7709166 | AH23: 31.445401 | AI23: 194.60325 | AJ23: 13.867941 | AK23: 22.02342 | AL23: 28.005186 | AM23: 28.218372 | AN23: 5.3995951 | AO23: 39.211127 | AP23: 3.8478855 | AQ23: 22.346286 | AR23: 3.6502861 | AS23: 2.6152938 | AT23: 5.3059561 | AU23: 11.366928 | AV23: 71.515594 | AW23: 111.40669 | AX23: 6729.9426 | AY23: 56.857713 | AZ23: 1.7187504 | BA23: 33.680218 | BB23: 63.906745 | BC23: 10.455078 | BD23: 101.21687 | BE23: 1189.4141 | BF23: 211.9362 | BG23: 605.27134 | BH23: 538.32545 | BI23: 1458.0066 | BJ23: 330.83617 | BK23: 556.47461 | BL23: 226.79439 | BM23: 2104.0794 | BN23: 63.744541 | BO23: 1293.0832 | BP23: 2.9332676 | BQ23: 1054.3199 | BR23: 222.82942 | BS23: 41.71413 | BT23: 89.60547 | BU23: 103.38245 | BV23: 328.68184 | BW23: 344.79312 | BX23: 0 | BY23: 20302.498 | BZ23: 176.53574 | CA23: 0.26935788 | CB23: 0 | CC23: 1258.4005 | CD23: 40.666816 | CE23: -445.37025 | CF23: 1030.5022 | CG23: 21333 | CI23: =CF23/CG23 -> 0.048305546
A24: S19 | B24: Derivados de petróleo | C24: 19 | D24: 12522.633 | E24: 4529.1577 | F24: 691.20361 | G24: 1123.6606 | H24: 3436.5901 | I24: 4990.8882 | J24: 1243.4586 | K24: 3099.5979 | L24: 901.23197 | M24: 3777.556 | N24: 721.48778 | O24: 19.753752 | P24: 252.82664 | Q24: 105.14507 | R24: 196.64051 | S24: 273.71901 | T24: 2024.9338 | U24: 22.932426 | V24: 110832.26 | W24: 2852.6018 | X24: 913.18108 | Y24: 372.77801 | Z24: 10873.963 | AA24: 960.79738 | AB24: 470.12621 | AC24: 187.46502 | AD24: 1671.0652 | AE24: 2993.1382 | AF24: 1853.8129 | AG24: 2401.5901 | AH24: 412.73978 | AI24: 196.80683 | AJ24: 532.91945 | AK24: 438.35205 | AL24: 997.16559 | AM24: 366.59462 | AN24: 99.828542 | AO24: 264.11534 | AP24: 340.00152 | AQ24: 2403.6211 | AR24: 392.5614 | AS24: 281.25559 | AT24: 39.351035 | AU24: 1057.6584 | AV24: 6560.9162 | AW24: 959.18197 | AX24: 15601.925 | AY24: ='Fluxos Energia'!H17 -> 0 | AZ24: 1664.3254 | BA24: 6710.9881 | BB24: 2004.3535 | BC24: 84.590636 | BD24: 2272.9757 | BE24: 23.045753 | BF24: 58.727795 | BG24: 89.357007 | BH24: 172.0103 | BI24: 598.21743 | BJ24: 101.5923 | BK24: 574.34079 | BL24: 407.75519 | BM24: 131.53973 | BN24: 708.48834 | BO24: 565.4077 | BP24: 427.26512 | BQ24: 2331.4275 | BR24: 334.3395 | BS24: 129.02051 | BT24: 80.289528 | BU24: 348.12058 | BV24: 142.96644 | BW24: 710.68955 | BX24: 0 | BY24: 300268.86 | BZ24: 21129.468 | CA24: 0 | CB24: 0 | CC24: 117714.64 | CD24: 1.4315587 | CE24: -5303.1362 | CF24: 133542.4 | CG24: 433811.27 | CI24: =CF24/CG24 -> 0.30783526
A25: S20 | B25: Biodiesel | C25: 20 | D25: 800.98709 | E25: 228.31395 | F25: 42.842108 | G25: 49.015375 | H25: 29.475244 | I25: 349.95762 | J25: 66.507065 | K25: 152.9996 | L25: 66.775695 | M25: 217.49628 | N25: 35.430375 | O25: 1.2241022 | P25: 0.087468574 | Q25: 0.041680128 | R25: 0.052176194 | S25: 0.70663884 | T25: 36.050745 | U25: 1.6231507 | V25: 4.9463166 | W25: 0.12740009 | X25: 0.022286903 | Y25: 830.99987 | Z25: 88.073226 | AA25: 26.38525 | AB25: 22.196834 | AC25: 15.228425 | AD25: 59.441331 | AE25: 62.487077 | AF25: 53.695921 | AG25: 14.697807 | AH25: 22.597382 | AI25: 14.780254 | AJ25: 16.201305 | AK25: 18.656442 | AL25: 66.238087 | AM25: 15.162336 | AN25: 6.2855793 | AO25: 16.047931 | AP25: 15.826858 | AQ25: 1.0453907 | AR25: 0.17033482 | AS25: 0.12203854 | AT25: 0.020696438 | AU25: 0.84012606 | AV25: 314.86489 | AW25: 14.792995 | AX25: 747.61132 | AY25: ='Fluxos Energia'!H18 -> 57202.593 | AZ25: 0.84983695 | BA25: 32.271138 | BB25: 102.63218 | BC25: 1.5996283 | BD25: 1.1177232 | BE25: 0.21533387 | BF25: 0.75360202 | BG25: 0.52129845 | BH25: 0.78407177 | BI25: 2.7230786 | BJ25: 0.56868637 | BK25: 2.614969 | BL25: 2.1615132 | BM25: 0.55949069 | BN25: 8.141389 | BO25: 2.5664202 | BP25: 24.202501 | BQ25: 7.0732373 | BR25: 0.70014748 | BS25: 6.9915698 | BT25: 0.20172778 | BU25: 4.8962953 | BV25: 4.0101392 | BW25: 16.713675 | BX25: 0 | BY25: 9935.2017 | BZ25: 421.58378 | CA25: 0 | CB25: 0 | CC25: 43.723355 | CD25: 0.48795202 | CE25: -15.134627 | CF25: 450.66046 | CG25: 10385.862 | CI25: =CF25/CG25 -> 0.043391724
A26: S21 | B26: Coquerias | C26: 21 | D26: 3.0975998 | E26: 2.6317442 | F26: 0.25045315 | G26: 1.1454318 | H26: 63.643881 | I26: 25.411817 | J26: 4.7089033 | K26: 1.4120661 | L26: 0.022448833 | M26: 0.73106478 | N26: 0.31731661 | O26: 0.0042146732 | P26: 0.073819092 | Q26: 0.0018262356 | R26: 0.068517284 | S26: 0.41032361 | T26: 0.80412552 | U26: 0.0042380244 | V26: 111.54951 | W26: 15.910303 | X26: 1312.4123 | Y26: 0.0033455572 | Z26: 3.6823053 | AA26: 0.54571521 | AB26: 0.20430784 | AC26: 0.023745336 | AD26: 0.91186851 | AE26: 18.895062 | AF26: 1035.1843 | AG26: 27.184975 | AH26: 20.278543 | AI26: 0.11311616 | AJ26: 81.72658 | AK26: 26.20013 | AL26: 22.452422 | AM26: 41.159031 | AN26: 2.3537012 | AO26: 10.863704 | AP26: 29.206644 | AQ26: 4.8418515 | AR26: 0.79068717 | AS26: 0.56649785 | AT26: 0.080074453 | AU26: 0.42937544 | AV26: 3.1763959 | AW26: 2.2347958 | AX26: 8.1256855 | AY26: 81.92363 | AZ26: 0.47737029 | BA26: 20.979156 | BB26: 0.5103159 | BC26: 0.16350879 | BD26: 2.3645019 | BE26: 0.059745756 | BF26: 0.13976577 | BG26: 0.24553159 | BH26: 0.47845516 | BI26: 1.6627307 | BJ26: 0.27622412 | BK26: 1.5968385 | BL26: 0.93384181 | BM26: 0.32403957 | BN26: 1.3773637 | BO26: 1.5326188 | BP26: 0.31426729 | BQ26: 4.6276771 | BR26: 0.47313427 | BS26: 0.11307741 | BT26: 0.12320487 | BU26: 0.75881367 | BV26: 0.26476191 | BW26: 0.95884654 | BX26: 0 | BY26: 3008.5262 | BZ26: 51.537175 | CA26: 0 | CB26: 0 | CC26: 245.8714 | CD26: 0 | CE26: -2.0634016 | CF26: 295.34518 | CG26: 3303.8714 | CI26: =CF26/CG26 -> 0.089393667
A27: S22 | B27: Fabricação de biocombustíveis | C27: 22 | D27: 79.900399 | E27: 99.636051 | F27: 3.1945139 | G27: 2.506321 | H27: 632.5737 | I27: 6.4954438 | J27: 1.6063796 | K27: 227.81004 | L27: 193.42907 | M27: 910.61411 | N27: 183.16587 | O27: 0.19687255 | P27: 1.4072229 | Q27: 0.96640033 | R27: 1.1141634 | S27: 26.899323 | T27: 9.3848407 | U27: 0.67263277 | V27: 15110.474 | W27: 76.356762 | X27: 76.309221 | Y27: 457.97466 | Z27: 296.72565 | AA27: 299.30408 | AB27: 1246.3545 | AC27: 713.90218 | AD27: 7.757368 | AE27: 2.9343726 | AF27: 3.476092 | AG27: 1.4932503 | AH27: 31.020153 | AI27: 1.4933829 | AJ27: 3.8333237 | AK27: 25.744485 | AL27: 15.046529 | AM27: 2.8046129 | AN27: 1.1816601 | AO27: 3.5941609 | AP27: 16.582466 | AQ27: 6.1615524 | AR27: 1.0064952 | AS27: 0.72111623 | AT27: 0.14624502 | AU27: 19.763071 | AV27: 293.64415 | AW27: 274.54746 | AX27: 499.37374 | AY27: ='Fluxos Energia'!H19 -> 1699.0902 | AZ27: 4.3904134 | BA27: 18.370765 | BB27: 45.122455 | BC27: 9.6670383 | BD27: 267.1649 | BE27: 3.5708401 | BF27: 7.7979006 | BG27: 19.931212 | BH27: 31.08543 | BI27: 116.31031 | BJ27: 14.918811 | BK27: 120.40394 | BL27: 94.92334 | BM27: 37.083554 | BN27: 94.076893 | BO27: 113.06572 | BP27: 63.778652 | BQ27: 545.14846 | BR27: 77.529339 | BS27: 7.9860567 | BT27: 31.915945 | BU27: 89.58174 | BV27: 15.024298 | BW27: 141.68801 | BX27: 0 | BY27: 24543.173 | BZ27: 5351.6554 | CA27: 0.20439016 | CB27: 0 | CC27: 24299.633 | CD27: 72.643596 | CE27: 369.69064 | CF27: 30093.827 | CG27: 54637 | CI27: =CF27/CG27 -> 0.55079575
A28: S23 | B28: Fabricação de químicos orgânicos e inorgânicos, resinas e elastômeros | C28: 23 | D28: 45933.044 | E28: 4700.5044 | F28: 342.73136 | G28: 238.96792 | H28: 4857.5133 | I28: 340.81704 | J28: 131.04423 | K28: 458.64652 | L28: 172.19125 | M28: 1063.8134 | N28: 94.697046 | O28: 16.378012 | P28: 3539.8888 | Q28: 140.25019 | R28: 1473.9022 | S28: 677.61342 | T28: 4354.2764 | U28: 67.362735 | V28: 2393.0475 | W28: 61.872098 | X28: 98.627655 | Y28: 648.58313 | Z28: 32375.577 | AA28: 12475.943 | AB28: 4409.2644 | AC28: 1782.2172 | AD28: 16336.884 | AE28: 2295.3151 | AF28: 973.06272 | AG28: 908.00851 | AH28: 1236.0286 | AI28: 176.46663 | AJ28: 2291.5755 | AK28: 179.95359 | AL28: 154.70952 | AM28: 1135.6976 | AN28: 253.54153 | AO28: 1680.149 | AP28: 172.4995 | AQ28: 136.21436 | AR28: 22.25074 | AS28: 15.941825 | AT28: 1.9475205 | AU28: 656.55925 | AV28: 483.24644 | AW28: 95.956964 | AX28: 1195.4936 | AY28: 117.98955 | AZ28: 2.4453832 | BA28: 4.7189596 | BB28: 50.015835 | BC28: 21.034007 | BD28: 166.06271 | BE28: 6.5973101 | BF28: 11.591103 | BG28: 36.65003 | BH28: 29.675183 | BI28: 81.330392 | BJ28: 75.323321 | BK28: 83.229416 | BL28: 53.316175 | BM28: 26.321729 | BN28: 24.461215 | BO28: 117.98117 | BP28: 4.1900923 | BQ28: 83.0922 | BR28: 74.527759 | BS28: 72.118323 | BT28: 277.19833 | BU28: 554.07565 | BV28: 57.260419 | BW28: 364.80967 | BX28: 0 | BY28: 155646.29 | BZ28: 19441.066 | CA28: 11.449279 | CB28: 0 | CC28: 3542.3546 | CD28: 713.95055 | CE28: 150.8875 | CF28: 23859.708 | CG28: 179506 | CI28: =CF28/CG28 -> 0.13291872
A29: S24 | B29: Fabricação de defensivos, desinfestantes, tintas e químicos diversos | C29: 24 | D29: 23436.868 | E29: 2659.0458 | F29: 87.893459 | G29: 1560.7928 | H29: 575.39185 | I29: 277.1698 | J29: 112.62711 | K29: 839.4749 | L29: 34.24234 | M29: 2339.5946 | N29: 116.42229 | O29: 5.054892 | P29: 306.23554 | Q29: 43.171646 | R29: 206.63342 | S29: 705.30913 | T29: 1430.9481 | U29: 638.57582 | V29: 388.26299 | W29: 9.8737706 | X29: 2.8454792 | Y29: 164.27653 | Z29: 2006.7763 | AA29: 9284.6465 | AB29: 1704.2634 | AC29: 864.88759 | AD29: 2767.0057 | AE29: 906.56114 | AF29: 446.19847 | AG29: 91.701863 | AH29: 559.00558 | AI29: 194.65756 | AJ29: 204.95976 | AK29: 175.09466 | AL29: 497.86933 | AM29: 231.01984 | AN29: 111.28724 | AO29: 540.55535 | AP29: 671.10572 | AQ29: 126.61999 | AR29: 20.588789 | AS29: 14.748137 | AT29: 1.7755108 | AU29: 331.61133 | AV29: 7547.2977 | AW29: 879.46696 | AX29: 1715.188 | AY29: 224.13311 | AZ29: 0.97484303 | BA29: 3.4208214 | BB29: 54.346922 | BC29: 27.371451 | BD29: 87.89679 | BE29: 89.460215 | BF29: 113.90617 | BG29: 21.411489 | BH29: 17.569591 | BI29: 66.398663 | BJ29: 1157.331 | BK29: 41.75966 | BL29: 42.798939 | BM29: 35.716779 | BN29: 22.450403 | BO29: 1733.3356 | BP29: 2.7201007 | BQ29: 227.90157 | BR29: 255.68521 | BS29: 36.280846 | BT29: 668.46403 | BU29: 97.554513 | BV29: 37.181086 | BW29: 119.89123 | BX29: 0 | BY29: 73021.564 | BZ29: 8559.7078 | CA29: 16.412404 | CB29: 0 | CC29: 3234.4272 | CD29: 1022.6946 | CE29: 2453.0639 | CF29: 15286.306 | CG29: 88308 | CI29: =CF29/CG29 -> 0.17310216
A30: S25 | B30: Fabricação de produtos de limpeza, cosméticos/perfumaria e higiene pessoal | C30: 25 | D30: 765.32407 | E30: 124.11388 | F30: 4.1411188 | G30: 26.412863 | H30: 122.19349 | I30: 63.069815 | J30: 11.163088 | K30: 95.473773 | L30: 9.1511034 | M30: 192.91992 | N30: 34.513376 | O30: 3.2668038 | P30: 51.801739 | Q30: 35.766428 | R30: 26.440694 | S30: 30.120874 | T30: 123.11266 | U30: 22.783766 | V30: 124.1784 | W30: 2.0914554 | X30: 0.94011927 | Y30: 15.692139 | Z30: 448.56544 | AA30: 480.65157 | AB30: 924.76117 | AC30: 75.265261 | AD30: 144.47271 | AE30: 65.70168 | AF30: 37.957525 | AG30: 41.675918 | AH30: 317.05273 | AI30: 29.079181 | AJ30: 28.954047 | AK30: 43.497999 | AL30: 34.735923 | AM30: 37.306512 | AN30: 9.7057737 | AO30: 38.819059 | AP30: 24.596692 | AQ30: 18.204243 | AR30: 2.9736796 | AS30: 2.1305305 | AT30: 0.64633242 | AU30: 42.033847 | AV30: 195.92545 | AW30: 120.41574 | AX30: 1401.1009 | AY30: 203.90997 | AZ30: 5.5952137 | BA30: 1.1265728 | BB30: 68.884047 | BC30: 53.710386 | BD30: 82.249491 | BE30: 21.158267 | BF30: 34.420096 | BG30: 70.625038 | BH30: 17.722424 | BI30: 36.376816 | BJ30: 16.273949 | BK30: 190.59552 | BL30: 71.454878 | BM30: 199.62395 | BN30: 71.733306 | BO30: 1199.0863 | BP30: 1.6549959 | BQ30: 159.23256 | BR30: 119.92704 | BS30: 95.531753 | BT30: 94.289859 | BU30: 592.29432 | BV30: 110.02516 | BW30: 795.73452 | BX30: 0 | BY30: 10764.138 | BZ30: 3455.2589 | CA30: 35.713769 | CB30: 0 | CC30: 33581.624 | CD30: 524.80294 | CE30: 1814.3668 | CF30: 39411.766 | CG30: 50176 | CI30: =CF30/CG30 -> 0.78547047
A31: S26 | B31: Fabricação de produtos farmoquímicos e farmacêuticos | C31: 26 | D31: 443.97217 | E31: 1869.1641 | F31: 14.50969 | G31: 21.801575 | H31: 344.6502 | I31: 12.749822 | J31: 2.597445 | K31: 76.787091 | L31: 1.3569439 | M31: 285.83398 | N31: 11.02808 | O31: 1.351365 | P31: 11.481965 | Q31: 44.242044 | R31: 15.518909 | S31: 7.8798413 | T31: 21.62656 | U31: 2.9720983 | V31: 12.242891 | W31: 0.31444667 | X31: 0.020529487 | Y31: 7.4184149 | Z31: 150.799 | AA31: 375.00097 | AB31: 53.960868 | AC31: 3129.91 | AD31: 38.414583 | AE31: 12.782497 | AF31: 12.930878 | AG31: 7.8937147 | AH31: 12.581002 | AI31: 7.0458295 | AJ31: 9.0717901 | AK31: 23.978799 | AL31: 21.038799 | AM31: 8.1781439 | AN31: 2.5045049 | AO31: 38.129608 | AP31: 10.456296 | AQ31: 7.1915976 | AR31: 1.174754 | AS31: 0.8416674 | AT31: 0.57083644 | AU31: 6.7002784 | AV31: 38.494487 | AW31: 11.011735 | AX31: 350.93074 | AY31: 15.001965 | AZ31: 3.1854828 | BA31: 0.89327323 | BB31: 12.376355 | BC31: 5.1967773 | BD31: 57.999276 | BE31: 1.0528672 | BF31: 3.3242458 | BG31: 8.657511 | BH31: 9.9219242 | BI31: 18.970806 | BJ31: 10.232229 | BK31: 22.657947 | BL31: 38.805067 | BM31: 45.310747 | BN31: 20.785824 | BO31: 42.917219 | BP31: 1.2398896 | BQ31: 372.68889 | BR31: 319.37331 | BS31: 159.33675 | BT31: 3521.2986 | BU31: 8425.7841 | BV31: 17.096774 | BW31: 404.31236 | BX31: 0 | BY31: 21079.534 | BZ31: 3220.0471 | CA31: 5793.2844 | CB31: 0 | CC31: 40030.055 | CD31: 1351.8378 | CE31: 4769.2415 | CF31: 55164.466 | CG31: 76244 | CI31: =CF31/CG31 -> 0.72352534
A32: S27 | B32: Fabricação de produtos de borracha e de material plástico | C32: 27 | D32: 698.19121 | E32: 235.00733 | F32: 46.570393 | G32: 145.4752 | H32: 191.68713 | I32: 734.84012 | J32: 72.852895 | K32: 2835.2781 | L32: 123.23957 | M32: 8166.6727 | N32: 2823.5617 | O32: 5.8291725 | P32: 242.18885 | Q32: 198.43576 | R32: 712.23021 | S32: 266.74123 | T32: 738.62736 | U32: 733.41384 | V32: 110.29826 | W32: 2.8397279 | X32: 0.45112675 | Y32: 43.249098 | Z32: 1403.9285 | AA32: 719.21447 | AB32: 1682.3857 | AC32: 463.56477 | AD32: 14371.992 | AE32: 1850.3009 | AF32: 520.80804 | AG32: 57.315708 | AH32: 828.61201 | AI32: 912.9805 | AJ32: 1826.2681 | AK32: 2015.7258 | AL32: 8176.9329 | AM32: 3620.2689 | AN32: 922.26892 | AO32: 2285.0355 | AP32: 1454.4904 | AQ32: 257.62248 | AR32: 42.082866 | AS32: 30.150803 | AT32: 7.1900259 | AU32: 429.3399 | AV32: 12177.286 | AW32: 1941.0436 | AX32: 6198.7944 | AY32: 5894.5159 | AZ32: 4.6589396 | BA32: 696.32353 | BB32: 156.37461 | BC32: 35.118482 | BD32: 615.77154 | BE32: 13.988935 | BF32: 9.262164 | BG32: 34.376201 | BH32: 32.765047 | BI32: 107.32416 | BJ32: 147.82293 | BK32: 554.69942 | BL32: 36.239848 | BM32: 32.213399 | BN32: 323.86814 | BO32: 604.73093 | BP32: 4.7775076 | BQ32: 220.03323 | BR32: 214.32989 | BS32: 57.36933 | BT32: 570.95267 | BU32: 669.58858 | BV32: 45.984354 | BW32: 182.77788 | BX32: 0 | BY32: 94589.152 | BZ32: 9260.7614 | CA32: 2.8306752 | CB32: 0 | CC32: 15552.936 | CD32: 1309.9415 | CE32: 501.3783 | CF32: 26627.848 | CG32: 121217 | CI32: =CF32/CG32 -> 0.2196709
A33: S28 | B33: Fabricação de produtos de minerais não-metálicos | C33: 28 | D33: 3226.6688 | E33: 1972.1846 | F33: 72.877294 | G33: 80.016722 | H33: 109.4592 | I33: 21.621881 | J33: 13.352699 | K33: 52.312555 | L33: 88.04165 | M33: 1536.0831 | N33: 1582.2385 | O33: 1.876822 | P33: 19.839804 | Q33: 18.911342 | R33: 14.029682 | S33: 17.490177 | T33: 282.7774 | U33: 18.736912 | V33: 26.429533 | W33: 0.67964277 | X33: 0.13850613 | Y33: 16.320968 | Z33: 717.09187 | AA33: 233.06967 | AB33: 355.9499 | AC33: 84.726938 | AD33: 536.72902 | AE33: 6686.5698 | AF33: 367.26831 | AG33: 31.730299 | AH33: 183.79941 | AI33: 22.689636 | AJ33: 295.70223 | AK33: 261.01599 | AL33: 1978.3926 | AM33: 128.52289 | AN33: 154.58344 | AO33: 460.50865 | AP33: 243.22036 | AQ33: 1495.2882 | AR33: 167.56234 | AS33: 117.65398 | AT33: 35.35863 | AU33: 852.5141 | AV33: 42784.12 | AW33: 251.57377 | AX33: 339.43383 | AY33: 33.648526 | AZ33: 1.0867095 | BA33: 1.2122493 | BB33: 29.991675 | BC33: 193.48775 | BD33: 697.94864 | BE33: 4.4716514 | BF33: 6.4131468 | BG33: 18.124563 | BH33: 15.212772 | BI33: 38.445138 | BJ33: 2315.1624 | BK33: 40.037059 | BL33: 19.614387 | BM33: 10.094007 | BN33: 9.9452631 | BO33: 141.16938 | BP33: 2.0603812 | BQ33: 393.17711 | BR33: 139.31583 | BS33: 33.413336 | BT33: 156.09209 | BU33: 169.65803 | BV33: 26.101551 | BW33: 262.04607 | BX33: 0 | BY33: 72715.093 | BZ33: 6379.5178 | CA33: 20.931346 | CB33: 0 | CC33: 3801.7964 | CD33: 838.13624 | CE33: 132.49279 | CF33: 11172.875 | CG33: 83888 | CI33: =CF33/CG33 -> 0.133188
A34: S29 | B34: Produção de ferro-gusa/ferroligas, siderurgia e tubos de aço sem costura | C34: 29 | D34: 262.77487 | E34: 389.14382 | F34: 24.861677 | G34: 113.51704 | H34: 3616.285 | I34: 64.496318 | J34: 85.483992 | K34: 355.10058 | L34: 4.7280077 | M34: 200.57533 | N34: 156.43377 | O34: 1.2409764 | P34: 30.136722 | Q34: 8.062274 | R34: 13.431866 | S34: 33.806226 | T34: 236.38041 | U34: 6.9742809 | V34: 66.478281 | W34: 1.7183629 | X34: 1.190928 | Y34: 7.4335377 | Z34: 143.92891 | AA34: 90.576788 | AB34: 67.684946 | AC34: 24.284206 | AD34: 1085.0757 | AE34: 918.01495 | AF34: 14070.167 | AG34: 865.59298 | AH34: 19426.165 | AI34: 103.61819 | AJ34: 3103.4382 | AK34: 8993.6738 | AL34: 6495.5527 | AM34: 8849.4908 | AN34: 896.68641 | AO34: 1379.4854 | AP34: 1483.4773 | AQ34: 317.09454 | AR34: 48.841655 | AS34: 34.90079 | AT34: 18.590944 | AU34: 146.56726 | AV34: 14400.859 | AW34: 81.85524 | AX34: 1901.4122 | AY34: 60.413187 | AZ34: 1.4900687 | BA34: 1.6712752 | BB34: 42.736558 | BC34: 20.59487 | BD34: 158.90557 | BE34: 2.3018929 | BF34: 6.1660231 | BG34: 27.881214 | BH34: 50.211722 | BI34: 63.325796 | BJ34: 69.945358 | BK34: 63.394797 | BL34: 38.642702 | BM34: 13.404672 | BN34: 268.22209 | BO34: 60.127341 | BP34: 6.5359951 | BQ34: 225.94612 | BR34: 45.689873 | BS34: 57.42511 | BT34: 23.13829 | BU34: 36.675005 | BV34: 44.724983 | BW34: 49.112858 | BX34: 0 | BY34: 92065.972 | BZ34: 46158.066 | CA34: 0.14070934 | CB34: 0 | CC34: 1916.034 | CD34: 796.32635 | CE34: 9128.493 | CF34: 57999.06 | CG34: 150065 | CI34: =CF34/CG34 -> 0.38649292
A35: S30 | B35: Metalurgia de metais não-ferosos e a fundição de metais | C35: 30 | D35: 327.99914 | E35: 72.250793 | F35: 4.8815267 | G35: 10.375023 | H35: 180.42287 | I35: 29.021051 | J35: 102.3993 | K35: 354.40532 | L35: 7.2109333 | M35: 602.0901 | N35: 32.250183 | O35: 1.2492381 | P35: 17.706036 | Q35: 11.292353 | R35: 15.895324 | S35: 6.2209217 | T35: 418.18347 | U35: 226.12039 | V35: 12.350051 | W35: 0.31704527 | X35: 0.014715076 | Y35: 4.8119873 | Z35: 1343.6894 | AA35: 360.21697 | AB35: 79.745506 | AC35: 29.644662 | AD35: 126.3432 | AE35: 182.45189 | AF35: 2111.1087 | AG35: 11749.076 | AH35: 2337.2706 | AI35: 167.97259 | AJ35: 6409.1057 | AK35: 1968.9882 | AL35: 757.11978 | AM35: 4903.9312 | AN35: 964.62694 | AO35: 2079.0499 | AP35: 1657.2837 | AQ35: 69.002082 | AR35: 11.271553 | AS35: 8.0756469 | AT35: 5.7094105 | AU35: 151.00309 | AV35: 2671.7049 | AW35: 671.10615 | AX35: 636.63495 | AY35: 91.1638 | AZ35: 1.8181177 | BA35: 1.8591241 | BB35: 42.485351 | BC35: 18.822652 | BD35: 102.3222 | BE35: 3.0964801 | BF35: 7.3669022 | BG35: 35.696867 | BH35: 27.292073 | BI35: 75.75747 | BJ35: 78.546779 | BK35: 77.794109 | BL35: 15.782527 | BM35: 17.582062 | BN35: 18.870314 | BO35: 61.924189 | BP35: 4.3873217 | BQ35: 65.879992 | BR35: 18.172086 | BS35: 68.052448 | BT35: 29.028014 | BU35: 117.57291 | BV35: 53.270977 | BW35: 82.363752 | BX35: 0 | BY35: 45006.509 | BZ35: 24409.736 | CA35: 0.72163791 | CB35: 0 | CC35: 2076.5018 | CD35: 474.42622 | CE35: 1180.1052 | CF35: 28141.491 | CG35: 73148 | CI35: =CF35/CG35 -> 0.3847199
A36: S31 | B36: Fabricação de produtos de metal, exceto máquinas e equipamentos | C36: 31 | D36: 499.03629 | E36: 637.12694 | F36: 57.088751 | G36: 52.952041 | H36: 1814.6536 | I36: 970.82499 | J36: 218.88177 | K36: 2499.7225 | L36: 62.759986 | M36: 2501.0729 | N36: 3555.6146 | O36: 16.308339 | P36: 79.14572 | Q36: 77.703657 | R36: 60.610065 | S36: 496.23165 | T36: 162.77406 | U36: 29.80484 | V36: 328.8878 | W36: 8.4721674 | X36: 1.5267308 | Y36: 64.505842 | Z36: 525.29842 | AA36: 703.8834 | AB36: 951.83371 | AC36: 152.41254 | AD36: 348.73827 | AE36: 220.63956 | AF36: 2342.1474 | AG36: 326.66536 | AH36: 7361.8054 | AI36: 902.08353 | AJ36: 2162.8146 | AK36: 4771.1427 | AL36: 3775.9249 | AM36: 2345.5037 | AN36: 1733.9024 | AO36: 1303.9481 | AP36: 3247.397 | AQ36: 2060.509 | AR36: 336.58601 | AS36: 241.15132 | AT36: 97.75222 | AU36: 490.86423 | AV36: 19392.368 | AW36: 394.15468 | AX36: 1607.234 | AY36: 165.62452 | AZ36: 11.291258 | BA36: 4.9721685 | BB36: 39.906179 | BC36: 145.16607 | BD36: 2131.8181 | BE36: 3.6640066 | BF36: 14.896722 | BG36: 37.318672 | BH36: 19.608033 | BI36: 30.890878 | BJ36: 417.59228 | BK36: 42.95142 | BL36: 29.159298 | BM36: 9.5612588 | BN36: 20.303371 | BO36: 345.61408 | BP36: 82.701262 | BQ36: 962.37642 | BR36: 83.657045 | BS36: 24.911509 | BT36: 117.28027 | BU36: 70.172174 | BV36: 22.595159 | BW36: 109.12299 | BX36: 0 | BY36: 76935.621 | BZ36: 7329.3582 | CA36: 1.2784449 | CB36: 0 | CC36: 12109.882 | CD36: 7061.8193 | CE36: -1483.9592 | CF36: 25018.379 | CG36: 101954 | CI36: =CF36/CG36 -> 0.24538889
A37: S32 | B37: Fabricação de equipamentos de informática, produtos eletrônicos e ópticos | C37: 32 | D37: 12.419134 | E37: 8.6898044 | F37: 1.1934858 | G37: 5.3596247 | H37: 366.70281 | I37: 98.368227 | J37: 16.221482 | K37: 38.201055 | L37: 1.8804611 | M37: 35.313877 | N37: 13.801932 | O37: 1.5691739 | P37: 9.1187669 | Q37: 13.362505 | R37: 9.6102571 | S37: 7.0166851 | T37: 14.734428 | U37: 217.35962 | V37: 10.095832 | W37: 0.25943691 | X37: 0.022207382 | Y37: 2.288045 | Z37: 13.94067 | AA37: 9.3898105 | AB37: 8.6718498 | AC37: 10.054823 | AD37: 30.206007 | AE37: 13.468237 | AF37: 21.050127 | AG37: 13.073065 | AH37: 21.162404 | AI37: 17405.685 | AJ37: 547.87497 | AK37: 756.88151 | AL37: 323.88078 | AM37: 225.81662 | AN37: 97.633184 | AO37: 79.034594 | AP37: 854.92364 | AQ37: 234.84853 | AR37: 38.362721 | AS37: 27.485458 | AT37: 41.94912 | AU37: 20.91407 | AV37: 562.15288 | AW37: 43.245688 | AX37: 351.46919 | AY37: 65.044062 | AZ37: 7.1038037 | BA37: 7.0741324 | BB37: 219.06182 | BC37: 4.2994957 | BD37: 20.580154 | BE37: 3.3640291 | BF37: 288.6826 | BG37: 289.90218 | BH37: 2116.4629 | BI37: 378.52008 | BJ37: 18.640705 | BK37: 386.96177 | BL37: 723.1501 | BM37: 136.46086 | BN37: 50.407472 | BO37: 1365.2978 | BP37: 145.45213 | BQ37: 318.4383 | BR37: 583.98244 | BS37: 135.66739 | BT37: 234.52423 | BU37: 296.78207 | BV37: 68.816515 | BW37: 876.65295 | BX37: 0 | BY37: 31378.094 | BZ37: 4359.544 | CA37: 0.84224592 | CB37: 0 | CC37: 38106.281 | CD37: 27834.344 | CE37: 1864.8951 | CF37: 72165.906 | CG37: 103544 | CI37: =CF37/CG37 -> 0.69695884
A38: S33 | B38: Fabricação de máquinas e equipamentos elétricos | C38: 33 | D38: 61.471443 | E38: 100.95108 | F38: 8.5343875 | G38: 33.536285 | H38: 351.44182 | I38: 105.93191 | J38: 28.623828 | K38: 106.00238 | L38: 20.203187 | M38: 138.2301 | N38: 54.237114 | O38: 3.1297544 | P38: 41.0578 | Q38: 12.686513 | R38: 14.122035 | S38: 37.245085 | T38: 94.046313 | U38: 25.089969 | V38: 24.56362 | W38: 0.63389096 | X38: 0.15812753 | Y38: 17.644357 | Z38: 128.51748 | AA38: 37.106257 | AB38: 27.521789 | AC38: 24.029436 | AD38: 122.22624 | AE38: 144.97496 | AF38: 174.91862 | AG38: 232.20439 | AH38: 169.6704 | AI38: 1981.3495 | AJ38: 7205.7318 | AK38: 2445.0632 | AL38: 1174.9433 | AM38: 1006.4146 | AN38: 328.24985 | AO38: 282.22592 | AP38: 2468.8557 | AQ38: 4211.3387 | AR38: 687.926 | AS38: 492.87331 | AT38: 799.26303 | AU38: 198.71649 | AV38: 7560.7586 | AW38: 469.43587 | AX38: 1152.1672 | AY38: 1150.876 | AZ38: 34.987698 | BA38: 8.9950211 | BB38: 126.21429 | BC38: 36.283964 | BD38: 80.774348 | BE38: 10.321334 | BF38: 54.167704 | BG38: 627.47282 | BH38: 55.847399 | BI38: 84.703041 | BJ38: 433.53833 | BK38: 614.4618 | BL38: 70.262748 | BM38: 48.605599 | BN38: 45.073338 | BO38: 663.14429 | BP38: 6.271772 | BQ38: 131.14882 | BR38: 61.569511 | BS38: 29.235818 | BT38: 32.201741 | BU38: 36.545806 | BV38: 79.163102 | BW38: 789.54654 | BX38: 0 | BY38: 40117.437 | BZ38: 8160.6082 | CA38: 1.0854721 | CB38: 0 | CC38: 18247.815 | CD38: 14696.133 | CE38: -1278.0788 | CF38: 39827.563 | CG38: 79945 | CI38: =CF38/CG38 -> 0.49818705
A39: S34 | B39: Fabricação de máquinas e equipamentos mecânicos | C39: 34 | D39: 59.522306 | E39: 52.217786 | F39: 7.7379427 | G39: 121.83013 | H39: 2981.3187 | I39: 3358.5305 | J39: 647.2461 | K39: 116.75762 | L39: 9.5497742 | M39: 134.22487 | N39: 105.791 | O39: 2.9828611 | P39: 20.954039 | Q39: 16.011767 | R39: 17.830645 | S39: 83.835357 | T39: 66.499361 | U39: 27.971484 | V39: 124.42444 | W39: 3.2068615 | X39: 0.64315817 | Y39: 14.664867 | Z39: 55.365175 | AA39: 42.928805 | AB39: 38.422246 | AC39: 23.581685 | AD39: 146.51909 | AE39: 63.810019 | AF39: 227.46372 | AG39: 109.6497 | AH39: 293.62667 | AI39: 187.07604 | AJ39: 561.55299 | AK39: 13998.184 | AL39: 1347.7858 | AM39: 250.3073 | AN39: 400.6078 | AO39: 86.468517 | AP39: 8156.5291 | AQ39: 183.87731 | AR39: 29.480191 | AS39: 21.121457 | AT39: 28.673874 | AU39: 87.632479 | AV39: 3082.2212 | AW39: 347.09498 | AX39: 492.90872 | AY39: 188.18252 | AZ39: 114.13173 | BA39: 16.756328 | BB39: 183.72105 | BC39: 10.695789 | BD39: 78.82 | BE39: 9.4137411 | BF39: 7.8433875 | BG39: 56.015753 | BH39: 39.26632 | BI39: 17.499684 | BJ39: 30.905609 | BK39: 36.413598 | BL39: 40.176683 | BM39: 12.242519 | BN39: 21.569958 | BO39: 1179.0029 | BP39: 5.7246073 | BQ39: 111.69727 | BR39: 25.460223 | BS39: 5.0073719 | BT39: 117.48268 | BU39: 49.931724 | BV39: 13.370874 | BW39: 42.232026 | BX39: 0 | BY39: 40650.205 | BZ39: 26105.196 | CA39: 1.8292214 | CB39: 0 | CC39: 4346.8636 | CD39: 59157.236 | CE39: -948.33001 | CF39: 88662.795 | CG39: 129313 | CI39: =CF39/CG39 -> 0.68564487
... A44: S39 | B44: Manutenção, reparação e instalação de máquinas e equipamentos | C44: 39 | D44: 95.999297 | E44: 40.232595 | F44: 86.093282 | G44: 716.65195 | H44: 3124.6301 | I44: 1811.8295 | J44: 682.14346 | K44: 1147.1755 | L44: 428.95832 | M44: 665.69626 | N44: 393.03264 | O44: 12.305104 | P44: 145.60212 | Q44: 260.75604 | R44: 168.1677 | S44: 627.01736 | T44: 2982.1012 | U44: 1057.8342 | V44: 620.6682 | W44: 16.245735 | X44: 12.915451 | Y44: 778.15252 | Z44: 1193.2544 | AA44: 534.26247 | AB44: 157.71896 | AC44: 621.4543 | AD44: 554.34084 | AE44: 2308.8232 | AF44: 8729.3709 | AG44: 1976.9636 | AH44: 777.57052 | AI44: 82.550318 | AJ44: 458.15065 | AK44: 1494.2985 | AL44: 217.14626 | AM44: 688.96154 | AN44: 423.04824 | AO44: 717.61152 | AP44: 1073.4425 | AQ44: 1338.9613 | AR44: 218.72055 | AS44: 156.70511 | AT44: 93.043619 | AU44: 1187.0909 | AV44: 1957.5839 | AW44: 735.16437 | AX44: 4433.1198 | AY44: 1319.0597 | AZ44: 1781.7765 | BA44: 768.3377 | BB44: 3303.0994 | BC44: 6.9671589 | BD44: 292.83002 | BE44: 404.22868 | BF44: 154.53954 | BG44: 393.52931 | BH44: 1214.7449 | BI44: 293.29376 | BJ44: 155.80859 | BK44: 871.89488 | BL44: 175.41423 | BM44: 151.98635 | BN44: 956.8375 | BO44: 919.4858 | BP44: 224.93924 | BQ44: 1063.5661 | BR44: 152.45372 | BS44: 1.5982708 | BT44: 991.79394 | BU44: 574.06168 | BV44: 526.4843 | BW44: 569.91556 | BX44: 0 | BY44: 65272.214 | BZ44: 4025.5921 | CA44: 0.69952644 | CB44: 0 | CC44: 770.61968 | CD44: 9962.6097 | CE44: -63.734893 | CF44: 14695.786 | CG44: 79968 | CI44: =CF44/CG44 -> 0.18377084
A45: S40 | B45: Geração centralizada de energia elétrica | C45: 40 | D45: 6395.2848 | E45: 3669.1911 | F45: 323.32534 | G45: 428.97572 | H45: 249.12162 | I45: 811.37785 | J45: 272.83286 | K45: 881.40677 | L45: 55.545081 | M45: 1747.4393 | N45: 343.9512 | O45: 27.165011 | P45: 709.91226 | Q45: 115.15109 | R45: 144.75464 | S45: 505.05657 | T45: 1086.1981 | U45: 77.84197 | V45: 17.978288 | W45: 0.38697919 | X45: 0.018961225 | Y45: 54.932393 | Z45: 1641.2751 | AA45: 251.37968 | AB45: 80.845611 | AC45: 115.83359 | AD45: 846.65338 | AE45: 2854.4839 | AF45: 1959.9921 | AG45: 1834.8706 | AH45: 862.60401 | AI45: 117.35017 | AJ45: 398.86575 | AK45: 431.7504 | AL45: 415.45654 | AM45: 900.33934 | AN45: 175.55883 | AO45: 267.98771 | AP45: 217.26177 | AQ45: 56040.996 | AR45: 2248.7233 | AS45: 2.3733184 | AT45: 3224.3241 | AU45: 3664.4363 | AV45: 473.83277 | AW45: 1333.3504 | AX45: 17447.128 | AY45: ='Fluxos Energia'!H20 -> 162.36655 | AZ45: 53.922482 | BA45: 38.803576 | BB45: 1181.1446 | BC45: 1186.4214 | BD45: 1700.4758 | BE45: 98.902912 | BF45: 335.62812 | BG45: 1531.1591 | BH45: 595.99822 | BI45: 2001.6851 | BJ45: 618.68951 | BK45: 1104.1971 | BL45: 268.65885 | BM45: 202.26999 | BN45: 164.18143 | BO45: 6287.5567 | BP45: 89.373979 | BQ45: 4731.8569 | BR45: 1531.8724 | BS45: 1968.1986 | BT45: 1013.6437 | BU45: 1538.7878 | BV45: 916.34218 | BW45: 2497.6159 | BX45: 0 | BY45: 147409.28 | BZ45: 74.173164 | CA45: 0 | CB45: 0 | CC45: 92106.416 | CD45: 179.78296 | CE45: -8028.2999 | CF45: 84332.072 | CG45: 231741.36 | CI45: =CF45/CG45 -> 0.36390601
A46: S41 | B46: Geração distribuída de energia elétrica | C46: 41 | D46: 1400.0172 | E46: 803.22911 | F46: 70.752758 | G46: 21.195727 | H46: 12.19926 | I46: 40.075277 | J46: 13.479532 | K46: 190.31441 | L46: 11.676093 | M46: 380.54681 | N46: 74.965026 | O46: 5.8558789 | P46: 154.2986 | Q46: 23.836708 | R46: 31.317968 | S46: 110.40197 | T46: 237.12579 | U46: 7.7863479 | V46: 1.5752701 | W46: 0.032926074 | X46: 0.0018735493 | Y46: 5.271944 | Z46: 165.28051 | AA46: 25.210657 | AB46: 7.906592 | AC46: 11.251019 | AD46: 84.82101 | AE46: 287.68148 | AF46: 197.27343 | AG46: 185.02014 | AH46: 86.667423 | AI46: 11.571198 | AJ46: 40.036437 | AK46: 43.156591 | AL46: 41.649137 | AM46: 90.469355 | AN46: 17.616359 | AO46: 26.709257 | AP46: 10.720946 | AQ46: 2329.3415 | AR46: 8887.7403 | AS46: 0.088882235 | AT46: 705.61465 | AU46: 181.02949 | AV46: 99.604798 | AW46: 278.12075 | AX46: 3669.2503 | AY46: ='Fluxos Energia'!H21 -> 6.2499677 | AZ46: 11.526444 | BA46: 8.0967209 | BB46: 115.34939 | BC46: 255.11247 | BD46: 350.92251 | BE46: 20.978521 | BF46: 71.731834 | BG46: 326.8462 | BH46: 123.48328 | BI46: 418.54053 | BJ46: 127.27199 | BK46: 222.23552 | BL46: 54.978845 | BM46: 40.20661 | BN46: 31.779413 | BO46: 1363.2728 | BP46: 18.589634 | BQ46: 473.71504 | BR46: 153.72296 | BS46: 412.88238 | BT46: 101.67511 | BU46: 327.24697 | BV46: 186.63242 | BW46: 533.07786 | BX46: 0 | BY46: 26830.655 | BZ46: 0 | CA46: 0 | CB46: 0 | CC46: 6979.0578 | CD46: 6.1148535 | CE46: 668.92539 | CF46: 7654.0981 | CG46: 34484.753 | CI46: =CF46/CG46 -> 0.22195601
A47: S42 | B47: Transmissão | C47: 42 | D47: 2.1140918 | E47: 1.2134196 | F47: 0.10864496 | G47: 0.15197736 | H47: 0.19472275 | I47: 0.28765798 | J47: 0.097766049 | K47: 0.45386221 | L47: 0.048693555 | M47: 0.70205867 | N47: 0.1292574 | O47: 0.013660813 | P47: 0.30567924 | Q47: 0.12478766 | R47: 0.069926296 | S47: 0.17644551 | T47: 0.3989356 | U47: 0.038227026 | V47: 0.049649387 | W47: 0.0012482046 | X47: 1.3554722e-05 | Y47: 0.067787743 | Z47: 0.59821907 | AA47: 0.10981401 | AB47: 0.068236554 | AC47: 0.10189907 | AD47: 0.38972657 | AE47: 1.0084386 | AF47: 0.73898058 | AG47: 0.6235064 | AH47: 0.35355807 | AI47: 0.084922892 | AJ47: 0.16114738 | AK47: 0.1964817 | AL47: 0.16855949 | AM47: 0.35746092 | AN47: 0.073893668 | AO47: 0.1480368 | AP47: 0.087934445 | AQ47: 16645.383 | AR47: 0.20782399 | AS47: 0.027647368 | AT47: 1.0805068 | AU47: 1.3287705 | AV47: 0.41526764 | AW47: 1.3202834 | AX47: 15.351602 | AY47: 0.31437856 | AZ47: 0.035449872 | BA47: 0.038255372 | BB47: 1.0927637 | BC47: 0.68689012 | BD47: 1.9254964 | BE47: 0.075540548 | BF47: 0.22225649 | BG47: 1.0349145 | BH47: 0.63671621 | BI47: 1.9172754 | BJ47: 0.72645642 | BK47: 1.6103737 | BL47: 0.28202501 | BM47: 0.32714188 | BN47: 0.31819807 | BO47: 2.917494 | BP47: 0.091885625 | BQ47: 2.2552452 | BR47: 0.66347015 | BS47: 1.7997554 | BT47: 0.44691179 | BU47: 1.1222598 | BV47: 1.1954727 | BW47: 1.7001468 | BX47: 0 | BY47: 16700.571 | BZ47: 0 | CA47: 0 | CB47: 0 | CC47: 19.73352 | CD47: 24.205935 | CE47: 9.2252057 | CF47: 53.16466 | CG47: 16753.736 | CI47: =CF47/CG47 -> 0.0031733018
A48: S43 | B48: Gás Natural | C48: 43 | D48: 521.81884 | E48: 299.38343 | F48: 26.375641 | G48: 222.359 | H48: 124.64051 | I48: 420.04605 | J48: 141.35956 | K48: 519.3474 | L48: 31.757555 | M48: 1039.5294 | N48: 204.81091 | O48: 15.978872 | P48: 442.64807 | Q48: 67.95583 | R48: 89.795921 | S48: 316.94614 | T48: 753.03008 | U48: 49.397586 | V48: 22.319131 | W48: 0.45692502 | X48: 0.02861779 | Y48: 79.176543 | Z48: 2551.581 | AA48: 388.3241 | AB48: 120.10696 | AC48: 170.33376 | AD48: 1305.7146 | AE48: 263.63484 | AF48: 1804.7351 | AG48: 576.36351 | AH48: 269.60701 | AI48: 35.747028 | AJ48: 124.52315 | AK48: 133.99115 | AL48: 129.49634 | AM48: 281.47074 | AN48: 54.77867 | AO48: 82.83797 | AP48: 65.805057 | AQ48: 8230.2789 | AR48: 496.47102 | AS48: 0.10289926 | AT48: 698.161 | AU48: 351.25028 | AV48: 46.310899 | AW48: 129.61331 | AX48: 1705.5087 | AY48: ='Fluxos Energia'!H22 -> 0 | AZ48: 4.3409966 | BA48: 3.0816805 | BB48: 115.57832 | BC48: 117.74711 | BD48: 164.10576 | BE48: 9.7246253 | BF48: 33.171279 | BG48: 151.20818 | BH48: 57.679251 | BI48: 194.90167 | BJ48: 59.5789 | BK48: 104.77869 | BL48: 25.835398 | BM48: 19.034479 | BN48: 15.181498 | BO48: 627.58401 | BP48: 8.6712271 | BQ48: 449.38658 | BR48: 145.78473 | BS48: 192.06581 | BT48: 96.429983 | BU48: 151.56913 | BV48: 87.650662 | BW48: 246.61921 | BX48: 0 | BY48: 30040.938 | BZ48: 3.4783578 | CA48: 0 | CB48: 0 | CC48: 2661.4744 | CD48: 75.878454 | CE48: 7377.3859 | CF48: 10118.217 | CG48: 40159.155 | CI48: =CF48/CG48 -> 0.25195294
A49: S44 | B49: Água, esgoto e gestão de resíduos | C49: 44 | D49: 11.385936 | E49: 2.6792019 | F49: 1.4771761 | G49: 27.466778 | H49: 76.393417 | I49: 276.98822 | J49: 58.205987 | K49: 185.26808 | L49: 57.97676 | M49: 355.73583 | N49: 498.03067 | O49: 1.1528691 | P49: 68.90485 | Q49: 30.051705 | R49: 25.257569 | S49: 261.20949 | T49: 342.45194 | U49: 6.4445518 | V49: 412.6592 | W49: 10.630001 | X49: 1.9108336 | Y49: 33.482583 | Z49: 701.73745 | AA49: 472.51164 | AB49: 142.9638 | AC49: 84.158643 | AD49: 535.38413 | AE49: 692.40928 | AF49: 4649.6417 | AG49: 2358.936 | AH49: 175.02494 | AI49: 19.434434 | AJ49: 59.444773 | AK49: 86.92077 | AL49: 126.88607 | AM49: 311.10131 | AN49: 92.757889 | AO49: 79.472997 | AP49: 29.881987 | AQ49: 67.031585 | AR49: 10.94967 | AS49: 7.8450302 | AT49: 1.1739004 | AU49: 1062.6781 | AV49: 277.72859 | AW49: 429.16433 | AX49: 4258.8786 | AY49: 343.79743 | AZ49: 9.7945591 | BA49: 8.2109751 | BB49: 809.59567 | BC49: 445.84402 | BD49: 1269.9302 | BE49: 25.678696 | BF49: 57.186368 | BG49: 49.700454 | BH49: 122.75779 | BI49: 472.76885 | BJ49: 432.01442 | BK49: 606.85136 | BL49: 73.331234 | BM49: 39.840044 | BN49: 52.186027 | BO49: 5777.2929 | BP49: 31.682273 | BQ49: 10413.964 | BR49: 1380.3933 | BS49: 276.10959 | BT49: 1532.3417 | BU49: 2210.7472 | BV49: 124.7404 | BW49: 2031.1037 | BX49: 0 | BY49: 48077.744 | BZ49: 24.483589 | CA49: 0.07567896 | CB49: 0 | CC49: 33927.86 | CD49: 34.004922 | CE49: 155.82623 | CF49: 34142.25 | CG49: 82220 | CI49: =CF49/CG49 -> 0.4152548
A50: S45 | B50: Construção | C50: 45 | D50: 104.44438 | E50: 188.15898 | F50: 12.143415 | G50: 6.7017627 | H50: 2129.1012 | I50: 1976.3195 | J50: 297.80285 | K50: 11.045396 | L50: 8.5788606 | M50: 26.166898 | N50: 5.5606198 | O50: 0.75902275 | P50: 25.310312 | Q50: 4.4915832 | R50: 1.7472971 | S50: 2.1934296 | T50: 36.091911 | U50: 20.367001 | V50: 33.996864 | W50: 0.87185731 | X50: 0.0055708768 | Y50: 30.079175 | Z50: 75.628419 | AA50: 8.4548562 | AB50: 2.7737367 | AC50: 5.1263301 | AD50: 13.091309 | AE50: 29.828421 | AF50: 140.43835 | AG50: 1994.8901 | AH50: 68.82001 | AI50: 84.541967 | AJ50: 13.95006 | AK50: 78.407544 | AL50: 276.34445 | AM50: 40.157532 | AN50: 200.37672 | AO50: 21.959668 | AP50: 7.8919568 | AQ50: 16.786777 | AR50: 2.7421352 | AS50: 1.9646375 | AT50: 1.1312394 | AU50: 4766.0307 | AV50: 57477.263 | AW50: 536.31097 | AX50: 1171.201 | AY50: 314.30679 | AZ50: 18.552863 | BA50: 33.163819 | BB50: 1570.8869 | BC50: 302.02418 | BD50: 546.24782 | BE50: 15.626072 | BF50: 234.13783 | BG50: 4200.096 | BH50: 902.15741 | BI50: 1220.1516 | BJ50: 1941.8476 | BK50: 323.17735 | BL50: 688.46329 | BM50: 17.059034 | BN50: 213.3818 | BO50: 3273.4101 | BP50: 14.270601 | BQ50: 15438.558 | BR50: 1371.616 | BS50: 457.9544 | BT50: 3510.4328 | BU50: 33.634583 | BV50: 149.18487 | BW50: 352.21459 | BX50: 0 | BY50: 109100.61 | BZ50: 3991.5567 | CA50: 0 | CB50: 0 | CC50: 963.46863 | CD50: 438017.37 | CE50: 0 | CF50: 442972.39 | CG50: 552073 | CI50: =CF50/CG50 -> 0.80238011
A51: S46 | B51: Comércio e reparação de veículos automotores e motocicletas | C51: 46 | D51: 213.3748 | E51: 44.765363 | F51: 20.017808 | G51: 61.762281 | H51: 200.03361 | I51: 1188.7545 | J51: 87.962171 | K51: 26.831655 | L51: 21.104618 | M51: 45.3026 | N51: 41.953653 | O51: 0.55653701 | P51: 5.0787064 | Q51: 1.7204557 | R51: 5.1833937 | S51: 2.1249756 | T51: 11.237134 | U51: 1.3627498 | V51: 8.083676 | W51: 0.2073079 | X51: 0.0013322615 | Y51: 9.597752 | Z51: 8.2785612 | AA51: 18.529588 | AB51: 2.8651066 | AC51: 53.262471 | AD51: 242.92391 | AE51: 322.63818 | AF51: 22.2996 | AG51: 59.935415 | AH51: 8.9730047 | AI51: 564.68151 | AJ51: 34.453139 | AK51: 2581.1766 | AL51: 14341.558 | AM51: 3300.3373 | AN51: 983.16667 | AO51: 52.330694 | AP51: 301.31337 | AQ51: 307.70658 | AR51: 50.26415 | AS51: 36.012388 | AT51: 20.778222 | AU51: 785.3576 | AV51: 473.88532 | AW51: 6440.1701 | AX51: 3989.537 | AY51: 10881.126 | AZ51: 16.998841 | BA51: 37.881389 | BB51: 468.52787 | BC51: 0.85423412 | BD51: 127.65475 | BE51: 7.9318226 | BF51: 63.957249 | BG51: 42.991332 | BH51: 17.659688 | BI51: 105.19949 | BJ51: 25.894499 | BK51: 4.5107129 | BL51: 104.63292 | BM51: 24.997551 | BN51: 985.30412 | BO51: 69.08567 | BP51: 169.90306 | BQ51: 2105.9907 | BR51: 386.81705 | BS51: 10.290896 | BT51: 1115.0396 | BU51: 756.98635 | BV51: 48.77569 | BW51: 56.266082 | BX51: 0 | BY51: 54634.729 | BZ51: 13664.825 | CA51: 0.20101334 | CB51: 0 | CC51: 83335.69 | CD51: 23505.118 | CE51: -47.563214 | CF51: 120458.27 | CG51: 175093 | CI51: =CF51/CG51 -> 0.68796737
A52: S47 | B52: Comércio por atacado e a varejo, exceto veículos automotores | C52: 47 | D52: 20065.542 | E52: 10578.3 | F52: 921.82921 | G52: 706.51263 | H52: 5517.4567 | I52: 2970.1372 | J52: 754.48005 | K52: 33868.094 | L52: 822.10109 | M52: 33523.526 | N52: 6301.9199 | O52: 2229.3668 | P52: 5179.4488 | Q52: 6931.901 | R52: 5598.3531 | S52: 2431.9729 | T52: 7897.9729 | U52: 1623.3166 | V52: 22262.355 | W52: 567.16528 | X52: 67.456586 | Y52: 2076.0697 | Z52: 10203.639 | AA52: 6324.7889 | AB52: 4149.2998 | AC52: 4998.2658 | AD52: 9399.1905 | AE52: 6500.7662 | AF52: 7645.937 | AG52: 4695.2801 | AH52: 7185.1643 | AI52: 11261.65 | AJ52: 7021.0688 | AK52: 12401.701 | AL52: 5613.1897 | AM52: 5033.8812 | AN52: 1692.0256 | AO52: 6771.1089 | AP52: 6343.2248 | AQ52: 3470.2671 | AR52: 566.28759 | AS52: 405.72393 | AT52: 241.06616 | AU52: 1369.5879 | AV52: 32538.159 | AW52: 1957.5112 | AX52: 23303.721 | AY52: 11823.04 | AZ52: 459.20877 | BA52: 1240.7376 | BB52: 1360.3615 | BC52: 1200.1643 | BD52: 24860.589 | BE52: 1464.6658 | BF52: 1272.1646 | BG52: 4607.3854 | BH52: 3117.9396 | BI52: 3851.8159 | BJ52: 2039.0853 | BK52: 2754.822 | BL52: 1662.6059 | BM52: 3375.4601 | BN52: 1110.7929 | BO52: 6017.6211 | BP52: 460.41963 | BQ52: 7320.3862 | BR52: 5232.9748 | BS52: 1673.3487 | BT52: 7300.7419 | BU52: 19050.648 | BV52: 758.17378 | BW52: 4810.0605 | BX52: 0 | BY52: 472813 | BZ52: 83853.491 | CA52: 2765.5801 | CB52: 2.4717411 | CC52: 503799.25 | CD52: 55581.557 | CE52: 1763.6545 | CF52: 647766 | CG52: 1120579 | CI52: =CF52/CG52 -> 0.57806366
A53: S48 | B53: Transporte terrestre | C53: 48 | D53: 7307.366 | E53: 2201.7665 | F53: 759.10341 | G53: 912.95436 | H53: 6475.7007 | I53: 3552.998 | J53: 781.79607 | K53: 13074.054 | L53: 3165.5561 | M53: 19108.96 | N53: 3878.9551 | O53: 300.63615 | P53: 1315.0091 | Q53: 1051.8337 | R53: 1211.3051 | S53: 1569.2351 | T53: 4157.8349 | U53: 362.96299 | V53: 5179.9925 | W53: 131.32714 | X53: 1.2085582 | Y53: 2459.0716 | Z53: 7156.4767 | AA53: 2644.5351 | AB53: 1989.3038 | AC53: 3369.966 | AD53: 3931.0659 | AE53: 3424.3342 | AF53: 7094.8222 | AG53: 1499.3307 | AH53: 3232.6086 | AI53: 2218.7862 | AJ53: 1900.3046 | AK53: 2935.6552 | AL53: 5758.2056 | AM53: 2546.4418 | AN53: 772.23847 | AO53: 1818.4498 | AP53: 694.19441 | AQ53: 3289.3869 | AR53: 537.32433 | AS53: 384.97283 | AT53: 639.87316 | AU53: 502.70008 | AV53: 5229.3344 | AW53: 1827.7701 | AX53: 45681.213 | AY53: 42845.106 | AZ53: 286.10225 | BA53: 351.73586 | BB53: 5689.8904 | BC53: 159.70357 | BD53: 2928.6506 | BE53: 432.91401 | BF53: 501.4047 | BG53: 642.8236 | BH53: 779.76812 | BI53: 2072.0931 | BJ53: 359.9909 | BK53: 1279.8995 | BL53: 1038.5244 | BM53: 445.46073 | BN53: 596.29321 | BO53: 897.37589 | BP53: 146.71538 | BQ53: 4091.6499 | BR53: 2338.8551 | BS53: 1558.6125 | BT53: 1497.2124 | BU53: 615.04952 | BV53: 325.6088 | BW53: 2457.6103 | BX53: 0 | BY53: 264377.97 | BZ53: 16374.594 | CA53: 89.027123 | CB53: 0 | CC53: 113227.3 | CD53: 4736.7298 | CE53: 7.4247544 | CF53: 134435.07 | CG53: 398813 | CI53: =CF53/CG53 -> 0.33708799
A54: S49 | B54: Transporte aquaviário | C54: 49 | D54: 39.738559 | E54: 30.188918 | F54: 2.6028834 | G54: 2.5855371 | H54: 6014.8756 | I54: 6.5371675 | J54: 12.379639 | K54: 1215.6784 | L54: 99.638254 | M54: 529.87292 | N54: 15.881198 | O54: 4.1122729 | P54: 17.862456 | Q54: 18.671242 | R54: 10.956892 | S54: 168.82465 | T54: 1369.3082 | U54: 15.165713 | V54: 101.21961 | W54: 2.5958 | X54: 0.016586294 | Y54: 38.128689 | Z54: 681.41859 | AA54: 22.967493 | AB54: 44.625488 | AC54: 7.3439862 | AD54: 61.018072 | AE54: 117.53425 | AF54: 364.35022 | AG54: 29.901183 | AH54: 46.359126 | AI54: 47.513143 | AJ54: 46.656803 | AK54: 252.53358 | AL54: 200.58448 | AM54: 87.175136 | AN54: 92.291004 | AO54: 11.27171 | AP54: 19.77223 | AQ54: 10.425442 | AR54: 1.7030054 | AS54: 1.2201398 | AT54: 1.9369097 | AU54: 3.9900222 | AV54: 85.468365 | AW54: 17.570055 | AX54: 974.42611 | AY54: 662.32475 | AZ54: 942.87093 | BA54: 4.0695481 | BB54: 56.843633 | BC54: 4.33629 | BD54: 66.858185 | BE54: 1.4128613 | BF54: 3.485576 | BG54: 6.1442029 | BH54: 19.801373 | BI54: 14.746733 | BJ54: 9.2220013 | BK54: 15.018517 | BL54: 5.1919711 | BM54: 4.4003648 | BN54: 3.7254654 | BO54: 239.95377 | BP54: 1.6846209 | BQ54: 14.072953 | BR54: 5.5129645 | BS54: 12.051007 | BT54: 7.2066724 | BU54: 19.466725 | BV54: 9.8233458 | BW54: 13.563345 | BX54: 0 | BY54: 15090.686 | BZ54: 5851.6851 | CA54: 2.0410606 | CB54: 0 | CC54: 1989.5855 | CD54: 108.00284 | CE54: 0 | CF54: 7951.3145 | CG54: 23042 | CI54: =CF54/CG54 -> 0.34507918
A55: S50 | B55: Transporte aéreo | C55: 50 | D55: 0.79905327 | E55: 0.014439555 | F55: 1.583667 | G55: 3.1838363 | H55: 2233.7214 | I55: 14.193182 | J55: 26.652113 | K55: 281.00854 | L55: 6.5657008 | M55: 241.49937 | N55: 40.851483 | O55: 19.611217 | P55: 27.322521 | Q55: 31.392047 | R55: 44.045633 | S55: 47.832557 | T55: 96.658071 | U55: 14.988109 | V55: 39.344344 | W55: 1.0089946 | X55: 0.0064471385 | Y55: 5.9729269 | Z55: 264.9354 | AA55: 280.40283 | AB55: 11.368272 | AC55: 127.40859 | AD55: 43.297398 | AE55: 102.16068 | AF55: 93.104242 | AG55: 12.549694 | AH55: 48.356507 | AI55: 234.4386 | AJ55: 144.25547 | AK55: 177.37014 | AL55: 220.18354 | AM55: 91.31017 | AN55: 47.099513 | AO55: 33.444721 | AP55: 72.917505 | AQ55: 321.08407 | AR55: 52.449374 | AS55: 37.578019 | AT55: 117.87551 | AU55: 44.588148 | AV55: 926.79588 | AW55: 195.09444 | AX55: 3175.757 | AY55: 202.62405 | AZ55: 85.47545 | BA55: 12.776601 | BB55: 716.74799 | BC55: 67.135472 | BD55: 64.579261 | BE55: 12.951939 | BF55: 142.76181 | BG55: 154.00668 | BH55: 661.76746 | BI55: 1955.7044 | BJ55: 61.593476 | BK55: 848.28966 | BL55: 251.59133 | BM55: 548.83823 | BN55: 84.822662 | BO55: 305.04013 | BP55: 22.538515 | BQ55: 1037.9845 | BR55: 307.43787 | BS55: 1902.2029 | BT55: 343.80314 | BU55: 6.1739411 | BV55: 90.362573 | BW55: 6697.2626 | BX55: 0 | BY55: 26638.554 | BZ55: 7922.3153 | CA55: 0 | CB55: 0 | CC55: 10246.131 | CD55: 0 | CE55: 0 | CF55: 18168.446 | CG55: 44807 | CI55: =CF55/CG55 -> 0.40548231
A56: S51 | B56: Armazenamento, atividades auxiliares dos transportes e correio | C56: 51 | D56: 1107.5531 | E56: 52.73432 | F56: 257.12418 | G56: 27.332603 | H56: 4686.5245 | I56: 2866.9375 | J56: 452.77897 | K56: 3106.4543 | L56: 1445.7661 | M56: 3759.9644 | N56: 1966.4343 | O56: 30.597632 | P56: 174.62686 | Q56: 117.35983 | R56: 178.81608 | S56: 283.69215 | T56: 1642.0242 | U56: 168.03246 | V56: 785.99973 | W56: 20.157142 | X56: 0.1287974 | Y56: 888.97563 | Z56: 1113.0502 | AA56: 890.70271 | AB56: 427.10706 | AC56: 680.82964 | AD56: 289.22323 | AE56: 340.45633 | AF56: 3106.1434 | AG56: 156.0566 | AH56: 882.07571 | AI56: 721.49554 | AJ56: 872.11437 | AK56: 355.37907 | AL56: 3921.2235 | AM56: 725.84497 | AN56: 363.13484 | AO56: 382.29547 | AP56: 230.35014 | AQ56: 533.24293 | AR56: 87.105717 | AS56: 62.407996 | AT56: 91.493002 | AU56: 26.775828 | AV56: 631.94792 | AW56: 761.13507 | AX56: 16732.047 | AY56: 8818.9589 | AZ56: 2554.2717 | BA56: 5204.6672 | BB56: 5321.2813 | BC56: 72.467839 | BD56: 328.64455 | BE56: 57.145727 | BF56: 87.252762 | BG56: 571.79887 | BH56: 184.26588 | BI56: 4048.7976 | BJ56: 236.48942 | BK56: 685.69266 | BL56: 220.72559 | BM56: 295.91744 | BN56: 239.99222 | BO56: 830.20475 | BP56: 78.821923 | BQ56: 3809.8181 | BR56: 316.69512 | BS56: 504.49717 | BT56: 409.62304 | BU56: 347.6563 | BV56: 80.772732 | BW56: 1440.9069 | BX56: 0 | BY56: 95151.019 | BZ56: 11538.987 | CA56: 0.43480694 | CB56: 0 | CC56: 32126.449 | CD56: 27.164585 | CE56: -0.053473668 | CF56: 43692.981 | CG56: 138844 | CI56: =CF56/CG56 -> 0.31469117
A57: S52 | B57: Alojamento | C57: 52 | D57: 4.1299404 | E57: 1.6539141 | F57: 1.885548 | G57: 7.1801427 | H57: 210.79459 | I57: 67.189308 | J57: 10.722197 | K57: 227.90752 | L57: 17.923759 | M57: 219.73661 | N57: 37.954435 | O57: 18.43123 | P57: 19.077939 | Q57: 16.258631 | R57: 20.680217 | S57: 6.5217089 | T57: 63.922052 | U57: 6.4289491 | V57: 24.168982 | W57: 0.61981904 | X57: 0.0039604365 | Y57: 11.931859 | Z57: 99.185218 | AA57: 109.70875 | AB57: 28.097571 | AC57: 149.94686 | AD57: 79.003465 | AE57: 57.578129 | AF57: 146.30126 | AG57: 33.30314 | AH57: 115.72905 | AI57: 112.15545 | AJ57: 84.579516 | AK57: 210.1091 | AL57: 92.814911 | AM57: 69.41308 | AN57: 44.510514 | AO57: 82.030391 | AP57: 53.462758 | AQ57: 111.47479 | AR57: 18.209508 | AS57: 13.046433 | AT57: 33.053968 | AU57: 9.7735636 | AV57: 701.01053 | AW57: 259.8759 | AX57: 2207.8944 | AY57: 143.84622 | AZ57: 3.2071103 | BA57: 48.469616 | BB57: 154.51379 | BC57: 1.437649 | BD57: 31.326821 | BE57: 41.951638 | BF57: 100.19454 | BG57: 64.72715 | BH57: 375.71862 | BI57: 679.87963 | BJ57: 43.252993 | BK57: 239.4412 | BL57: 184.68858 | BM57: 108.18452 | BN57: 103.50029 | BO57: 118.54613 | BP57: 29.531699 | BQ57: 1383.4049 | BR57: 155.66127 | BS57: 255.27052 | BT57: 224.24029 | BU57: 4.8312718 | BV57: 96.513917 | BW57: 4241.4455 | BX57: 0 | BY57: 14751.177 | BZ57: 6880.2093 | CA57: 0.24925655 | CB57: 0 | CC57: 6148.9937 | CD57: 6.3702419 | CE57: 0 | CF57: 13035.823 | CG57: 27787 | CI57: =CF57/CG57 -> 0.46913386
A58: S53 | B58: Alimentação | C58: 53 | D58: 5.7119933 | E58: 1.4331556 | F58: 2.3233255 | G58: 2.3478969 | H58: 283.53171 | I58: 12.248523 | J58: 7.5612081 | K58: 11.13271 | L58: 2.6990689 | M58: 142.84797 | N58: 4.3215952 | O58: 0.62829078 | P58: 10.940055 | Q58: 5.0451783 | R58: 1.5443919 | S58: 1.3941141 | T58: 10.376543 | U58: 13.041174 | V58: 6.3176787 | W58: 0.16201831 | X58: 0.0010352428 | Y58: 3.4775552 | Z58: 101.34717 | AA58: 120.55989 | AB58: 2.8213972 | AC58: 277.56403 | AD58: 19.001142 | AE58: 3.8044545 | AF58: 34.642971 | AG58: 59.37072 | AH58: 29.351326 | AI58: 6.3299635 | AJ58: 2.7023425 | AK58: 96.737355 | AL58: 401.0511 | AM58: 17.727466 | AN58: 3.8891572 | AO58: 3.4957758 | AP58: 91.230422 | AQ58: 196.26757 | AR58: 32.060486 | AS58: 22.970141 | AT58: 56.486009 | AU58: 12.38142 | AV58: 28.155344 | AW58: 166.75301 | AX58: 845.30467 | AY58: 43.108678 | AZ58: 6.6604751 | BA58: 789.18577 | BB58: 60.956711 | BC58: 246.79012 | BD58: 43.246198 | BE58: 4.9160156 | BF58: 676.29798 | BG58: 82.536731 | BH58: 45.198177 | BI58: 2652.6171 | BJ58: 76.064864 | BK58: 1420.0686 | BL58: 10.69921 | BM58: 244.56918 | BN58: 16.801665 | BO58: 1589.0944 | BP58: 6.7428345 | BQ58: 10034.804 | BR58: 1761.0157 | BS58: 264.58281 | BT58: 4477.652 | BU58: 4109.6975 | BV58: 62.948878 | BW58: 8593.9851 | BX58: 0 | BY58: 40481.333 | BZ58: 5122.7292 | CA58: 0.21106401 | CB58: 0 | CC58: 231328.33 | CD58: 5.3941564 | CE58: 0 | CF58: 236456.67 | CG58: 276938 | CI58: =CF58/CG58 -> 0.85382529
A59: S54 | B59: Edição e edição integrada à impressão | C59: 54 | D59: 2.0258132 | E59: 0.91149839 | F59: 0.18224302 | G59: 0.086837528 | H59: 1.1233094 | I59: 0.96245542 | J59: 0.24641011 | K59: 5.8841823 | L59: 0.69258435 | M59: 6.4348791 | N59: 10.596534 | O59: 0.23323678 | P59: 1.2834555 | Q59: 1.4841893 | R59: 0.81508009 | S59: 1.1191412 | T59: 6.5122799 | U59: 45.700344 | V59: 2.2185371 | W59: 0.056895361 | X59: 0.00038196835 | Y59: 0.78824225 | Z59: 121.28069 | AA59: 1.573078 | AB59: 0.6085789 | AC59: 1.2147818 | AD59: 2.3424463 | AE59: 1.1009232 | AF59: 1.7264799 | AG59: 0.52027498 | AH59: 1.7508633 | AI59: 9.7763993 | AJ59: 1.1422225 | AK59: 2.1106986 | AL59: 1.6438697 | AM59: 3.7261302 | AN59: 0.41958234 | AO59: 1.9487137 | AP59: 13.555992 | AQ59: 60.779444 | AR59: 9.9283773 | AS59: 7.1133119 | AT59: 18.017855 | AU59: 5.1970877 | AV59: 5.462843 | AW59: 8.6483782 | AX59: 546.4153 | AY59: 4.7530342 | AZ59: 0.14129981 | BA59: 1.7442844 | BB59: 5.8243706 | BC59: 49.678507 | BD59: 11.82315 | BE59: 66.255004 | BF59: 11.912114 | BG59: 116.15928 | BH59: 27.293283 | BI59: 1117.0738 | BJ59: 50.804095 | BK59: 261.00113 | BL59: 105.79011 | BM59: 1522.684 | BN59: 19.496105 | BO59: 65.060908 | BP59: 0.41834075 | BQ59: 861.45929 | BR59: 2152.4844 | BS59: 1193.043 | BT59: 29.877389 | BU59: 116.80605 | BV59: 18.994664 | BW59: 125.85249 | BX59: 0 | BY59: 8853.793 | BZ59: 788.70626 | CA59: 0.18694241 | CB59: 0 | CC59: 8410.8482 | CD59: 25.385909 | CE59: -175.9203 | CF59: 9049.207 | CG59: 17903 | CI59: =CF59/CG59 -> 0.50545758
A60: S55 | B60: Atividades de televisão, rádio, cinema e gravação/edição de som e imagem | C60: 55 | D60: 1.4623937 | E60: 0.74959421 | F60: 0.068320076 | G60: 0.052242623 | H60: 0.4462048 | I60: 0.2102032 | J60: 0.0549785 | K60: 2.4564688 | L60: 0.08268981 | M60: 2.3987122 | N60: 0.45741898 | O60: 0.17031789 | P60: 0.44932796 | Q60: 0.59337073 | R60: 0.43556961 | S60: 0.18500158 | T60: 0.59992883 | U60: 0.12323921 | V60: 1.5341917 | W60: 0.039344695 | X60: 0.00025139945 | Y60: 0.1740964 | Z60: 0.78391529 | AA60: 0.48273775 | AB60: 0.33535902 | AC60: 0.39313733 | AD60: 0.78057684 | AE60: 0.50300548 | AF60: 0.57894524 | AG60: 0.34079801 | AH60: 0.58084695 | AI60: 0.86508674 | AJ60: 0.53800501 | AK60: 0.95309496 | AL60: 0.42722378 | AM60: 0.41364235 | AN60: 0.13424463 | AO60: 0.54666389 | AP60: 0.47352152 | AQ60: 0.44168181 | AR60: 0.072149126 | AS60: 0.051692156 | AT60: 0.029764374 | AU60: 0.1582293 | AV60: 2.5908658 | AW60: 0.92628261 | AX60: 10.199375 | AY60: 2.0504121 | AZ60: 0.035482509 | BA60: 0.099604293 | BB60: 0.69255755 | BC60: 4.1351882 | BD60: 2.9238604 | BE60: 9.607955 | BF60: 5381.7137 | BG60: 4752.7742 | BH60: 1.5258284 | BI60: 3.2627424 | BJ60: 0.61568537 | BK60: 1.3016963 | BL60: 0.29090176 | BM60: 30979.524 | BN60: 0.30813851 | BO60: 33.35352 | BP60: 2.9272783 | BQ60: 1.0633686 | BR60: 0.4928567 | BS60: 1.1412073 | BT60: 0.56259616 | BU60: 1.867759 | BV60: 122.96938 | BW60: 1.1216463 | BX60: 0 | BY60: 41342.707 | BZ60: 601.25606 | CA60: 0.15478028 | CB60: 0 | CC60: 1925.9269 | CD60: 3.9557147 | CE60: 0 | CF60: 2531.2934 | CG60: 43874 | CI60: =CF60/CG60 -> 0.057694612
... A78: S73 | B78: Serviços domésticos | C78: 73 | D78: 0 | E78: 0 | F78: 0 | G78: 0 | H78: 0 | I78: 0 | J78: 0 | K78: 0 | L78: 0 | M78: 0 | N78: 0 | O78: 0 | P78: 0 | Q78: 0 | R78: 0 | S78: 0 | T78: 0 | U78: 0 | V78: 0 | W78: 0 | X78: 0 | Y78: 0 | Z78: 0 | AA78: 0 | AB78: 0 | AC78: 0 | AD78: 0 | AE78: 0 | AF78: 0 | AG78: 0 | AH78: 0 | AI78: 0 | AJ78: 0 | AK78: 0 | AL78: 0 | AM78: 0 | AN78: 0 | AO78: 0 | AP78: 0 | AQ78: 0 | AR78: 0 | AS78: 0 | AT78: 0 | AU78: 0 | AV78: 0 | AW78: 0 | AX78: 0 | AY78: 0 | AZ78: 0 | BA78: 0 | BB78: 0 | BC78: 0 | BD78: 0 | BE78: 0 | BF78: 0 | BG78: 0 | BH78: 0 | BI78: 0 | BJ78: 0 | BK78: 0 | BL78: 0 | BM78: 0 | BN78: 0 | BO78: 0 | BP78: 0 | BQ78: 0 | BR78: 0 | BS78: 0 | BT78: 0 | BU78: 0 | BV78: 0 | BW78: 0 | BX78: 0 | BY78: 0 | BZ78: 0 | CA78: 0 | CB78: 0 | CC78: 74451 | CD78: 0 | CE78: 0 | CF78: 74451 | CG78: 74451 | CI78: =CF78/CG78 -> 1
B79: Prod Nac | C79: 74 | D79: 149151.39 | E79: 68079.254 | F79: 8177.4548 | G79: 9360.8652 | H79: 86780.302 | I79: 38249.787 | J79: 8861.9731 | K79: 226295.97 | L79: 40680.402 | M79: 229159.4 | N79: 47291.889 | O79: 10510.046 | P79: 30369.291 | Q79: 29704.034 | R79: 22278.689 | S79: 17495.769 | T79: 62825.276 | U79: 8728.225 | V79: 287013.67 | W79: 6884.7092 | X79: 3133.1479 | Y79: 39806.995 | Z79: 93685.49 | AA79: 50165.759 | AB79: 29616.109 | AC79: 32534.935 | AD79: 67095.931 | AE79: 47995.653 | AF79: 90011.633 | AG79: 42241.063 | AH79: 55292.639 | AI79: 48924.359 | AJ79: 43882.672 | AK79: 69100.829 | AL79: 125399.05 | AM79: 57957.342 | AN79: 14198.782 | AO79: 34015.197 | AP79: 34232.729 | AQ79: 127681.24 | AR79: 18161.429 | AS79: 4642.9823 | AT79: 13663.351 | AU79: 25919.117 | AV79: 258586.87 | AW79: 61466.17 | AX79: 379634.9 | AY79: =SUM(AY6:AY78) -> 182365.77 | AZ79: 10000.749 | BA79: 22005.894 | BB79: 50075.886 | BC79: 11174.565 | BD79: 120776.23 | BE79: 7719.1866 | BF79: 22366.727 | BG79: 80996.904 | BH79: 45349.946 | BI79: 196028.97 | BJ79: 44529.805 | BK79: 62859.567 | BL79: 18857.747 | BM79: 59576.858 | BN79: 14344.205 | BO79: 71519.591 | BP79: 6663.1352 | BQ79: 207583.76 | BR79: 47100.065 | BS79: 34108.375 | BT79: 55184.158 | BU79: 109176.75 | BV79: 14856.013 | BW79: 67590.784 | BX79: 0 | BY79: 4840485.2 | BZ79: 1025056 | CA79: 1393480 | CB79: 102253 | CC79: 3769922 | CD79: 878944.83 | CE79: -131 | CF79: 7169524.8 | CG79: 12010010
B80: Importado | C80: 75 | D80: 24183.129 | E80: 5755.6609 | F80: 537.51612 | G80: 1556.2578 | H80: 27867.644 | I80: 5714.0844 | J80: 1597.9782 | K80: 6328.4894 | L80: 797.17685 | M80: 16720.175 | N80: 3497.4522 | O80: 722.70448 | P80: 5295.776 | Q80: 4427.6391 | R80: 2917.4641 | S80: 1608.7089 | T80: 9260.3347 | U80: 1398.3211 | V80: 55572.301 | W80: 1426.2976 | X80: 53.305845 | Y80: 1431.7307 | Z80: 48562.221 | AA80: 17822.444 | AB80: 6237.9026 | AC80: 5422.9335 | AD80: 17408.563 | AE80: 6069.3113 | AF80: 19877.812 | AG80: 11436.201 | AH80: 8465.1792 | AI80: 30697.93 | AJ80: 11191.577 | AK80: 15905.433 | AL80: 26596.214 | AM80: 12200.315 | AN80: 14472.288 | AO80: 4902.2705 | AP80: 13043.475 | AQ80: 9178.8369 | AR80: 1499.3714 | AS80: 1074.2436 | AT80: 1248.4881 | AU80: 3312.4579 | AV80: 25282.9 | AW80: 9933.6931 | AX80: 25771.75 | AY80: 14216.85 | AZ80: 1813.1869 | BA80: 6864.6108 | BB80: 5592.0703 | BC80: 580.0006 | BD80: 7774.4096 | BE80: 867.59187 | BF80: 2456.9546 | BG80: 6453.1873 | BH80: 7361.4426 | BI80: 10937.472 | BJ80: 2406.1138 | BK80: 3950.1054 | BL80: 3129.4021 | BM80: 2737.6559 | BN80: 2492.8391 | BO80: 5948.6571 | BP80: 637.79733 | BQ80: 14920.461 | BR80: 4536.5689 | BS80: 3659.9193 | BT80: 7433.0689 | BU80: 11490.934 | BV80: 1279.3587 | BW80: 10473.725 | BX80: 0 | BY80: 666298.34 | BZ80: 0 | CA80: 0 | CB80: 0 | CC80: 223389.89 | CD80: 107785.77 | CE80: 0 | CF80: 331175.66 | CG80: 997474
B81: Imp Import | C81: 76 | D81: 712.48471 | E81: 199.5759 | F81: 13.047764 | G81: 76.297227 | H81: 466.80115 | I81: 239.77884 | J81: 45.092211 | K81: 238.16234 | L81: 10.760873 | M81: 528.53165 | N81: 179.89358 | O81: 15.484262 | P81: 582.11499 | Q81: 903.7247 | R81: 373.57057 | S81: 89.304294 | T81: 245.81929 | U81: 54.472307 | V81: 155.63269 | W81: 3.9944096 | X81: 0.14928538 | Y81: 46.298515 | Z81: 853.5344 | AA81: 659.64531 | AB81: 267.98503 | AC81: 175.63799 | AD81: 1221.5685 | AE81: 203.34953 | AF81: 250.88856 | AG81: 153.88986 | AH81: 467.94078 | AI81: 1037.8875 | AJ81: 727.82478 | AK81: 1148.6944 | AL81: 2358.4851 | AM81: 941.11738 | AN81: 205.25746 | AO81: 337.80723 | AP81: 775.38843 | AQ81: 314.97887 | AR81: 51.452084 | AS81: 36.863498 | AT81: 42.842833 | AU81: 59.210497 | AV81: 1773.444 | AW81: 813.62324 | AX81: 365.11869 | AY81: 764.6132 | AZ81: 11.32522 | BA81: 28.371281 | BB81: 40.502798 | BC81: 23.078653 | BD81: 276.9793 | BE81: 6.1069491 | BF81: 23.590256 | BG81: 46.680084 | BH81: 85.295711 | BI81: 46.890031 | BJ81: 70.859998 | BK81: 71.367215 | BL81: 85.10213 | BM81: 31.274499 | BN81: 44.544242 | BO81: 239.64417 | BP81: 14.531849 | BQ81: 164.15405 | BR81: 116.15244 | BS81: 12.221295 | BT81: 240.39342 | BU81: 698.18873 | BV81: 16.167585 | BW81: 154.32497 | BX81: 0 | BY81: 23737.788 | BZ81: 0 | CA81: 0 | CB81: 0 | CC81: 11407.196 | CD81: 5430.0163 | CE81: 0 | CF81: 16837.212 | CG81: 40575
B82: ICMS Total | C82: 77 | D82: 8343.3248 | E82: 4147.5786 | F82: 444.5748 | G82: 280.50113 | H82: 2135.2467 | I82: 953.89695 | J82: 215.15108 | K82: 7586.0308 | L82: 306.04427 | M82: 6674.5662 | N82: 2477.124 | O82: 442.39621 | P82: 1237.9742 | Q82: 1774.1848 | R82: 1798.833 | S82: 1016.1477 | T82: 2030.5233 | U82: 435.32753 | V82: 8752.2784 | W82: 178.62543 | X82: 0.36781858 | Y82: 628.38128 | Z82: 2149.1884 | AA82: 1286.9069 | AB82: 1455.429 | AC82: 1781.9362 | AD82: 1993.9188 | AE82: 2222.71 | AF82: 1552.7652 | AG82: 965.71295 | AH82: 1751.693 | AI82: 2602.761 | AJ82: 1490.1682 | AK82: 1879.5987 | AL82: 2966.0638 | AM82: 1722.8801 | AN82: 883.29842 | AO82: 1714.3592 | AP82: 1225.2546 | AQ82: 12175.833 | AR82: 1988.9335 | AS82: 1424.9966 | AT82: 1656.134 | AU82: 1108.2852 | AV82: 10706.709 | AW82: 1612.3979 | AX82: 10468.138 | AY82: 8076.6371 | AZ82: 111.34152 | BA82: 2402.9494 | BB82: 783.90607 | BC82: 694.50274 | BD82: 10107.12 | BE82: 290.44062 | BF82: 399.46081 | BG82: 4518.3805 | BH82: 1004.7901 | BI82: 3115.6887 | BJ82: 907.5556 | BK82: 1600.7393 | BL82: 638.51923 | BM82: 1102.1474 | BN82: 490.89624 | BO82: 3608.0465 | BP82: 253.90625 | BQ82: 5343.4811 | BR82: 2010.6387 | BS82: 1049.8188 | BT82: 3299.4808 | BU82: 7722.846 | BV82: 443.82303 | BW82: 3537.0443 | BX82: 0 | BY82: 186159.31 | BZ82: 0 | CA82: 0 | CB82: 0 | CC82: 274756.24 | CD82: 18394.451 | CE82: 0 | CF82: 293150.69 | CG82: 479310
B83: Zeros | C83: 78 | D83: 0 | E83: 0 | F83: 0 | G83: 0 | H83: 0 | I83: 0 | J83: 0 | K83: 0 | L83: 0 | M83: 0 | N83: 0 | O83: 0 | P83: 0 | Q83: 0 | R83: 0 | S83: 0 | T83: 0 | U83: 0 | V83: 0 | W83: 0 | X83: 0 | Y83: 0 | Z83: 0 | AA83: 0 | AB83: 0 | AC83: 0 | AD83: 0 | AE83: 0 | AF83: 0 | AG83: 0 | AH83: 0 | AI83: 0 | AJ83: 0 | AK83: 0 | AL83: 0 | AM83: 0 | AN83: 0 | AO83: 0 | AP83: 0 | AQ83: 0 | AR83: 0 | AS83: 0 | AT83: 0 | AU83: 0 | AV83: 0 | AW83: 0 | AX83: 0 | AY83: 0 | AZ83: 0 | BA83: 0 | BB83: 0 | BC83: 0 | BD83: 0 | BE83: 0 | BF83: 0 | BG83: 0 | BH83: 0 | BI83: 0 | BJ83: 0 | BK83: 0 | BL83: 0 | BM83: 0 | BN83: 0 | BO83: 0 | BP83: 0 | BQ83: 0 | BR83: 0 | BS83: 0 | BT83: 0 | BU83: 0 | BV83: 0 | BW83: 0 | BX83: 0 | BY83: 0 | BZ83: 0 | CA83: 0 | CB83: 0 | CC83: 0 | CD83: 0 | CE83: 0 | CF83: 0 | CG83: 0
B84: IPI Total | C84: 79 | D84: 92.83045 | E84: 108.75609 | F84: 8.8181189 | G84: 43.901705 | H84: 149.82467 | I84: 114.79842 | J84: 21.270716 | K84: 343.65182 | L84: 12.27611 | M84: 474.52055 | N84: 656.88983 | O84: 224.92679 | P84: 64.127689 | Q84: 91.499562 | R84: 95.836041 | S84: 103.98039 | T84: 264.25549 | U84: 70.396165 | V84: 98.002876 | W84: 2.0001427 | X84: 0.0041186166 | Y84: 10.183701 | Z84: 85.352802 | AA84: 111.77922 | AB84: 205.31806 | AC84: 57.339309 | AD84: 488.98762 | AE84: 148.60719 | AF84: 123.62493 | AG84: 62.22164 | AH84: 343.11461 | AI84: 1261.8141 | AJ84: 422.20155 | AK84: 506.16003 | AL84: 1432.0627 | AM84: 488.59848 | AN84: 502.12281 | AO84: 267.14322 | AP84: 455.42621 | AQ84: 200.78386 | AR84: 32.798227 | AS84: 23.498705 | AT84: 27.310243 | AU84: 42.842027 | AV84: 1560.7762 | AW84: 461.77681 | AX84: 574.3649 | AY84: 548.46866 | AZ84: 6.291749 | BA84: 28.427618 | BB84: 34.720319 | BC84: 52.355074 | BD84: 1985.9758 | BE84: 26.799991 | BF84: 40.444089 | BG84: 47.213289 | BH84: 192.23565 | BI84: 87.152662 | BJ84: 78.291817 | BK84: 125.437 | BL84: 82.52707 | BM84: 60.613208 | BN84: 52.163486 | BO84: 368.76159 | BP84: 18.233672 | BQ84: 160.10975 | BR84: 131.36614 | BS84: 33.137338 | BT84: 133.81203 | BU84: 479.39071 | BV84: 25.764398 | BW84: 246.34988 | BX84: 0 | BY84: 17984.82 | BZ84: 0 | CA84: 0 | CB84: 0 | CC84: 27535.434 | CD84: 8464.7465 | CE84: 0 | CF84: 36000.18 | CG84: 53985
B85: Zeros | C85: 80 | D85: 0 | E85: 0 | F85: 0 | G85: 0 | H85: 0 | I85: 0 | J85: 0 | K85: 0 | L85: 0 | M85: 0 | N85: 0 | O85: 0 | P85: 0 | Q85: 0 | R85: 0 | S85: 0 | T85: 0 | U85: 0 | V85: 0 | W85: 0 | X85: 0 | Y85: 0 | Z85: 0 | AA85: 0 | AB85: 0 | AC85: 0 | AD85: 0 | AE85: 0 | AF85: 0 | AG85: 0 | AH85: 0 | AI85: 0 | AJ85: 0 | AK85: 0 | AL85: 0 | AM85: 0 | AN85: 0 | AO85: 0 | AP85: 0 | AQ85: 0 | AR85: 0 | AS85: 0 | AT85: 0 | AU85: 0 | AV85: 0 | AW85: 0 | AX85: 0 | AY85: 0 | AZ85: 0 | BA85: 0 | BB85: 0 | BC85: 0 | BD85: 0 | BE85: 0 | BF85: 0 | BG85: 0 | BH85: 0 | BI85: 0 | BJ85: 0 | BK85: 0 | BL85: 0 | BM85: 0 | BN85: 0 | BO85: 0 | BP85: 0 | BQ85: 0 | BR85: 0 | BS85: 0 | BT85: 0 | BU85: 0 | BV85: 0 | BW85: 0 | BX85: 0 | BY85: 0 | BZ85: 0 | CA85: 0 | CB85: 0 | CC85: 0 | CD85: 0 | CE85: 0 | CF85: 0 | CG85: 0
B86: Outros IIL Total | C86: 81 | D86: 6042.8387 | E86: 1976.1746 | F86: 280.58837 | G86: 542.17693 | H86: 7778.1809 | I86: 1919.654 | J86: 507.53471 | K86: 5782.6909 | L86: 1324.3403 | M86: 5357.8042 | N86: 2360.7513 | O86: 196.44201 | P86: 1196.7163 | Q86: 1126.9178 | R86: 813.60704 | S86: 614.08995 | T86: 3188.7908 | U86: 386.25785 | V86: 41050.979 | W86: 837.81029 | X86: 1.7251865 | Y86: 1189.411 | Z86: 7474.2134 | AA86: 3009.4653 | AB86: 1473.2559 | AC86: 1482.2181 | AD86: 3363.0311 | AE86: 2491.3685 | AF86: 4071.2767 | AG86: 2442.911 | AH86: 2290.4334 | AI86: 3419.2493 | AJ86: 2196.5567 | AK86: 3229.2856 | AL86: 5950.1222 | AM86: 2615.7468 | AN86: 872.25178 | AO86: 1270.2224 | AP86: 1720.7274 | AQ86: 4884.6491 | AR86: 797.91186 | AS86: 571.67407 | AT86: 664.40077 | AU86: 1439.0873 | AV86: 10882.295 | AW86: 2927.3386 | AX86: 18595.729 | AY86: 6896.9237 | AZ86: 1024.1055 | BA86: 3522.7472 | BB86: 2896.9147 | BC86: 440.49756 | BD86: 5506.2819 | BE86: 380.87397 | BF86: 1598.8234 | BG86: 4872.6352 | BH86: 2867.2902 | BI86: 16130.832 | BJ86: 3723.3741 | BK86: 3130.7843 | BL86: 1098.7025 | BM86: 2497.4509 | BN86: 903.35185 | BO86: 3371.2999 | BP86: 393.3957 | BQ86: 14569.03 | BR86: 2067.2089 | BS86: 1689.5278 | BT86: 2196.0872 | BU86: 3526.8894 | BV86: 760.87382 | BW86: 3517.7723 | BX86: 0 | BY86: 264194.58 | BZ86: 0 | CA86: 0 | CB86: 0 | CC86: 116537.24 | CD86: 38389.184 | CE86: 0 | CF86: 154926.42 | CG86: 419121
B87: Zeros | C87: 82 | D87: 0 | E87: 0 | F87: 0 | G87: 0 | H87: 0 | I87: 0 | J87: 0 | K87: 0 | L87: 0 | M87: 0 | N87: 0 | O87: 0 | P87: 0 | Q87: 0 | R87: 0 | S87: 0 | T87: 0 | U87: 0 | V87: 0 | W87: 0 | X87: 0 | Y87: 0 | Z87: 0 | AA87: 0 | AB87: 0 | AC87: 0 | AD87: 0 | AE87: 0 | AF87: 0 | AG87: 0 | AH87: 0 | AI87: 0 | AJ87: 0 | AK87: 0 | AL87: 0 | AM87: 0 | AN87: 0 | AO87: 0 | AP87: 0 | AQ87: 0 | AR87: 0 | AS87: 0 | AT87: 0 | AU87: 0 | AV87: 0 | AW87: 0 | AX87: 0 | AY87: 0 | AZ87: 0 | BA87: 0 | BB87: 0 | BC87: 0 | BD87: 0 | BE87: 0 | BF87: 0 | BG87: 0 | BH87: 0 | BI87: 0 | BJ87: 0 | BK87: 0 | BL87: 0 | BM87: 0 | BN87: 0 | BO87: 0 | BP87: 0 | BQ87: 0 | BR87: 0 | BS87: 0 | BT87: 0 | BU87: 0 | BV87: 0 | BW87: 0 | BX87: 0 | BY87: 0 | BZ87: 0 | CA87: 0 | CB87: 0 | CC87: 0 | CD87: 0 | CE87: 0 | CF87: 0 | CG87: 0
B88: CONSUMO INTERMEDIÁRIO | C88: 83 | D88: 188526 | E88: 80267 | F88: 9462 | G88: 11860 | H88: 125178 | I88: 47192 | J88: 11249 | K88: 246575 | L88: 43131 | M88: 258915 | N88: 56464 | O88: 12112 | P88: 38746 | Q88: 38028 | R88: 28278 | S88: 20928 | T88: 77815 | U88: 11073 | V88: 392642.86 | W88: 9333.4371 | X88: 3188.7001 | Y88: 43113 | Z88: 152810 | AA88: 73056 | AB88: 39256 | AC88: 41455 | AD88: 91572 | AE88: 59131 | AF88: 115888 | AG88: 57302 | AH88: 68611 | AI88: 87944 | AJ88: 59911 | AK88: 91770 | AL88: 164702 | AM88: 75926 | AN88: 31134 | AO88: 42507 | AP88: 51453 | AQ88: 154436.32 | AR88: 22531.896 | AS88: 7774.2588 | AT88: 17302.527 | AU88: 31881 | AV88: 308793 | AW88: 77215 | AX88: 435410 | AY88: =SUM(AY79:AY87) -> 212869.26 | AZ88: 12967 | BA88: 34853 | BB88: 59424 | BC88: 12965 | BD88: 146427 | BE88: 9291 | BF88: 26886 | BG88: 96935 | BH88: 56861 | BI88: 226347 | BJ88: 51716 | BK88: 71738 | BL88: 23892 | BM88: 66006 | BN88: 18328 | BO88: 85056 | BP88: 7981 | BQ88: 242741 | BR88: 55962 | BS88: 40553 | BT88: 68487 | BU88: 133095 | BV88: 17382 | BW88: 85520 | BX88: 0 | BY88: 5998860 | BZ88: 1025056 | CA88: 1393480 | CB88: 102253 | CC88: 4423548 | CD88: 1057409 | CE88: -131 | CF88: 8001615 | CG88: 14000475
A89: R10 | B89: Remunerações | C89: 84 | D89: 34356 | E89: 22217 | F89: 2255 | G89: 4126 | H89: 16917 | I89: 4502 | J89: 2607 | K89: 30117 | L89: 8690 | M89: 35422 | N89: 9953 | O89: 1711 | P89: 11262 | Q89: 18543 | R89: 11048 | S89: 6644 | T89: 14028 | U89: 5664 | V89: 8644.8181 | W89: 222.3 | X89: 24.88187 | Y89: 7013 | Z89: 12903 | AA89: 9380 | AB89: 6854 | AC89: 12695 | AD89: 22917 | AE89: 19150 | AF89: 13401 | AG89: 6247 | AH89: 22042 | AI89: 9775 | AJ89: 14631 | AK89: 27620 | AL89: 20483 | AM89: 20855 | AN89: 8257 | AO89: 16648 | AP89: 13057 | AQ89: 14489.444 | AR89: 1691.8722 | AS89: 1627.8645 | AT89: 3685.8193 | AU89: 22993 | AV89: 104570 | AW89: 49181 | AX89: 352528 | AY89: =AY90+AY91+AY94 -> 87877 | AZ89: 5137 | BA89: 7492 | BB89: 44037 | BC89: 11307 | BD89: 60116 | BE89: 6798 | BF89: 11678 | BG89: 19212 | BH89: 57187 | BI89: 165217 | BJ89: 7923 | BK89: 61939 | BL89: 18585 | BM89: 15429 | BN89: 11344 | BO89: 118404 | BP89: 31074 | BQ89: 528703 | BR89: 282090 | BS89: 89933 | BT89: 127700 | BU89: 89831 | BV89: 13265 | BW89: 45395 | BX89: 74451 | BY89: 3055773 | BZ89: 0 | CA89: 0 | CB89: 0 | CC89: 0 | CD89: 0 | CE89: 0 | CF89: 0 | CG89: 3055773
A90: R11 | B90: Salários | C90: 85 | D90: 29230 | E90: 19506 | F90: 1981 | G90: 3307 | H90: 12359 | I90: 3581 | J90: 2011 | K90: 23432 | L90: 6252 | M90: 27911 | N90: 7718 | O90: 1309 | P90: 9222 | Q90: 14743 | R90: 9151 | S90: 5395 | T90: 11059 | U90: 4600 | V90: 6069.4556 | W90: 156.075 | X90: 17.469356 | Y90: 5622 | Z90: 9758 | AA90: 7225 | AB90: 5400 | AC90: 9702 | AD90: 17824 | AE90: 15527 | AF90: 10413 | AG90: 5015 | AH90: 17453 | AI90: 7775 | AJ90: 11477 | AK90: 21904 | AL90: 15859 | AM90: 17465 | AN90: 6659 | AO90: 13658 | AP90: 10523 | AQ90: 10400.448 | AR90: 1214.4171 | AS90: 1168.4727 | AT90: 2645.6621 | AU90: 17320 | AV90: 85935 | AW90: 40106 | AX90: 279452 | AY90: 71610 | AZ90: 4217 | BA90: 6119 | BB90: 34067 | BC90: 9520 | BD90: 50603 | BE90: 5563 | BF90: 9857 | BG90: 14372 | BH90: 45370 | BI90: 127124 | BJ90: 6253 | BK90: 50719 | BL90: 14886 | BM90: 12362 | BN90: 8992 | BO90: 95075 | BP90: 24376 | BQ90: 381003 | BR90: 227721 | BS90: 74374 | BT90: 102765 | BU90: 77743 | BV90: 11518 | BW90: 38820 | BX90: 70758 | BY90: 2422298 | BZ90: 0 | CA90: 0 | CB90: 0 | CC90: 0 | CD90: 0 | CE90: 0 | CF90: 0 | CG90: 2422298
A91: R12 | B91: Contribuições sociais efetivas | C91: 86 | D91: 5126 | E91: 2711 | F91: 274 | G91: 819 | H91: 4558 | I91: 921 | J91: 596 | K91: 6685 | L91: 2438 | M91: 7511 | N91: 2235 | O91: 402 | P91: 2040 | Q91: 3800 | R91: 1897 | S91: 1249 | T91: 2969 | U91: 1064 | V91: 2575.3625 | W91: 66.225 | X91: 7.412514 | Y91: 1391 | Z91: 3145 | AA91: 2155 | AB91: 1454 | AC91: 2993 | AD91: 5093 | AE91: 3623 | AF91: 2988 | AG91: 1232 | AH91: 4589 | AI91: 2000 | AJ91: 3154 | AK91: 5716 | AL91: 4624 | AM91: 3390 | AN91: 1598 | AO91: 2990 | AP91: 2534 | AQ91: 4088.9959 | AR91: 477.45506 | AS91: 459.39176 | AT91: 1040.1573 | AU91: 5673 | AV91: 18635 | AW91: 9075 | AX91: 73076 | AY91: =SUM(AY92:AY93) -> 16267 | AZ91: 920 | BA91: 1373 | BB91: 9970 | BC91: 1787 | BD91: 9513 | BE91: 1235 | BF91: 1821 | BG91: 4840 | BH91: 11817 | BI91: 38093 | BJ91: 1670 | BK91: 11220 | BL91: 3699 | BM91: 3067 | BN91: 2352 | BO91: 23329 | BP91: 6698 | BQ91: 64857 | BR91: 47663 | BS91: 15559 | BT91: 17672 | BU91: 12088 | BV91: 1747 | BW91: 6575 | BX91: 3693 | BY91: 536663 | BZ91: 0 | CA91: 0 | CB91: 0 | CC91: 0 | CD91: 0 | CE91: 0 | CF91: 0 | CG91: 536663
B92: Previdência oficial /FGTS | C92: 87 | D92: 5123 | E92: 2698 | F92: 272 | G92: 806 | H92: 3536 | I92: 884 | J92: 566 | K92: 6513 | L92: 2394 | M92: 7273 | N92: 2148 | O92: 367 | P92: 1996 | Q92: 3739 | R92: 1856 | S92: 1182 | T92: 2686 | U92: 1025 | V92: 1824.8227 | W92: 46.925 | X92: 5.2522797 | Y92: 1350 | Z92: 2868 | AA92: 1980 | AB92: 1412 | AC92: 2814 | AD92: 4943 | AE92: 3466 | AF92: 2727 | AG92: 1168 | AH92: 4470 | AI92: 1937 | AJ92: 3036 | AK92: 5460 | AL92: 4407 | AM92: 3257 | AN92: 1477 | AO92: 2905 | AP92: 2436 | AQ92: 3142.5814 | AR92: 366.94617 | AS92: 353.06369 | AT92: 799.40869 | AU92: 5109 | AV92: 18183 | AW92: 8959 | AX92: 71753 | AY92: 15650 | AZ92: 881 | BA92: 1333 | BB92: 8842 | BC92: 1736 | BD92: 9380 | BE92: 1198 | BF92: 1745 | BG92: 3960 | BH92: 11081 | BI92: 32184 | BJ92: 1614 | BK92: 10153 | BL92: 3565 | BM92: 3015 | BN92: 2297 | BO92: 22948 | BP92: 6601 | BQ92: 64134 | BR92: 47469 | BS92: 15429 | BT92: 17649 | BU92: 11939 | BV92: 1701 | BW92: 6456 | BX92: 3693 | BY92: 514373 | BZ92: 0 | CA92: 0 | CB92: 0 | CC92: 0 | CD92: 0 | CE92: 0 | CF92: 0 | CG92: 514373
B93: Previdência privada | C93: 88 | D93: 3 | E93: 13 | F93: 2 | G93: 13 | H93: 1022 | I93: 37 | J93: 30 | K93: 172 | L93: 44 | M93: 238 | N93: 87 | O93: 35 | P93: 44 | Q93: 61 | R93: 41 | S93: 67 | T93: 283 | U93: 39 | V93: 750.53977 | W93: 19.3 | X93: 2.1602344 | Y93: 41 | Z93: 277 | AA93: 175 | AB93: 42 | AC93: 179 | AD93: 150 | AE93: 157 | AF93: 261 | AG93: 64 | AH93: 119 | AI93: 63 | AJ93: 118 | AK93: 256 | AL93: 217 | AM93: 133 | AN93: 121 | AO93: 85 | AP93: 98 | AQ93: 946.41449 | AR93: 110.50889 | AS93: 106.32806 | AT93: 240.74856 | AU93: 564 | AV93: 452 | AW93: 116 | AX93: 1323 | AY93: 617 | AZ93: 39 | BA93: 40 | BB93: 1128 | BC93: 51 | BD93: 133 | BE93: 37 | BF93: 76 | BG93: 880 | BH93: 736 | BI93: 5909 | BJ93: 56 | BK93: 1067 | BL93: 134 | BM93: 52 | BN93: 55 | BO93: 381 | BP93: 97 | BQ93: 723 | BR93: 194 | BS93: 130 | BT93: 23 | BU93: 149 | BV93: 46 | BW93: 119 | BX93: 0 | BY93: 22290 | BZ93: 0 | CA93: 0 | CB93: 0 | CC93: 0 | CD93: 0 | CE93: 0 | CF93: 0 | CG93: 22290
A94: R13 | B94: Contribuições sociais imputadas | C94: 89 | D94: 0 | E94: 0 | F94: 0 | G94: 0 | H94: 0 | I94: 0 | J94: 0 | K94: 0 | L94: 0 | M94: 0 | N94: 0 | O94: 0 | P94: 0 | Q94: 0 | R94: 0 | S94: 0 | T94: 0 | U94: 0 | V94: 0 | W94: 0 | X94: 0 | Y94: 0 | Z94: 0 | AA94: 0 | AB94: 0 | AC94: 0 | AD94: 0 | AE94: 0 | AF94: 0 | AG94: 0 | AH94: 0 | AI94: 0 | AJ94: 0 | AK94: 0 | AL94: 0 | AM94: 0 | AN94: 0 | AO94: 0 | AP94: 0 | AQ94: 0 | AR94: 0 | AS94: 0 | AT94: 0 | AU94: 0 | AV94: 0 | AW94: 0 | AX94: 0 | AY94: 0 | AZ94: 0 | BA94: 0 | BB94: 0 | BC94: 0 | BD94: 0 | BE94: 0 | BF94: 0 | BG94: 0 | BH94: 0 | BI94: 0 | BJ94: 0 | BK94: 0 | BL94: 0 | BM94: 0 | BN94: 0 | BO94: 0 | BP94: 0 | BQ94: 82843 | BR94: 6706 | BS94: 0 | BT94: 7263 | BU94: 0 | BV94: 0 | BW94: 0 | BX94: 0 | BY94: 96812 | BZ94: 0 | CA94: 0 | CB94: 0 | CC94: 0 | CD94: 0 | CE94: 0 | CF94: 0 | CG94: 96812
A95: N2 | B95: Excedente operacional bruto e rendimento misto bruto | C95: 90 | D95: 182575 | E95: 48953 | F95: 26039 | G95: 3887 | H95: 82275 | I95: 40026 | J95: 4247 | K95: 13233 | L95: -927 | M95: 27501 | N95: 11221 | O95: 1741 | P95: 4276 | Q95: 9211 | R95: 4032 | S95: 4783 | T95: 16893 | U95: 4315 | V95: 31352.535 | W95: 806.225 | X95: 90.240153 | Y95: 4134 | Z95: 12505 | AA95: 5167 | AB95: 3587 | AC95: 21406 | AD95: 5651 | AE95: 4831 | AF95: 19673 | AG95: 9072 | AH95: 10310 | AI95: 4751 | AJ95: 4693 | AK95: 8755 | AL95: 1419 | AM95: 8283 | AN95: 2054 | AO95: 15383 | AP95: 14972 | AQ95: 60670.726 | AR95: 9910.6183 | AS95: 7100.5882 | AT95: 18879.067 | AU95: 26426 | AV95: 135690 | AW95: 47260 | AX95: 320736 | AY95: =AY96+AY97 -> 75354 | AZ95: 4521 | BA95: 1775 | BB95: 33698 | BC95: 3121 | BD95: 68654 | BE95: 1586 | BF95: 3948 | BG95: 43825 | BH95: 51289 | BI95: 249222 | BJ95: 579640 | BK95: 92276 | BL95: 20171 | BM95: 22865 | BN95: 18437 | BO95: 54852 | BP95: 2998 | BQ95: 87157 | BR95: 13026 | BS95: 10137 | BT95: 6529 | BU95: 77062 | BV95: 9413 | BW95: 39805 | BX95: 0 | BY95: 2871210 | BZ95: 0 | CA95: 0 | CB95: 0 | CC95: 0 | CD95: 0 | CE95: 0 | CF95: 0 | CG95: 2871210
B96: Rendimento misto bruto | C96: 91 | D96: 97228 | E96: 38269 | F96: 12179 | G96: 254 | H96: 0 | I96: 0 | J96: 0 | K96: 365 | L96: 0 | M96: 4151 | N96: 23 | O96: 0 | P96: 1228 | Q96: 6429 | R96: 625 | S96: 1625 | T96: 296 | U96: 460 | V96: 0 | W96: 0 | X96: 0 | Y96: 0 | Z96: 0 | AA96: 0 | AB96: 585 | AC96: 0 | AD96: 373 | AE96: 799 | AF96: 0 | AG96: -18 | AH96: 2385 | AI96: 0 | AJ96: 0 | AK96: 0 | AL96: 0 | AM96: 28 | AN96: 0 | AO96: 1333 | AP96: 5023 | AQ96: 0 | AR96: 0 | AS96: 0 | AT96: 0 | AU96: 1734 | AV96: 68569 | AW96: 22740 | AX96: 58881 | AY96: 25394 | AZ96: 430 | BA96: 0 | BB96: 1273 | BC96: 1302 | BD96: 48476 | BE96: 56 | BF96: 853 | BG96: 253 | BH96: 9240 | BI96: 2638 | BJ96: 4300 | BK96: 39398 | BL96: 11034 | BM96: 6368 | BN96: 793 | BO96: 7868 | BP96: 1175 | BQ96: 0 | BR96: 0 | BS96: 7947 | BT96: 0 | BU96: 50020 | BV96: 6325 | BW96: 32861 | BX96: 0 | BY96: 583568 | BZ96: 0 | CA96: 0 | CB96: 0 | CC96: 0 | CD96: 0 | CE96: 0 | CF96: 0 | CG96: 583568
B97: Excedente operacional bruto (EOB) | C97: 92 | D97: 85347 | E97: 10684 | F97: 13860 | G97: 3633 | H97: 82275 | I97: 40026 | J97: 4247 | K97: 12868 | L97: -927 | M97: 23350 | N97: 11198 | O97: 1741 | P97: 3048 | Q97: 2782 | R97: 3407 | S97: 3158 | T97: 16597 | U97: 3855 | V97: 31352.535 | W97: 806.225 | X97: 90.240153 | Y97: 4134 | Z97: 12505 | AA97: 5167 | AB97: 3002 | AC97: 21406 | AD97: 5278 | AE97: 4032 | AF97: 19673 | AG97: 9090 | AH97: 7925 | AI97: 4751 | AJ97: 4693 | AK97: 8755 | AL97: 1419 | AM97: 8255 | AN97: 2054 | AO97: 14050 | AP97: 9949 | AQ97: 60670.726 | AR97: 9910.6183 | AS97: 7100.5882 | AT97: 18879.067 | AU97: 24692 | AV97: 67121 | AW97: 24520 | AX97: 261855 | AY97: 49960 | AZ97: 4091 | BA97: 1775 | BB97: 32425 | BC97: 1819 | BD97: 20178 | BE97: 1530 | BF97: 3095 | BG97: 43572 | BH97: 42049 | BI97: 246584 | BJ97: 575340 | BK97: 52878 | BL97: 9137 | BM97: 16497 | BN97: 17644 | BO97: 46984 | BP97: 1823 | BQ97: 87157 | BR97: 13026 | BS97: 2190 | BT97: 6529 | BU97: 27042 | BV97: 3088 | BW97: 6944 | BX97: 0 | BY97: 2287642 | BZ97: 0 | CA97: 0 | CB97: 0 | CC97: 0 | CD97: 0 | CE97: 0 | CF97: 0 | CG97: 2287642
A98: N0 | B98: VALOR ADICIONADO CUSTO FATORES | C98: 93 | D98: 216931 | E98: 71170 | F98: 28294 | G98: 8013 | H98: 99192 | I98: 44528 | J98: 6854 | K98: 43350 | L98: 7763 | M98: 62923 | N98: 21174 | O98: 3452 | P98: 15538 | Q98: 27754 | R98: 15080 | S98: 11427 | T98: 30921 | U98: 9979 | V98: 39997.353 | W98: 1028.525 | X98: 115.12202 | Y98: 11147 | Z98: 25408 | AA98: 14547 | AB98: 10441 | AC98: 34101 | AD98: 28568 | AE98: 23981 | AF98: 33074 | AG98: 15319 | AH98: 32352 | AI98: 14526 | AJ98: 19324 | AK98: 36375 | AL98: 21902 | AM98: 29138 | AN98: 10311 | AO98: 32031 | AP98: 28029 | AQ98: 75160.17 | AR98: 11602.49 | AS98: 8728.4526 | AT98: 22564.887 | AU98: 49419 | AV98: 240260 | AW98: 96441 | AX98: 673264 | AY98: =AY95+AY89 -> 163231 | AZ98: 9658 | BA98: 9267 | BB98: 77735 | BC98: 14428 | BD98: 128770 | BE98: 8384 | BF98: 15626 | BG98: 63037 | BH98: 108476 | BI98: 414439 | BJ98: 587563 | BK98: 154215 | BL98: 38756 | BM98: 38294 | BN98: 29781 | BO98: 173256 | BP98: 34072 | BQ98: 615860 | BR98: 295116 | BS98: 100070 | BT98: 134229 | BU98: 166893 | BV98: 22678 | BW98: 85200 | BX98: 74451 | BY98: 5926983 | BZ98: 0 | CA98: 0 | CB98: 0 | CC98: 0 | CD98: 0 | CE98: 0 | CF98: 0 | CG98: 5926983
A99: R22 | B99: Outros impostos sobre a produção | C99: 94 | D99: 1841 | E99: 641 | F99: 151 | G99: 199 | H99: 1568 | I99: 630 | J99: 170 | K99: 2563 | L99: 775 | M99: 3210 | N99: 938 | O99: 130 | P99: 530 | Q99: 650 | R99: 490 | S99: 363 | T99: 939 | U99: 281 | V99: 1318.0446 | W99: 26.9 | X99: 0.055391439 | Y99: 501 | Z99: 1318 | AA99: 705 | AB99: 479 | AC99: 709 | AD99: 1197 | AE99: 875 | AF99: 1156 | AG99: 555 | AH99: 1058 | AI99: 1074 | AJ99: 784 | AK99: 1363 | AL99: 1530 | AM99: 1108 | AN99: 419 | AO99: 725 | AP99: 486 | AQ99: 2228.8841 | AR99: 364.09024 | AS99: 260.85707 | AT99: 303.16862 | AU99: 951 | AV99: 3384 | AW99: 1466 | AX99: 12523 | AY99: 3613 | AZ99: 417 | BA99: 712 | BB99: 1734 | BC99: 394 | BD99: 1741 | BE99: 228 | BF99: 1362 | BG99: 6971 | BH99: 2073 | BI99: 8223 | BJ99: 473 | BK99: 2660 | BL99: 617 | BM99: 520 | BN99: 525 | BO99: 3452 | BP99: 1043 | BQ99: 163 | BR99: 17 | BS99: 2814 | BT99: 0 | BU99: 3006 | BV99: 306 | BW99: 1199 | BX99: 0 | BY99: 99200 | BZ99: 0 | CA99: 0 | CB99: 0 | CC99: 0 | CD99: 0 | CE99: 0 | CF99: 0 | CG99: 99200
A100: R32 | B100: Outros subsídios à produção | C100: 95 | D100: -9261 | E100: -119 | F100: -37 | G100: -61 | H100: 0 | I100: -24 | J100: 0 | K100: -82 | L100: -114 | M100: -105 | N100: -32 | O100: 0 | P100: -21 | Q100: 0 | R100: 0 | S100: -31 | T100: -80 | U100: 0 | V100: -146.99382 | W100: -3 | X100: -0.006177484 | Y100: -124 | Z100: -30 | AA100: 0 | AB100: 0 | AC100: -21 | AD100: -120 | AE100: -99 | AF100: -53 | AG100: -28 | AH100: -67 | AI100: 0 | AJ100: -74 | AK100: -195 | AL100: -219 | AM100: -180 | AN100: -51 | AO100: -28 | AP100: 0 | AQ100: -84.015586 | AR100: -13.724022 | AS100: -9.8327498 | AT100: -11.427642 | AU100: -31 | AV100: -364 | AW100: -29 | AX100: -618 | AY100: -1629 | AZ100: 0 | BA100: -25 | BB100: -49 | BC100: 0 | BD100: 0 | BE100: 0 | BF100: 0 | BG100: -64 | BH100: 0 | BI100: 0 | BJ100: 0 | BK100: 0 | BL100: -374 | BM100: 0 | BN100: -155 | BO100: -49 | BP100: 0 | BQ100: 0 | BR100: 0 | BS100: 0 | BT100: 0 | BU100: -121 | BV100: 0 | BW100: 0 | BX100: 0 | BY100: -15033 | BZ100: 0 | CA100: 0 | CB100: 0 | CC100: 0 | CD100: 0 | CE100: 0 | CF100: 0 | CG100: -15033
A101: N1 | B101: Valor adicionado bruto ( PIB ) | C101: 96 | D101: 209511 | E101: 71692 | F101: 28408 | G101: 8151 | H101: 100760 | I101: 45134 | J101: 7024 | K101: 45831 | L101: 8424 | M101: 66028 | N101: 22080 | O101: 3582 | P101: 16047 | Q101: 28404 | R101: 15570 | S101: 11759 | T101: 31780 | U101: 10260 | V101: 41168.404 | W101: 1052.425 | X101: 115.17124 | Y101: 11524 | Z101: 26696 | AA101: 15252 | AB101: 10920 | AC101: 34789 | AD101: 29645 | AE101: 24757 | AF101: 34177 | AG101: 15846 | AH101: 33343 | AI101: 15600 | AJ101: 20034 | AK101: 37543 | AL101: 23213 | AM101: 30066 | AN101: 10679 | AO101: 32728 | AP101: 28515 | AQ101: 77305.039 | AR101: 11952.857 | AS101: 8979.4769 | AT101: 22856.628 | AU101: 50339 | AV101: 243280 | AW101: 97878 | AX101: 685169 | AY101: =AY98+AY99+AY100 -> 165215 | AZ101: 10075 | BA101: 9954 | BB101: 79420 | BC101: 14822 | BD101: 130511 | BE101: 8612 | BF101: 16988 | BG101: 69944 | BH101: 110549 | BI101: 422662 | BJ101: 588036 | BK101: 156875 | BL101: 38999 | BM101: 38814 | BN101: 30151 | BO101: 176659 | BP101: 35115 | BQ101: 616023 | BR101: 295133 | BS101: 102884 | BT101: 134229 | BU101: 169778 | BV101: 22984 | BW101: 86399 | BX101: 74451 | BY101: 6011150 | BZ101: 0 | CA101: 0 | CB101: 0 | CC101: 0 | CD101: 0 | CE101: 0 | CF101: 0 | CG101: 6011150
A102: P10 | B102: VALOR DA PRODUÇÃO | C102: 97 | D102: 398037 | E102: 151959 | F102: 37870 | G102: 20011 | H102: 225938 | I102: 92326 | J102: 18273 | K102: 292406 | L102: 51555 | M102: 324943 | N102: 78544 | O102: 15694 | P102: 54793 | Q102: 66432 | R102: 43848 | S102: 32687 | T102: 109595 | U102: 21333 | V102: 433811.27 | W102: 10385.862 | X102: 3303.8714 | Y102: 54637 | Z102: 179506 | AA102: 88308 | AB102: 50176 | AC102: 76244 | AD102: 121217 | AE102: 83888 | AF102: 150065 | AG102: 73148 | AH102: 101954 | AI102: 103544 | AJ102: 79945 | AK102: 129313 | AL102: 187915 | AM102: 105992 | AN102: 41813 | AO102: 75235 | AP102: 79968 | AQ102: 231741.36 | AR102: 34484.753 | AS102: 16753.736 | AT102: 40159.155 | AU102: 82220 | AV102: 552073 | AW102: 175093 | AX102: 1120579 | AY102: =AY101+AY88 -> 378084.26 | AZ102: 23042 | BA102: 44807 | BB102: 138844 | BC102: 27787 | BD102: 276938 | BE102: 17903 | BF102: 43874 | BG102: 166879 | BH102: 167410 | BI102: 649009 | BJ102: 639752 | BK102: 228613 | BL102: 62891 | BM102: 104820 | BN102: 48479 | BO102: 261715 | BP102: 43096 | BQ102: 858764 | BR102: 351095 | BS102: 143437 | BT102: 202716 | BU102: 302873 | BV102: 40366 | BW102: 171919 | BX102: 74451 | BY102: 12010010 | BZ102: 0 | CA102: 0 | CB102: 0 | CC102: 0 | CD102: 0 | CE102: 0 | CF102: 0 | CG102: 12010010
B103: Fator trabalho (ocupações) | C103: 98 | D103: 6687599 | E103: 5891326 | F103: 801096 | G103: 118276 | H103: 50144 | I103: 35440 | J103: 28949 | K103: 765202 | L103: 156442 | M103: 1285134 | N103: 190956 | O103: 17784 | P103: 632157 | Q103: 1676586 | R103: 468535 | S103: 376397 | T103: 201777 | U103: 180593 | V103: 18842.968 | W103: 2617.3805 | X103: 260.652 | Y103: 98255 | Z103: 92285 | AA103: 85311 | AB103: 137454 | AC103: 104114 | AD103: 444627 | AE103: 563545 | AF103: 122810 | AG103: 100208 | AH103: 669483 | AI103: 127233 | AJ103: 198332 | AK103: 378379 | AL103: 160623 | AM103: 305020 | AN103: 81338 | AO103: 744311 | AP103: 532601 | AQ103: 102497.99 | AR103: 16271.463 | AS103: 12467.512 | AT103: 27161.033 | AU103: 563905 | AV103: 7617875 | AW103: 2968849 | AX103: 16293655 | AY103: 4076625 | AZ103: 52733 | BA103: 60529 | BB103: 808476 | BC103: 438611 | BD103: 5622208 | BE103: 136112 | BF103: 166605 | BG103: 252106 | BH103: 752017 | BI103: 1241143 | BJ103: 466409 | BK103: 1887743 | BL103: 630552 | BM103: 613009 | BN103: 298455 | BO103: 4178701 | BP103: 781913 | BQ103: 4825230 | BR103: 4202039 | BS103: 2878667 | BT103: 2218572 | BU103: 3428002 | BV103: 1122849 | BW103: 4502808 | BX103: 6563436 | BY103: 104340275 | BZ103: 0 | CA103: 0 | CB103: 0 | CC103: 0 | CD103: 0 | CE103: 0 | CF103: 0 | CG103: 104340275

Sheet FM - C2
A1: (1) a matriz de fluxos em valores monetários Z, com os setores de valor adicionado e a demanda final;
A3: Valores correntes em 1 000 000 R$ | D3: S01 | E3: S02 | F3: S03 | G3: S04 | H3: S05 | I3: S06 | J3: S07 | K3: S08 | L3: S09 | M3: S10 | N3: S11 | O3: S12 | P3: S13 | Q3: S14 | R3: S15 | S3: S16 | T3: S17 | U3: S18 | V3: S19 | W3: S20 | X3: S21 | Y3: S22 | Z3: S23 | AA3: S24 | AB3: S25 | AC3: S26 | AD3: S27 | AE3: S28 | AF3: S29 | AG3: S30 | AH3: S31 | AI3: S32 | AJ3: S33 | AK3: S34 | AL3: S35 | AM3: S36 | AN3: S37 | AO3: S38 | AP3: S39 | AQ3: S40 | AR3: S41 | AS3: S42 | AT3: S43 | AU3: S44 | AV3: S45 | AW3: S46 | AX3: S47 | AY3: S48 | AZ3: S49 | BA3: S50 | BB3: S51 | BC3: S52 | BD3: S53 | BE3: S54 | BF3: S55 | BG3: S56 | BH3: S57 | BI3: S58 | BJ3: S59 | BK3: S60 | BL3: S61 | BM3: S62 | BN3: S63 | BO3: S64 | BP3: S65 | BQ3: S66 | BR3: S67 | BS3: S68 | BT3: S69 | BU3: S70 | BV3: S71 | BW3: S72 | BX3: S73
A4: Matriz de usos setor x setor | D4: Agricultura, inclusive o apoio à agricultura e a pós-colheita | E4: Pecuária, inclusive o apoio à pecuária | F4: Produção florestal; pesca e aquicultura | G4: Extração de carvão mineral e de minerais não-metálicos | H4: Extração de petróleo e gás, inclusive as atividades de apoio | I4: Extração de minério de ferro, inclusive beneficiamentos e a aglomeração | J4: Extração de minerais metálicos não-ferrosos, inclusive beneficiamentos | K4: Abate e produtos de carne, inclusive os produtos do laticínio e da pesca | L4: Fabricação e refino de açúcar | M4: Outros produtos alimentares | N4: Fabricação de bebidas | O4: Fabricação de produtos do fumo | P4: Fabricação de produtos têxteis | Q4: Confecção de artefatos do vestuário e acessórios | R4: Fabricação de calçados e de artefatos de couro | S4: Fabricação de produtos da madeira | T4: Fabricação de celulose, papel e produtos de papel | U4: Impressão e reprodução de gravações | V4: Derivados de petróleo | W4: Biodiesel | X4: Coquerias | Y4: Fabricação de biocombustíveis | Z4: Fabricação de químicos orgânicos e inorgânicos, resinas e elastômeros | AA4: Fabricação de defensivos, desinfestantes, tintas e químicos diversos | AB4: Fabricação de produtos de limpeza, cosméticos/perfumaria e higiene pessoal | AC4: Fabricação de produtos farmoquímicos e farmacêuticos | AD4: Fabricação de produtos de borracha e de material plástico | AE4: Fabricação de produtos de minerais não-metálicos | AF4: Produção de ferro-gusa/ferroligas, siderurgia e tubos de aço sem costura | AG4: Metalurgia de metais não-ferosos e a fundição de metais | AH4: Fabricação de produtos de metal, exceto máquinas e equipamentos | AI4: Fabricação de equipamentos de informática, produtos eletrônicos e ópticos | AJ4: Fabricação de máquinas e equipamentos elétricos | AK4: Fabricação de máquinas e equipamentos mecânicos | AL4: Fabricação de automóveis, caminhões e ônibus, exceto peças | AM4: Fabricação de peças e acessórios para veículos automotores | AN4: Fabricação de outros equipamentos de transporte, exceto veículos automotores | AO4: Fabricação de móveis e de produtos de indústrias diversas | AP4: Manutenção, reparação e instalação de máquinas e equipamentos | AQ4: Geração centralizada de energia elétrica | AR4: Geração distribuída de energia elétrica | AS4: Transmissão | AT4: Gás Natural | AU4: Água, esgoto e gestão de resíduos | AV4: Construção | AW4: Comércio e reparação de veículos automotores e motocicletas | AX4: Comércio por atacado e a varejo, exceto veículos automotores | AY4: Transporte terrestre | AZ4: Transporte aquaviário | BA4: Transporte aéreo | BB4: Armazenamento, atividades auxiliares dos transportes e correio | BC4: Alojamento | BD4: Alimentação | BE4: Edição e edição integrada à impressão | BF4: Atividades de televisão, rádio, cinema e gravação/edição de som e imagem | BG4: Telecomunicações | BH4: Desenvolvimento de sistemas e outros serviços de informação | BI4: Intermediação financeira, seguros e previdência complementar | BJ4: Atividades imobiliárias | BK4: Atividades jurídicas, contábeis, consultoria e sedes de empresas | BL4: Serviços de arquitetura, engenharia, testes/análises técnicas e P & D | BM4: Outras atividades profissionais, científicas e técnicas | BN4: Aluguéis não-imobiliários e gestão de ativos de propriedade intelectual | BO4: Outras atividades administrativas e serviços complementares | BP4: Atividades de vigilância, segurança e investigação | BQ4: Administração pública, defesa e seguridade social | BR4: Educação pública | BS4: Educação privada | BT4: Saúde pública | BU4: Saúde privada | BV4: Atividades artísticas, criativas e de espetáculos | BW4: Organizações associativas e outros serviços pessoais | BX4: Serviços domésticos | BY4: Consumo Intermediário total | BZ4: Exportação de bens e serviços | CA4: Consumo do governo | CB4: Consumo das ISFLSF | CC4: Consumo das famílias | CD4: Formação bruta de capital fixo | CE4: Variação de estoque | CF4: Demanda final | CG4: Demanda total | CI4: Proporção Demanda Final / Demanda total
B5: Número identificador | C5: 0 | D5: 1 | E5: 2 | F5: 3 | G5: 4 | H5: 5 | I5: 6 | J5: 7 | K5: 8 | L5: 9 | M5: 10 | N5: 11 | O5: 12 | P5: 13 | Q5: 14 | R5: 15 | S5: 16 | T5: 17 | U5: 18 | V5: 19 | W5: 20 | X5: 21 | Y5: 22 | Z5: 23 | AA5: 24 | AB5: 25 | AC5: 26 | AD5: 27 | AE5: 28 | AF5: 29 | AG5: 30 | AH5: 31 | AI5: 32 | AJ5: 33 | AK5: 34 | AL5: 35 | AM5: 36 | AN5: 37 | AO5: 38 | AP5: 39 | AQ5: 40 | AR5: 41 | AS5: 42 | AT5: 43 | AU5: 44 | AV5: 45 | AW5: 46 | AX5: 47 | AY5: 48 | AZ5: 49 | BA5: 50 | BB5: 51 | BC5: 52 | BD5: 53 | BE5: 54 | BF5: 55 | BG5: 56 | BH5: 57 | BI5: 58 | BJ5: 59 | BK5: 60 | BL5: 61 | BM5: 62 | BN5: 63 | BO5: 64 | BP5: 65 | BQ5: 66 | BR5: 67 | BS5: 68 | BT5: 69 | BU5: 70 | BV5: 71 | BW5: 72 | BX5: 73 | BY5: 74 | BZ5: 75 | CA5: 76 | CB5: 77 | CC5: 78 | CD5: 79 | CE5: 80 | CF5: 81 | CG5: 82
A6: S01 | B6: Agricultura, inclusive o apoio à agricultura e a pós-colheita | C6: 1 | D6: 8170.3586 | E6: 5290.2246 | F6: 156.75542 | G6: 1.8265937 | H6: 9.8692679 | I6: 1.1434984 | J6: 1.7841451 | K6: 7264.3074 | L6: 28021.78 | M6: 76458.432 | N6: 2089.3011 | O6: 4889.0335 | P6: 5526.2619 | Q6: 518.70182 | R6: 6.6028531 | S6: 90.994169 | T6: 172.72948 | U6: 0.25638423 | V6: 8.6760449 | W6: 0.051985351 | X6: 0.041880586 | Y6: 22484.79 | Z6: 15.129223 | AA6: 18.049511 | AB6: 2.2091675 | AC6: 13.484794 | AD6: 38.146982 | AE6: 14.418004 | AF6: 42.241869 | AG6: 26.216602 | AH6: 2.7665426 | AI6: 0.27528051 | AJ6: 0.30007581 | AK6: 0.76078595 | AL6: 0.62121565 | AM6: 0.40229091 | AN6: 0.52416479 | AO6: 10.45024 | AP6: 0.065167124 | AQ6: 0.47598929 | AR6: 0.077753282 | AS6: 0.055707325 | AT6: 0.062671933 | AU6: 28.709259 | AV6: 402.52785 | AW6: 2.6558165 | AX6: 12090.688 | AY6: 0.96387781 | AZ6: 0.028456625 | BA6: 0.29297865 | BB6: 12.456639 | BC6: 277.13534 | BD6: 4385.9634 | BE6: 0.088943908 | BF6: 0.61952657 | BG6: 44.855835 | BH6: 2.1532612 | BI6: 14.762971 | BJ6: 20.40651 | BK6: 7.4743084 | BL6: 12.024632 | BM6: 0.80278958 | BN6: 0.68757086 | BO6: 133.6114 | BP6: 0.22205855 | BQ6: 947.57032 | BR6: 357.35736 | BS6: 43.808221 | BT6: 354.48805 | BU6: 180.63426 | BV6: 2.8571215 | BW6: 249.91177 | BX6: 0 | BY6: 180926.42 | BZ6: 150718.72 | CA6: 48.304678 | CB6: 0 | CC6: 71191.699 | CD6: 3188.2578 | CE6: -8036.3973 | CF6: 217110.58 | CG6: 398037 | CI6: =CF6/CG6 -> 0.54545327
A7: S02 | B7: Pecuária, inclusive o apoio à pecuária | C7: 2 | D7: 1004.9599 | E7: 6106.8111 | F7: 183.36264 | G7: 3.7251917 | H7: 22.939 | I7: 1.9494384 | J7: 3.2441343 | K7: 84046.279 | L7: 152.99908 | M7: 4376.6755 | N7: 64.457872 | O7: 192.81143 | P7: 250.2414 | Q7: 190.38282 | R7: 6.6377087 | S7: 143.03866 | T7: 239.09947 | U7: 0.46679488 | V7: 0.72657442 | W7: 0.018633166 | X7: 0.0001190597 | Y7: 178.77565 | Z7: 46.126672 | AA7: 7.8961205 | AB7: 5.0532195 | AC7: 5.4165196 | AD7: 52.888428 | AE7: 56.619524 | AF7: 70.6231 | AG7: 49.444454 | AH7: 2.5281526 | AI7: 0.71683903 | AJ7: 0.95724033 | AK7: 1.7317397 | AL7: 1.242744 | AM7: 0.99247143 | AN7: 0.87514563 | AO7: 7.2734053 | AP7: 0.23085892 | AQ7: 0.79136222 | AR7: 0.12926974 | AS7: 0.092616943 | AT7: 0.16790002 | AU7: 5.6993907 | AV7: 751.8631 | AW7: 3.5113748 | AX7: 386.78199 | AY7: 1.0736839 | AZ7: 0.037829304 | BA7: 0.34145151 | BB7: 22.136468 | BC7: 331.24359 | BD7: 1919.459 | BE7: 0.21618546 | BF7: 1.1913409 | BG7: 80.686603 | BH7: 4.2899018 | BI7: 25.488379 | BJ7: 38.429739 | BK7: 6.829628 | BL7: 14.52577 | BM7: 6.4682792 | BN7: 1.1312263 | BO7: 36.689298 | BP7: 0.34850966 | BQ7: 301.70844 | BR7: 120.20425 | BS7: 17.204426 | BT7: 110.89112 | BU7: 110.42372 | BV7: 3.3228892 | BW7: 37.971527 | BX7: 0 | BY7: 101821.57 | BZ7: 7635.5157 | CA7: 3.1875319 | CB7: 0 | CC7: 27053.775 | CD7: 16625.08 | CE7: -1180.1272 | CF7: 50137.431 | CG7: 151959 | CI7: =CF7/CG7 -> 0.32994052
A8: S03 | B8: Produção florestal; pesca e aquicultura | C8: 3 | D8: 1414.9162 | E8: 1437.2819 | F8: 2063.4117 | G8: 1.7907537 | H8: 1.8236877 | I8: 0.17010573 | J8: 0.24112751 | K8: 1830.067 | L8: 0.62916373 | M8: 261.16769 | N8: 13.874288 | O8: 13.085165 | P8: 25.024372 | Q8: 8.2471144 | R8: 6.78895 | S8: 1995.4595 | T8: 3242.7461 | U8: 0.035396002 | V8: 0.056630047 | W8: 0.0014522904 | X8: 9.2796503e-06 | Y8: 3.6633906 | Z8: 162.13204 | AA8: 2.8177035 | AB8: 0.084317617 | AC8: 0.12671282 | AD8: 713.86171 | AE8: 59.563969 | AF8: 910.44283 | AG8: 3.7053405 | AH8: 5.5140517 | AI8: 0.069501986 | AJ8: 0.088522362 | AK8: 0.17941951 | AL8: 0.11471484 | AM8: 0.093657764 | AN8: 0.076952408 | AO8: 2.773387 | AP8: 0.02522399 | AQ8: 0.094589682 | AR8: 0.015451311 | AS8: 0.011070287 | AT8: 0.019459657 | AU8: 0.4257136 | AV8: 759.42361 | AW8: 0.27333371 | AX8: 161.92523 | AY8: 0.099740228 | AZ8: 0.0030144069 | BA8: 0.027363157 | BB8: 1.6585272 | BC8: 42.674553 | BD8: 549.53668 | BE8: 0.021951251 | BF8: 0.10959413 | BG8: 5.9766224 | BH8: 0.36575555 | BI8: 1.9402982 | BJ8: 2.9162219 | BK8: 0.52073673 | BL8: 3.7816158 | BM8: 0.083967239 | BN8: 0.095237422 | BO8: 2.6303824 | BP8: 0.029566698 | BQ8: 91.342914 | BR8: 66.866054 | BS8: 8.8889308 | BT8: 63.403735 | BU8: 19.813852 | BV8: 0.24397311 | BW8: 2.9434756 | BX8: 0 | BY8: 15970.315 | BZ8: 3068.1586 | CA8: 2.4427056 | CB8: 0 | CC8: 17611.77 | CD8: 1054.003 | CE8: 163.3106 | CF8: 21899.685 | CG8: 37870 | CI8: =CF8/CG8 -> 0.57828585
A9: S04 | B9: Extração de carvão mineral e de minerais não-metálicos | C9: 4 | D9: 154.57131 | E9: 418.65628 | F9: 13.284636 | G9: 255.38746 | H9: 731.23872 | I9: 0.30874708 | J9: 1.3587158 | K9: 53.244166 | L9: 8.1587147 | M9: 279.65589 | N9: 16.421368 | O9: 0.065622521 | P9: 0.97438319 | Q9: 0.29823967 | R9: 0.94713613 | S9: 0.22325809 | T9: 18.581952 | U9: 0.14003746 | V9: 6.1948655 | W9: 0.1589928 | X9: 0.0058538919 | Y9: 219.10581 | Z9: 2854.8663 | AA9: 68.702101 | AB9: 8.0050703 | AC9: 1.8960083 | AD9: 6.7281211 | AE9: 4463.2487 | AF9: 1496.018 | AG9: 337.50822 | AH9: 3.5700793 | AI9: 0.34796092 | AJ9: 35.919486 | AK9: 2.5200509 | AL9: 18.623404 | AM9: 34.401273 | AN9: 1.7813222 | AO9: 31.983519 | AP9: 2.7992514 | AQ9: 235.19416 | AR9: 5.7714331 | AS9: 1.184596 | AT9: 1.2563515 | AU9: 356.51608 | AV9: 5769.238 | AW9: 2.9175716 | AX9: 79.436083 | AY9: 0.65802409 | AZ9: 0.02811291 | BA9: 0.057457623 | BB9: 4.3639196 | BC9: 2.4382302 | BD9: 15.584106 | BE9: 0.087448574 | BF9: 0.1645093 | BG9: 0.76492018 | BH9: 0.61648428 | BI9: 1.6296091 | BJ9: 369.75982 | BK9: 1.5956916 | BL9: 1.1474393 | BM9: 0.42774142 | BN9: 0.35090323 | BO9: 2.106388 | BP9: 0.086702237 | BQ9: 71.223802 | BR9: 16.960069 | BS9: 1.5619518 | BT9: 6.8222989 | BU9: 5.5002185 | BV9: 1.1191405 | BW9: 4.310632 | BX9: 0 | BY9: 18508.781 | BZ9: 1808.1263 | CA9: 0.074826886 | CB9: 0 | CC9: 199.54565 | CD9: 9.7663346 | CE9: -515.2941 | CF9: 1502.2191 | CG9: 20011 | CI9: =CF9/CG9 -> 0.075069665
A10: S05 | B10: Extração de petróleo e gás, inclusive as atividades de apoio | C10: 5 | D10: 21.840529 | E10: 15.400401 | F10: 0.88883243 | G10: 2.8557716 | H10: 6630.1612 | I10: 276.15336 | J10: 28.805251 | K10: 63.705839 | L10: 0.44529788 | M10: 591.27168 | N10: 106.02011 | O10: 0.12079151 | P10: 91.397968 | Q10: 0.98598288 | R10: 1.5852201 | S10: 39.944558 | T10: 541.2167 | U10: 0.14283782 | V10: 106597.07 | W10: 2746.8599 | X10: 590.10146 | Y10: 1.2543756 | Z10: 1369.8245 | AA10: 67.887327 | AB10: 24.388558 | AC10: 28.616612 | AD10: 80.815094 | AE10: 444.90473 | AF10: 358.13112 | AG10: 243.1048 | AH10: 282.1276 | AI10: 1.128992 | AJ10: 26.624933 | AK10: 19.396171 | AL10: 62.055893 | AM10: 126.58879 | AN10: 1.6722904 | AO10: 2.9946627 | AP10: 6.2288933 | AQ10: 3962.6267 | AR10: 1.0026425 | AS10: 0.71835594 | AT10: 5204.7213 | AU10: 522.87686 | AV10: 571.58375 | AW10: 9.6259108 | AX10: 157.08909 | AY10: 72.420509 | AZ10: 0.79119726 | BA10: 0.27180433 | BB10: 47.629023 | BC10: 3.4384093 | BD10: 49.277023 | BE10: 0.46020694 | BF10: 1.2321138 | BG10: 87.263751 | BH10: 4.8051068 | BI10: 13.428733 | BJ10: 6.8459631 | BK10: 13.309644 | BL10: 55.849417 | BM10: 3.1144653 | BN10: 5.7667873 | BO10: 9.2018492 | BP10: 0.72124886 | BQ10: 1045.7362 | BR10: 8.0402548 | BS10: 12.284845 | BT10: 1.4955079 | BU10: 7.5123371 | BV10: 9.5743714 | BW10: 21.701482 | BX10: 0 | BY10: 133407.14 | BZ10: 92727.09 | CA10: 0 | CB10: 0 | CC10: 602.27835 | CD10: 11369.449 | CE10: -12167.956 | CF10: 92530.862 | CG10: 225938 | CI10: =CF10/CG10 -> 0.40954095
A11: S06 | B11: Extração de minério de ferro, inclusive beneficiamentos e a aglomeração | C11: 6 | D11: 0.13674266 | E11: 0.077076579 | F11: 0.0079907095 | G11: 0.02196498 | H11: 2.3512303 | I11: 1793.5447 | J11: 45.052166 | K11: 0.48557035 | L11: 0.032457224 | M11: 0.34478482 | N11: 0.27770406 | O11: 0.063359672 | P11: 0.043394837 | Q11: 0.095809719 | R11: 0.10896933 | S11: 0.074421837 | T11: 0.14841067 | U11: 0.014610975 | V11: 0.14103175 | W11: 0.0036167913 | X11: 2.3110087e-05 | Y11: 0.017588449 | Z11: 0.34414227 | AA11: 0.11931618 | AB11: 0.21383963 | AC11: 0.70292247 | AD11: 0.20161083 | AE11: 106.29352 | AF11: 16914.009 | AG11: 123.08645 | AH11: 0.096515193 | AI11: 0.2311134 | AJ11: 0.55081086 | AK11: 4.5165857 | AL11: 1.1407709 | AM11: 0.66480908 | AN11: 0.23246828 | AO11: 0.11436779 | AP11: 2.6358292 | AQ11: 0.28979805 | AR11: 0.047338775 | AS11: 0.033916466 | AT11: 0.019881708 | AU11: 0.072340698 | AV11: 1.2898289 | AW11: 0.20090651 | AX11: 1.8876588 | AY11: 0.11844738 | AZ11: 0.04249387 | BA11: 0.0099650457 | BB11: 0.14510725 | BC11: 0.043813445 | BD11: 0.31459912 | BE11: 0.020385269 | BF11: 0.020853743 | BG11: 0.29065394 | BH11: 0.36060677 | BI11: 0.19109174 | BJ11: 0.07465067 | BK11: 0.16290206 | BL11: 6.5571966 | BM11: 0.053040758 | BN11: 0.12392835 | BO11: 0.64194197 | BP11: 0.010178673 | BQ11: 0.14299228 | BR11: 0.052338503 | BS11: 0.14785893 | BT11: 0.091322143 | BU11: 0.22754425 | BV11: 0.11034237 | BW11: 0.13327856 | BX11: 0 | BY11: 19012.127 | BZ11: 65510.697 | CA11: 0.014070934 | CB11: 0 | CC11: 7.116125 | CD11: 145.98411 | CE11: 7650.0619 | CF11: 73313.873 | CG11: 92326 | CI11: =CF11/CG11 -> 0.79407613
A12: S07 | B12: Extração de minerais metálicos não-ferrosos, inclusive beneficiamentos | C12: 7 | D12: 4.6695015 | E12: 2.628304 | F12: 0.12435658 | G12: 1.2402923 | H12: 68.177003 | I12: 10.656378 | J12: 810.56588 | K12: 6.0089169 | L12: 0.15093813 | M12: 12.972218 | N12: 1.4659626 | O12: 0.0030025647 | P12: 0.16470019 | Q12: 0.037493815 | R12: 0.28587826 | S12: 0.12078567 | T12: 5.8959539 | U12: 3.4978879 | V12: 0.045892973 | W12: 0.0011822536 | X12: 0.00021491581 | Y12: 0.99308581 | Z12: 30.317773 | AA12: 5.272019 | AB12: 1.7076522 | AC12: 0.54015883 | AD12: 7.8003983 | AE12: 52.370365 | AF12: 1602.2277 | AG12: 5411.8108 | AH12: 31.658929 | AI12: 2.4799909 | AJ12: 79.4302 | AK12: 12.403471 | AL12: 8.4362246 | AM12: 49.252453 | AN12: 12.92217 | AO12: 30.016131 | AP12: 5.5688269 | AQ12: 0.38191835 | AR12: 0.06238671 | AS12: 0.044697749 | AT12: 0.002747953 | AU12: 3.6386314 | AV12: 59.821666 | AW12: 0.56351331 | AX12: 3.5850876 | AY12: 0.16152433 | AZ12: 0 | BA12: 0.0036377033 | BB12: 0.073311621 | BC12: 0.0046298042 | BD12: 0.25629273 | BE12: 0.00037532059 | BF12: 0 | BG12: 0.012010259 | BH12: 0.01938281 | BI12: 0.015203035 | BJ12: 2.0032489 | BK12: 0.23876561 | BL12: 0.70972307 | BM12: 0.0016222907 | BN12: 0.0054421485 | BO12: 0.26001967 | BP12: 0 | BQ12: 0.51230206 | BR12: 0.19266821 | BS12: 0.00018766029 | BT12: 0.41110175 | BU12: 0.71872299 | BV12: 0 | BW12: 0.38814583 | BX12: 0 | BY12: 8348.0101 | BZ12: 11140.001 | CA12: 0 | CB12: 0 | CC12: 7.4490404 | CD12: 8.4306387 | CE12: -1230.8903 | CF12: 9924.9899 | CG12: 18273 | CI12: =CF12/CG12 -> 0.54315054
A13: S08 | B13: Abate e produtos de carne, inclusive os produtos do laticínio e da pesca | C13: 8 | D13: 73.15487 | E13: 2090.4666 | F13: 38.303224 | G13: 9.9476144 | H13: 19.441015 | I13: 17.034337 | J13: 3.2840564 | K13: 22154.159 | L13: 1.0823479 | M13: 2486.5336 | N13: 47.126808 | O13: 2.4639672 | P13: 7.0604126 | Q13: 8.6616937 | R13: 1473.7109 | S13: 5.5399254 | T13: 15.727026 | U13: 3.1952587 | V13: 23.045817 | W13: 0.59120438 | X13: 0.011154334 | Y13: 737.52755 | Z13: 29.649497 | AA13: 44.063117 | AB13: 1728.7212 | AC13: 13.395568 | AD13: 28.418666 | AE13: 9.9546155 | AF13: 10.274331 | AG13: 5.788068 | AH13: 65.983484 | AI13: 13.052513 | AJ13: 11.427341 | AK13: 65.885116 | AL13: 13.947594 | AM13: 8.0334682 | AN13: 3.9970415 | AO13: 12.233521 | AP13: 40.666301 | AQ13: 4.9078319 | AR13: 0.80169879 | AS13: 0.57438727 | AT13: 0.39508868 | AU13: 3.2880463 | AV13: 58.979781 | AW13: 7.2079814 | AX13: 448.87841 | AY13: 13.177598 | AZ13: 0.87761198 | BA13: 1.2127732 | BB13: 4.6743079 | BC13: 445.42571 | BD13: 17469.215 | BE13: 1.6282579 | BF13: 1.6628426 | BG13: 6.3279886 | BH13: 4.661158 | BI13: 8.4847063 | BJ13: 4.2251629 | BK13: 7.7048874 | BL13: 6.6234746 | BM13: 5.7445294 | BN13: 2.4002707 | BO13: 15.891834 | BP13: 0.73876873 | BQ13: 2176.6448 | BR13: 1294.0752 | BS13: 207.92015 | BT13: 1280.2889 | BU13: 750.19255 | BV13: 7.872699 | BW13: 194.08998 | BX13: 0 | BY13: 55760.354 | BZ13: 46170.634 | CA13: 72.403107 | CB13: 0 | CC13: 189902.01 | CD13: 408.57985 | CE13: 92.022182 | CF13: 236645.65 | CG13: 292406 | CI13: =CF13/CG13 -> 0.80930503
A14: S09 | B14: Fabricação e refino de açúcar | C14: 9 | D14: 53.525246 | E14: 87.091629 | F14: 2.3933686 | G14: 1.6267936 | H14: 330.37378 | I14: 22.21335 | J14: 3.8758144 | K14: 291.48502 | L14: 755.07055 | M14: 3193.1451 | N14: 671.87757 | O14: 0.80970769 | P14: 2.0182717 | Q14: 2.6748804 | R14: 2.0719631 | S14: 14.517455 | T14: 5.707496 | U14: 0.69458071 | V14: 7507.7582 | W14: 38.065829 | X14: 37.884553 | Y14: 641.94531 | Z14: 141.83333 | AA14: 414.07002 | AB14: 612.65487 | AC14: 355.93829 | AD14: 4.1415098 | AE14: 3.0130159 | AF14: 3.8189358 | AG14: 2.182539 | AH14: 17.070744 | AI14: 4.3963944 | AJ14: 6.2673357 | AK14: 94.892959 | AL14: 16.375697 | AM14: 2.8484954 | AN14: 3.8857596 | AO14: 3.4125174 | AP14: 59.620441 | AQ14: 4.5778112 | AR14: 0.74778963 | AS14: 0.53576336 | AT14: 0.18604367 | AU14: 10.534485 | AV14: 172.49428 | AW14: 139.72003 | AX14: 273.44868 | AY14: 351.88253 | AZ14: 3.0478343 | BA14: 9.5131123 | BB14: 24.925262 | BC14: 7.1586323 | BD14: 795.99698 | BE14: 2.2736976 | BF14: 4.3632644 | BG14: 12.172919 | BH14: 17.104176 | BI14: 62.695757 | BJ14: 8.9417937 | BK14: 62.340633 | BL14: 49.822366 | BM14: 19.535258 | BN14: 47.389975 | BO14: 66.916953 | BP14: 31.905779 | BQ14: 347.6269 | BR14: 93.441802 | BS14: 10.050684 | BT14: 71.418105 | BU14: 65.577576 | BV14: 9.0821778 | BW14: 75.349417 | BX14: 0 | BY14: 18266.028 | BZ14: 16586.094 | CA14: 0.75832747 | CB14: 0 | CC14: 16804.06 | CD14: 332.2654 | CE14: -434.20561 | CF14: 33288.972 | CG14: 51555 | CI14: =CF14/CG14 -> 0.64569823
A15: S10 | B15: Outros produtos alimentares | C15: 10 | D15: 1901.0055 | E15: 13289.225 | F15: 896.41033 | G15: 153.2433 | H15: 190.88615 | I15: 51.948534 | J15: 15.388239 | K15: 23451.189 | L15: 23.73499 | M15: 28439.3 | N15: 2077.0625 | O15: 14.848455 | P15: 56.298103 | Q15: 48.649656 | R15: 64.823663 | S15: 57.154409 | T15: 656.92772 | U15: 23.74503 | V15: 2090.5259 | W15: 13.734147 | X15: 9.9100746 | Y15: 3052.5007 | Z15: 488.08572 | AA15: 802.79043 | AB15: 1071.7383 | AC15: 229.29723 | AD15: 175.308 | AE15: 93.455962 | AF15: 91.502096 | AG15: 40.730426 | AH15: 88.811443 | AI15: 75.800275 | AJ15: 60.469387 | AK15: 109.61639 | AL15: 56.823494 | AM15: 43.043403 | AN15: 18.514591 | AO15: 81.249431 | AP15: 72.461506 | AQ15: 32.640495 | AR15: 5.3318544 | AS15: 3.8200747 | AT15: 1.9974554 | AU15: 32.438763 | AV15: 362.30878 | AW15: 131.80172 | AX15: 3488.1786 | AY15: 177.61548 | AZ15: 2.5711517 | BA15: 31.863844 | BB15: 38.202178 | BC15: 243.18735 | BD15: 12354.485 | BE15: 10.176693 | BF15: 10.564222 | BG15: 46.146675 | BH15: 27.97588 | BI15: 179.04353 | BJ15: 39.398785 | BK15: 74.566393 | BL15: 36.341617 | BM15: 66.42593 | BN15: 23.287125 | BO15: 77.880838 | BP15: 12.251409 | BQ15: 1527.907 | BR15: 1168.2631 | BS15: 166.10331 | BT15: 1598.3147 | BU15: 711.43383 | BV15: 52.378456 | BW15: 738.0151 | BX15: 0 | BY15: 103651.13 | BZ15: 40248.49 | CA15: 79.511138 | CB15: 0 | CC15: 177717.31 | CD15: 617.39769 | CE15: 2629.1666 | CF15: 221291.87 | CG15: 324943 | CI15: =CF15/CG15 -> 0.68101751
A16: S11 | B16: Fabricação de bebidas | C16: 11 | D16: 14.73899 | E16: 9.3559629 | F16: 0.76997094 | G16: 5.2965241 | H16: 13.258631 | I16: 7.7752004 | J16: 1.7552234 | K16: 397.9374 | L16: 1.2398412 | M16: 99.164789 | N16: 6639.8139 | O16: 1.607351 | P16: 4.5283349 | Q16: 5.5452055 | R16: 4.3324331 | S16: 4.1709141 | T16: 8.1110653 | U16: 1.6440958 | V16: 62.724309 | W16: 0.63813413 | X16: 0.24728806 | Y16: 3.2332953 | Z16: 10.807878 | AA16: 13.785349 | AB16: 11.285939 | AC16: 8.407027 | AD16: 10.372939 | AE16: 5.7335931 | AF16: 10.690565 | AG16: 3.6727054 | AH16: 20.532547 | AI16: 9.8421771 | AJ16: 9.681718 | AK16: 31.591531 | AL16: 12.546867 | AM16: 8.0829596 | AN16: 5.4079929 | AO16: 8.3460781 | AP16: 19.980903 | AQ16: 8.2460964 | AR16: 1.3470073 | AS16: 0.96508049 | AT16: 0.45259475 | AU16: 3.0293874 | AV16: 69.490475 | AW16: 10.121867 | AX16: 107.19138 | AY16: 17.00447 | AZ16: 0.45098489 | BA16: 8.1017402 | BB16: 6.2954672 | BC16: 450.04095 | BD16: 26011.353 | BE16: 1.2831512 | BF16: 1.6703356 | BG16: 6.6399483 | BH16: 5.1156866 | BI16: 98.337038 | BJ16: 6.2222205 | BK16: 12.41899 | BL16: 3.020191 | BM16: 4.3590942 | BN16: 2.9262015 | BO16: 13.385941 | BP16: 1.1279803 | BQ16: 100.9831 | BR16: 69.203497 | BS16: 17.627628 | BT16: 72.575288 | BU16: 174.85303 | BV16: 28.677202 | BW16: 19.690719 | BX16: 0 | BY16: 34822.866 | BZ16: 2978.2515 | CA16: 1.7119308 | CB16: 0 | CC16: 40937.66 | CD16: 99.164106 | CE16: -295.65319 | CF16: 43721.134 | CG16: 78544 | CI16: =CF16/CG16 -> 0.55664512
A17: S12 | B17: Fabricação de produtos do fumo | C17: 12 | D17: 1.8863692 | E17: 0.9809415 | F17: 0.089514122 | G17: 0.088027857 | H17: 2.1983798 | I17: 2.4823702 | J17: 0.38449654 | K17: 3.1242665 | L17: 0.08724313 | M17: 3.0183844 | N17: 0.69678189 | O17: 304.40931 | P17: 0.50326689 | Q17: 0.6927617 | R17: 0.57329707 | S17: 0.29665773 | T17: 0.77841528 | U17: 0.1475926 | V17: 1.9269422 | W17: 0.04941687 | X17: 0.00031575728 | Y17: 0.17235201 | Z17: 1.1070472 | AA17: 0.63432236 | AB17: 0.4849366 | AC17: 0.79277348 | AD17: 0.99845903 | AE17: 0.6455419 | AF17: 0.71252419 | AG17: 0.61963993 | AH17: 0.72265568 | AI17: 1.1712195 | AJ17: 1.1271924 | AK17: 9.9519577 | AL17: 1.7055668 | AM17: 0.71215732 | AN17: 0.50240734 | AO17: 0.67606475 | AP17: 6.042271 | AQ17: 0.46340185 | AR17: 0.075697113 | AS17: 0.054234156 | AT17: 0.031969707 | AU17: 0.18846967 | AV17: 5.1648107 | AW17: 0.45008789 | AX17: 3.6160293 | AY17: 1.1145936 | AZ17: 0.10844203 | BA17: 0.10146145 | BB17: 0.28571454 | BC17: 0.1431338 | BD17: 2.3330807 | BE17: 0.14060472 | BF17: 0.12207898 | BG17: 0.53625142 | BH17: 0.43983917 | BI17: 0.45998094 | BJ17: 0.24562702 | BK17: 0.37100818 | BL17: 1.3352302 | BM17: 0.34056163 | BN17: 0.16603915 | BO17: 1.6680395 | BP17: 0.047183572 | BQ17: 0.73080867 | BR17: 0.48670412 | BS17: 0.26664794 | BT17: 0.6912563 | BU17: 1.7783447 | BV17: 0.16768687 | BW17: 0.52694909 | BX17: 0 | BY17: 377.84581 | BZ17: 6460.6451 | CA17: 0.19900321 | CB17: 0 | CC17: 7980.5129 | CD17: 100.82736 | CE17: 773.96982 | CF17: 15316.154 | CG17: 15694 | CI17: =CF17/CG17 -> 0.97592419
... A23: S18 | B23: Impressão e reprodução de gravações | C23: 18 | D23: 13.339322 | E23: 3.1329614 | F23: 2.4387296 | G23: 0.41174963 | H23: 6.618274 | I23: 14.804113 | J23: 3.8701545 | K23: 85.18641 | L23: 11.087753 | M23: 114.1104 | N23: 221.79901 | O23: 5.1576768 | P23: 17.391981 | Q23: 19.532919 | R23: 12.239218 | S23: 28.701402 | T23: 196.93696 | U23: 996.48162 | V23: 8.9755705 | W23: 0.23020988 | X23: 0.0026149487 | Y23: 9.8994417 | Z23: 5.5179687 | AA23: 23.272288 | AB23: 16.904612 | AC23: 18.810886 | AD23: 61.632087 | AE23: 25.164052 | AF23: 18.243605 | AG23: 1.7709166 | AH23: 31.445401 | AI23: 194.60325 | AJ23: 13.867941 | AK23: 22.02342 | AL23: 28.005186 | AM23: 28.218372 | AN23: 5.3995951 | AO23: 39.211127 | AP23: 3.8478855 | AQ23: 22.346286 | AR23: 3.6502861 | AS23: 2.6152938 | AT23: 5.3059561 | AU23: 11.366928 | AV23: 71.515594 | AW23: 111.40669 | AX23: 6729.9426 | AY23: 56.857713 | AZ23: 1.7187504 | BA23: 33.680218 | BB23: 63.906745 | BC23: 10.455078 | BD23: 101.21687 | BE23: 1189.4141 | BF23: 211.9362 | BG23: 605.27134 | BH23: 538.32545 | BI23: 1458.0066 | BJ23: 330.83617 | BK23: 556.47461 | BL23: 226.79439 | BM23: 2104.0794 | BN23: 63.744541 | BO23: 1293.0832 | BP23: 2.9332676 | BQ23: 1054.3199 | BR23: 222.82942 | BS23: 41.71413 | BT23: 89.60547 | BU23: 103.38245 | BV23: 328.68184 | BW23: 344.79312 | BX23: 0 | BY23: 20302.498 | BZ23: 176.53574 | CA23: 0.26935788 | CB23: 0 | CC23: 1258.4005 | CD23: 40.666816 | CE23: -445.37025 | CF23: 1030.5022 | CG23: 21333 | CI23: =CF23/CG23 -> 0.048305546
A24: S19 | B24: Derivados de petróleo | C24: 19 | D24: 12522.633 | E24: 4529.1577 | F24: 691.20361 | G24: 1123.6606 | H24: 3436.5901 | I24: 4990.8882 | J24: 1243.4586 | K24: 3099.5979 | L24: 901.23197 | M24: 3777.556 | N24: 721.48778 | O24: 19.753752 | P24: 252.82664 | Q24: 105.14507 | R24: 196.64051 | S24: 273.71901 | T24: 2024.9338 | U24: 22.932426 | V24: 110832.26 | W24: 2852.6018 | X24: 913.18108 | Y24: 372.77801 | Z24: 10873.963 | AA24: 960.79738 | AB24: 470.12621 | AC24: 187.46502 | AD24: 1671.0652 | AE24: 2993.1382 | AF24: 1853.8129 | AG24: 2401.5901 | AH24: 412.73978 | AI24: 196.80683 | AJ24: 532.91945 | AK24: 438.35205 | AL24: 997.16559 | AM24: 366.59462 | AN24: 99.828542 | AO24: 264.11534 | AP24: 340.00152 | AQ24: 2403.6211 | AR24: 392.5614 | AS24: 281.25559 | AT24: 39.351035 | AU24: 1057.6584 | AV24: 6560.9162 | AW24: 959.18197 | AX24: 15601.925 | AY24: ='Fluxos Energia'!L17 -> 44920.555 | AZ24: 1664.3254 | BA24: 6710.9881 | BB24: 2004.3535 | BC24: 84.590636 | BD24: 2272.9757 | BE24: 23.045753 | BF24: 58.727795 | BG24: 89.357007 | BH24: 172.0103 | BI24: 598.21743 | BJ24: 101.5923 | BK24: 574.34079 | BL24: 407.75519 | BM24: 131.53973 | BN24: 708.48834 | BO24: 565.4077 | BP24: 427.26512 | BQ24: 2331.4275 | BR24: 334.3395 | BS24: 129.02051 | BT24: 80.289528 | BU24: 348.12058 | BV24: 142.96644 | BW24: 710.68955 | BX24: 0 | BY24: 300268.86 | BZ24: 21129.468 | CA24: 0 | CB24: 0 | CC24: 117714.64 | CD24: 1.4315587 | CE24: -5303.1362 | CF24: 133542.4 | CG24: 433811.27 | CI24: =CF24/CG24 -> 0.30783526
A25: S20 | B25: Biodiesel | C25: 20 | D25: 800.98709 | E25: 228.31395 | F25: 42.842108 | G25: 49.015375 | H25: 29.475244 | I25: 349.95762 | J25: 66.507065 | K25: 152.9996 | L25: 66.775695 | M25: 217.49628 | N25: 35.430375 | O25: 1.2241022 | P25: 0.087468574 | Q25: 0.041680128 | R25: 0.052176194 | S25: 0.70663884 | T25: 36.050745 | U25: 1.6231507 | V25: 4.9463166 | W25: 0.12740009 | X25: 0.022286903 | Y25: 830.99987 | Z25: 88.073226 | AA25: 26.38525 | AB25: 22.196834 | AC25: 15.228425 | AD25: 59.441331 | AE25: 62.487077 | AF25: 53.695921 | AG25: 14.697807 | AH25: 22.597382 | AI25: 14.780254 | AJ25: 16.201305 | AK25: 18.656442 | AL25: 66.238087 | AM25: 15.162336 | AN25: 6.2855793 | AO25: 16.047931 | AP25: 15.826858 | AQ25: 1.0453907 | AR25: 0.17033482 | AS25: 0.12203854 | AT25: 0.020696438 | AU25: 0.84012606 | AV25: 314.86489 | AW25: 14.792995 | AX25: 747.61132 | AY25: ='Fluxos Energia'!L18 -> 5181.1799 | AZ25: 0.84983695 | BA25: 32.271138 | BB25: 102.63218 | BC25: 1.5996283 | BD25: 1.1177232 | BE25: 0.21533387 | BF25: 0.75360202 | BG25: 0.52129845 | BH25: 0.78407177 | BI25: 2.7230786 | BJ25: 0.56868637 | BK25: 2.614969 | BL25: 2.1615132 | BM25: 0.55949069 | BN25: 8.141389 | BO25: 2.5664202 | BP25: 24.202501 | BQ25: 7.0732373 | BR25: 0.70014748 | BS25: 6.9915698 | BT25: 0.20172778 | BU25: 4.8962953 | BV25: 4.0101392 | BW25: 16.713675 | BX25: 0 | BY25: 9935.2017 | BZ25: 421.58378 | CA25: 0 | CB25: 0 | CC25: 43.723355 | CD25: 0.48795202 | CE25: -15.134627 | CF25: 450.66046 | CG25: 10385.862 | CI25: =CF25/CG25 -> 0.043391724
A26: S21 | B26: Coquerias | C26: 21 | D26: 3.0975998 | E26: 2.6317442 | F26: 0.25045315 | G26: 1.1454318 | H26: 63.643881 | I26: 25.411817 | J26: 4.7089033 | K26: 1.4120661 | L26: 0.022448833 | M26: 0.73106478 | N26: 0.31731661 | O26: 0.0042146732 | P26: 0.073819092 | Q26: 0.0018262356 | R26: 0.068517284 | S26: 0.41032361 | T26: 0.80412552 | U26: 0.0042380244 | V26: 111.54951 | W26: 15.910303 | X26: 1312.4123 | Y26: 0.0033455572 | Z26: 3.6823053 | AA26: 0.54571521 | AB26: 0.20430784 | AC26: 0.023745336 | AD26: 0.91186851 | AE26: 18.895062 | AF26: 1035.1843 | AG26: 27.184975 | AH26: 20.278543 | AI26: 0.11311616 | AJ26: 81.72658 | AK26: 26.20013 | AL26: 22.452422 | AM26: 41.159031 | AN26: 2.3537012 | AO26: 10.863704 | AP26: 29.206644 | AQ26: 4.8418515 | AR26: 0.79068717 | AS26: 0.56649785 | AT26: 0.080074453 | AU26: 0.42937544 | AV26: 3.1763959 | AW26: 2.2347958 | AX26: 8.1256855 | AY26: 81.92363 | AZ26: 0.47737029 | BA26: 20.979156 | BB26: 0.5103159 | BC26: 0.16350879 | BD26: 2.3645019 | BE26: 0.059745756 | BF26: 0.13976577 | BG26: 0.24553159 | BH26: 0.47845516 | BI26: 1.6627307 | BJ26: 0.27622412 | BK26: 1.5968385 | BL26: 0.93384181 | BM26: 0.32403957 | BN26: 1.3773637 | BO26: 1.5326188 | BP26: 0.31426729 | BQ26: 4.6276771 | BR26: 0.47313427 | BS26: 0.11307741 | BT26: 0.12320487 | BU26: 0.75881367 | BV26: 0.26476191 | BW26: 0.95884654 | BX26: 0 | BY26: 3008.5262 | BZ26: 51.537175 | CA26: 0 | CB26: 0 | CC26: 245.8714 | CD26: 0 | CE26: -2.0634016 | CF26: 295.34518 | CG26: 3303.8714 | CI26: =CF26/CG26 -> 0.089393667
A27: S22 | B27: Fabricação de biocombustíveis | C27: 22 | D27: 79.900399 | E27: 99.636051 | F27: 3.1945139 | G27: 2.506321 | H27: 632.5737 | I27: 6.4954438 | J27: 1.6063796 | K27: 227.81004 | L27: 193.42907 | M27: 910.61411 | N27: 183.16587 | O27: 0.19687255 | P27: 1.4072229 | Q27: 0.96640033 | R27: 1.1141634 | S27: 26.899323 | T27: 9.3848407 | U27: 0.67263277 | V27: 15110.474 | W27: 76.356762 | X27: 76.309221 | Y27: 457.97466 | Z27: 296.72565 | AA27: 299.30408 | AB27: 1246.3545 | AC27: 713.90218 | AD27: 7.757368 | AE27: 2.9343726 | AF27: 3.476092 | AG27: 1.4932503 | AH27: 31.020153 | AI27: 1.4933829 | AJ27: 3.8333237 | AK27: 25.744485 | AL27: 15.046529 | AM27: 2.8046129 | AN27: 1.1816601 | AO27: 3.5941609 | AP27: 16.582466 | AQ27: 6.1615524 | AR27: 1.0064952 | AS27: 0.72111623 | AT27: 0.14624502 | AU27: 19.763071 | AV27: 293.64415 | AW27: 274.54746 | AX27: 499.37374 | AY27: ='Fluxos Energia'!L19 -> 0 | AZ27: 4.3904134 | BA27: 18.370765 | BB27: 45.122455 | BC27: 9.6670383 | BD27: 267.1649 | BE27: 3.5708401 | BF27: 7.7979006 | BG27: 19.931212 | BH27: 31.08543 | BI27: 116.31031 | BJ27: 14.918811 | BK27: 120.40394 | BL27: 94.92334 | BM27: 37.083554 | BN27: 94.076893 | BO27: 113.06572 | BP27: 63.778652 | BQ27: 545.14846 | BR27: 77.529339 | BS27: 7.9860567 | BT27: 31.915945 | BU27: 89.58174 | BV27: 15.024298 | BW27: 141.68801 | BX27: 0 | BY27: 24543.173 | BZ27: 5351.6554 | CA27: 0.20439016 | CB27: 0 | CC27: 24299.633 | CD27: 72.643596 | CE27: 369.69064 | CF27: 30093.827 | CG27: 54637 | CI27: =CF27/CG27 -> 0.55079575
A28: S23 | B28: Fabricação de químicos orgânicos e inorgânicos, resinas e elastômeros | C28: 23 | D28: 45933.044 | E28: 4700.5044 | F28: 342.73136 | G28: 238.96792 | H28: 4857.5133 | I28: 340.81704 | J28: 131.04423 | K28: 458.64652 | L28: 172.19125 | M28: 1063.8134 | N28: 94.697046 | O28: 16.378012 | P28: 3539.8888 | Q28: 140.25019 | R28: 1473.9022 | S28: 677.61342 | T28: 4354.2764 | U28: 67.362735 | V28: 2393.0475 | W28: 61.872098 | X28: 98.627655 | Y28: 648.58313 | Z28: 32375.577 | AA28: 12475.943 | AB28: 4409.2644 | AC28: 1782.2172 | AD28: 16336.884 | AE28: 2295.3151 | AF28: 973.06272 | AG28: 908.00851 | AH28: 1236.0286 | AI28: 176.46663 | AJ28: 2291.5755 | AK28: 179.95359 | AL28: 154.70952 | AM28: 1135.6976 | AN28: 253.54153 | AO28: 1680.149 | AP28: 172.4995 | AQ28: 136.21436 | AR28: 22.25074 | AS28: 15.941825 | AT28: 1.9475205 | AU28: 656.55925 | AV28: 483.24644 | AW28: 95.956964 | AX28: 1195.4936 | AY28: 117.98955 | AZ28: 2.4453832 | BA28: 4.7189596 | BB28: 50.015835 | BC28: 21.034007 | BD28: 166.06271 | BE28: 6.5973101 | BF28: 11.591103 | BG28: 36.65003 | BH28: 29.675183 | BI28: 81.330392 | BJ28: 75.323321 | BK28: 83.229416 | BL28: 53.316175 | BM28: 26.321729 | BN28: 24.461215 | BO28: 117.98117 | BP28: 4.1900923 | BQ28: 83.0922 | BR28: 74.527759 | BS28: 72.118323 | BT28: 277.19833 | BU28: 554.07565 | BV28: 57.260419 | BW28: 364.80967 | BX28: 0 | BY28: 155646.29 | BZ28: 19441.066 | CA28: 11.449279 | CB28: 0 | CC28: 3542.3546 | CD28: 713.95055 | CE28: 150.8875 | CF28: 23859.708 | CG28: 179506 | CI28: =CF28/CG28 -> 0.13291872
A29: S24 | B29: Fabricação de defensivos, desinfestantes, tintas e químicos diversos | C29: 24 | D29: 23436.868 | E29: 2659.0458 | F29: 87.893459 | G29: 1560.7928 | H29: 575.39185 | I29: 277.1698 | J29: 112.62711 | K29: 839.4749 | L29: 34.24234 | M29: 2339.5946 | N29: 116.42229 | O29: 5.054892 | P29: 306.23554 | Q29: 43.171646 | R29: 206.63342 | S29: 705.30913 | T29: 1430.9481 | U29: 638.57582 | V29: 388.26299 | W29: 9.8737706 | X29: 2.8454792 | Y29: 164.27653 | Z29: 2006.7763 | AA29: 9284.6465 | AB29: 1704.2634 | AC29: 864.88759 | AD29: 2767.0057 | AE29: 906.56114 | AF29: 446.19847 | AG29: 91.701863 | AH29: 559.00558 | AI29: 194.65756 | AJ29: 204.95976 | AK29: 175.09466 | AL29: 497.86933 | AM29: 231.01984 | AN29: 111.28724 | AO29: 540.55535 | AP29: 671.10572 | AQ29: 126.61999 | AR29: 20.588789 | AS29: 14.748137 | AT29: 1.7755108 | AU29: 331.61133 | AV29: 7547.2977 | AW29: 879.46696 | AX29: 1715.188 | AY29: 224.13311 | AZ29: 0.97484303 | BA29: 3.4208214 | BB29: 54.346922 | BC29: 27.371451 | BD29: 87.89679 | BE29: 89.460215 | BF29: 113.90617 | BG29: 21.411489 | BH29: 17.569591 | BI29: 66.398663 | BJ29: 1157.331 | BK29: 41.75966 | BL29: 42.798939 | BM29: 35.716779 | BN29: 22.450403 | BO29: 1733.3356 | BP29: 2.7201007 | BQ29: 227.90157 | BR29: 255.68521 | BS29: 36.280846 | BT29: 668.46403 | BU29: 97.554513 | BV29: 37.181086 | BW29: 119.89123 | BX29: 0 | BY29: 73021.564 | BZ29: 8559.7078 | CA29: 16.412404 | CB29: 0 | CC29: 3234.4272 | CD29: 1022.6946 | CE29: 2453.0639 | CF29: 15286.306 | CG29: 88308 | CI29: =CF29/CG29 -> 0.17310216
A30: S25 | B30: Fabricação de produtos de limpeza, cosméticos/perfumaria e higiene pessoal | C30: 25 | D30: 765.32407 | E30: 124.11388 | F30: 4.1411188 | G30: 26.412863 | H30: 122.19349 | I30: 63.069815 | J30: 11.163088 | K30: 95.473773 | L30: 9.1511034 | M30: 192.91992 | N30: 34.513376 | O30: 3.2668038 | P30: 51.801739 | Q30: 35.766428 | R30: 26.440694 | S30: 30.120874 | T30: 123.11266 | U30: 22.783766 | V30: 124.1784 | W30: 2.0914554 | X30: 0.94011927 | Y30: 15.692139 | Z30: 448.56544 | AA30: 480.65157 | AB30: 924.76117 | AC30: 75.265261 | AD30: 144.47271 | AE30: 65.70168 | AF30: 37.957525 | AG30: 41.675918 | AH30: 317.05273 | AI30: 29.079181 | AJ30: 28.954047 | AK30: 43.497999 | AL30: 34.735923 | AM30: 37.306512 | AN30: 9.7057737 | AO30: 38.819059 | AP30: 24.596692 | AQ30: 18.204243 | AR30: 2.9736796 | AS30: 2.1305305 | AT30: 0.64633242 | AU30: 42.033847 | AV30: 195.92545 | AW30: 120.41574 | AX30: 1401.1009 | AY30: 203.90997 | AZ30: 5.5952137 | BA30: 1.1265728 | BB30: 68.884047 | BC30: 53.710386 | BD30: 82.249491 | BE30: 21.158267 | BF30: 34.420096 | BG30: 70.625038 | BH30: 17.722424 | BI30: 36.376816 | BJ30: 16.273949 | BK30: 190.59552 | BL30: 71.454878 | BM30: 199.62395 | BN30: 71.733306 | BO30: 1199.0863 | BP30: 1.6549959 | BQ30: 159.23256 | BR30: 119.92704 | BS30: 95.531753 | BT30: 94.289859 | BU30: 592.29432 | BV30: 110.02516 | BW30: 795.73452 | BX30: 0 | BY30: 10764.138 | BZ30: 3455.2589 | CA30: 35.713769 | CB30: 0 | CC30: 33581.624 | CD30: 524.80294 | CE30: 1814.3668 | CF30: 39411.766 | CG30: 50176 | CI30: =CF30/CG30 -> 0.78547047
A31: S26 | B31: Fabricação de produtos farmoquímicos e farmacêuticos | C31: 26 | D31: 443.97217 | E31: 1869.1641 | F31: 14.50969 | G31: 21.801575 | H31: 344.6502 | I31: 12.749822 | J31: 2.597445 | K31: 76.787091 | L31: 1.3569439 | M31: 285.83398 | N31: 11.02808 | O31: 1.351365 | P31: 11.481965 | Q31: 44.242044 | R31: 15.518909 | S31: 7.8798413 | T31: 21.62656 | U31: 2.9720983 | V31: 12.242891 | W31: 0.31444667 | X31: 0.020529487 | Y31: 7.4184149 | Z31: 150.799 | AA31: 375.00097 | AB31: 53.960868 | AC31: 3129.91 | AD31: 38.414583 | AE31: 12.782497 | AF31: 12.930878 | AG31: 7.8937147 | AH31: 12.581002 | AI31: 7.0458295 | AJ31: 9.0717901 | AK31: 23.978799 | AL31: 21.038799 | AM31: 8.1781439 | AN31: 2.5045049 | AO31: 38.129608 | AP31: 10.456296 | AQ31: 7.1915976 | AR31: 1.174754 | AS31: 0.8416674 | AT31: 0.57083644 | AU31: 6.7002784 | AV31: 38.494487 | AW31: 11.011735 | AX31: 350.93074 | AY31: 15.001965 | AZ31: 3.1854828 | BA31: 0.89327323 | BB31: 12.376355 | BC31: 5.1967773 | BD31: 57.999276 | BE31: 1.0528672 | BF31: 3.3242458 | BG31: 8.657511 | BH31: 9.9219242 | BI31: 18.970806 | BJ31: 10.232229 | BK31: 22.657947 | BL31: 38.805067 | BM31: 45.310747 | BN31: 20.785824 | BO31: 42.917219 | BP31: 1.2398896 | BQ31: 372.68889 | BR31: 319.37331 | BS31: 159.33675 | BT31: 3521.2986 | BU31: 8425.7841 | BV31: 17.096774 | BW31: 404.31236 | BX31: 0 | BY31: 21079.534 | BZ31: 3220.0471 | CA31: 5793.2844 | CB31: 0 | CC31: 40030.055 | CD31: 1351.8378 | CE31: 4769.2415 | CF31: 55164.466 | CG31: 76244 | CI31: =CF31/CG31 -> 0.72352534
